Workbook

Sheet parts
A1: partID | B1: label | C1: partType | D1: partDesc | E1: partInstr | F1: fKAliasID | G1: domain | H1: specimenSet | I1: compartmentSet | J1: group | K1: class | L1: nomenclature | M1: ontologyRef | N1: latExp | O1: mmaSet | P1: unitSet | Q1: aggregationScale | R1: aggregationSet | S1: qualityIndSet | T1: missingnessSet | U1: status | V1: firstReleased | W1: lastUpdated | X1: changes | Y1: protocolSteps | Z1: protocolStepsRequired | AA1: protocolStepsOrder | AB1: protocolRelationships | AC1: protocolRelationshipsRequired | AD1: protocolRelationshipsOrder | AE1: measures | AF1: measuresRequired | AG1: measuresOrder | AH1: measureSets | AI1: measureSetsRequired | AJ1: measureSetsOrder | AK1: datasets | AL1: datasetsRequired | AM1: datasetsOrder | AN1: sites | AO1: sitesRequired | AP1: sitesOrder | AQ1: samples | AR1: samplesRequired | AS1: samplesOrder | AT1: addresses | AU1: addressesRequired | AV1: addressesOrder | AW1: contacts | AX1: contactsRequired | AY1: contactsOrder | AZ1: organizations | BA1: organizationsRequired | BB1: organizationsOrder | BC1: instruments | BD1: instrumentsRequired | BE1: instrumentsOrder | BF1: polygons | BG1: polygonsRequired | BH1: polygonsOrder | BI1: languages | BJ1: languagesRequired | BK1: languagesOrder | BL1: translations | BM1: translationsRequired | BN1: translationsOrder | BO1: parts | BP1: partsRequired | BQ1: partsOrder | BR1: sets | BS1: setsRequired | BT1: setsOrder | BU1: qualityReports | BV1: qualityReportsRequired | BW1: qualityReportsOrder | BX1: sampleRelationships | BY1: sampleRelationshipsRequired | BZ1: sampleRelationshipsOrder | CA1: protocols | CB1: protocolsRequired | CC1: protocolsOrder | CD1: countries | CE1: countriesRequired | CF1: countriesOrder | CG1: zones | CH1: zonesRequired | CI1: zonesOrder | CJ1: wideNames | CK1: wideNamesRequired | CL1: wideNamesOrder | CM1: refLink | CN1: dataType | CO1: minValue | CP1: maxValue | CQ1: minLength | CR1: maxLength
A2: a1306s | B2: a1306s delta-variant gene target | C2: measurements | D2: a1306s delta-variant mutation gene target | E2: NA | F2: NA | G2: bio | H2: saSpecimenSet | I2: anyCompartmentSet | J2: sarsCov2 | K2: pcr | L2: naNomenclature | M2: NA | N2: NA | O2: NA | P2: geneticUnitSet | Q2: seeUnitAggScale | R2: otherAggrSet | S2: pcrQualitySet | T2: genMissingnessSet | U2: active | V2: 2.0.0 | W2: 2.0.0 | X2: added in V2.0.0 | Y2: input | Z2: NA | AA2: NA | AB2: NA | AC2: NA | AD2: NA | AE2: input | AF2: NA | AG2: NA | AH2: NA | AI2: NA | AJ2: NA | AK2: NA | AL2: NA | AM2: NA | AN2: NA | AO2: NA | AP2: NA | AQ2: NA | AR2: NA | AS2: NA | AT2: NA | AU2: NA | AV2: NA | AW2: NA | AX2: NA | AY2: NA | AZ2: NA | BA2: NA | BB2: NA | BC2: NA | BD2: NA | BE2: NA | BF2: NA | BG2: NA | BH2: NA | BI2: NA | BJ2: NA | BK2: NA | BL2: NA | BM2: NA | BN2: NA | BO2: NA | BP2: NA | BQ2: NA | BR2: NA | BS2: NA | BT2: NA | BU2: NA | BV2: NA | BW2: NA | BX2: NA | BY2: NA | BZ2: NA | CA2: NA | CB2: NA | CC2: NA | CD2: NA | CE2: NA | CF2: NA | CG2: NA | CH2: NA | CI2: NA | CJ2: input | CK2: NA | CL2: NA | CM2: NA | CN2: seeUnitData | CO2: seeUnitVal | CP2: seeUnitVal | CQ2: NA | CR2: NA
A3: a1918v | B3: a1918v delta-variant gene target | C3: measurements | D3: a1918v delta-variant mutation gene target | E3: NA | F3: NA | G3: bio | H3: saSpecimenSet | I3: anyCompartmentSet | J3: sarsCov2 | K3: pcr | L3: naNomenclature | M3: NA | N3: NA | O3: NA | P3: geneticUnitSet | Q3: seeUnitAggScale | R3: otherAggrSet | S3: pcrQualitySet | T3: genMissingnessSet | U3: active | V3: 2.0.0 | W3: 2.0.0 | X3: added in V2.0.0 | Y3: input | Z3: NA | AA3: NA | AB3: NA | AC3: NA | AD3: NA | AE3: input | AF3: NA | AG3: NA | AH3: NA | AI3: NA | AJ3: NA | AK3: NA | AL3: NA | AM3: NA | AN3: NA | AO3: NA | AP3: NA | AQ3: NA | AR3: NA | AS3: NA | AT3: NA | AU3: NA | AV3: NA | AW3: NA | AX3: NA | AY3: NA | AZ3: NA | BA3: NA | BB3: NA | BC3: NA | BD3: NA | BE3: NA | BF3: NA | BG3: NA | BH3: NA | BI3: NA | BJ3: NA | BK3: NA | BL3: NA | BM3: NA | BN3: NA | BO3: NA | BP3: NA | BQ3: NA | BR3: NA | BS3: NA | BT3: NA | BU3: NA | BV3: NA | BW3: NA | BX3: NA | BY3: NA | BZ3: NA | CA3: NA | CB3: NA | CC3: NA | CD3: NA | CE3: NA | CF3: NA | CG3: NA | CH3: NA | CI3: NA | CJ3: input | CK3: NA | CL3: NA | CM3: NA | CN3: seeUnitData | CO3: seeUnitVal | CP3: seeUnitVal | CQ3: NA | CR3: NA
A4: a2710t | B4: a2710t omicron-variant gene target | C4: measurements | D4: a2710t omicron-variant mutation gene target | E4: NA | F4: NA | G4: bio | H4: saSpecimenSet | I4: anyCompartmentSet | J4: sarsCov2 | K4: pcr | L4: naNomenclature | M4: NA | N4: NA | O4: NA | P4: geneticUnitSet | Q4: seeUnitAggScale | R4: otherAggrSet | S4: pcrQualitySet | T4: genMissingnessSet | U4: active | V4: 2.0.0 | W4: 2.0.0 | X4: added in V2.0.0 | Y4: input | Z4: NA | AA4: NA | AB4: NA | AC4: NA | AD4: NA | AE4: input | AF4: NA | AG4: NA | AH4: NA | AI4: NA | AJ4: NA | AK4: NA | AL4: NA | AM4: NA | AN4: NA | AO4: NA | AP4: NA | AQ4: NA | AR4: NA | AS4: NA | AT4: NA | AU4: NA | AV4: NA | AW4: NA | AX4: NA | AY4: NA | AZ4: NA | BA4: NA | BB4: NA | BC4: NA | BD4: NA | BE4: NA | BF4: NA | BG4: NA | BH4: NA | BI4: NA | BJ4: NA | BK4: NA | BL4: NA | BM4: NA | BN4: NA | BO4: NA | BP4: NA | BQ4: NA | BR4: NA | BS4: NA | BT4: NA | BU4: NA | BV4: NA | BW4: NA | BX4: NA | BY4: NA | BZ4: NA | CA4: NA | CB4: NA | CC4: NA | CD4: NA | CE4: NA | CF4: NA | CG4: NA | CH4: NA | CI4: NA | CJ4: input | CK4: NA | CL4: NA | CM4: NA | CN4: seeUnitData | CO4: seeUnitVal | CP4: seeUnitVal | CQ4: NA | CR4: NA
A5: a63t | B5: a63t omicron-variant gene target | C5: measurements | D5: a63t omicron-variant mutation gene target | E5: NA | F5: NA | G5: bio | H5: saSpecimenSet | I5: anyCompartmentSet | J5: sarsCov2 | K5: pcr | L5: naNomenclature | M5: NA | N5: NA | O5: NA | P5: geneticUnitSet | Q5: seeUnitAggScale | R5: otherAggrSet | S5: pcrQualitySet | T5: genMissingnessSet | U5: active | V5: 2.0.0 | W5: 2.0.0 | X5: added in V2.0.0 | Y5: input | Z5: NA | AA5: NA | AB5: NA | AC5: NA | AD5: NA | AE5: input | AF5: NA | AG5: NA | AH5: NA | AI5: NA | AJ5: NA | AK5: NA | AL5: NA | AM5: NA | AN5: NA | AO5: NA | AP5: NA | AQ5: NA | AR5: NA | AS5: NA | AT5: NA | AU5: NA | AV5: NA | AW5: NA | AX5: NA | AY5: NA | AZ5: NA | BA5: NA | BB5: NA | BC5: NA | BD5: NA | BE5: NA | BF5: NA | BG5: NA | BH5: NA | BI5: NA | BJ5: NA | BK5: NA | BL5: NA | BM5: NA | BN5: NA | BO5: NA | BP5: NA | BQ5: NA | BR5: NA | BS5: NA | BT5: NA | BU5: NA | BV5: NA | BW5: NA | BX5: NA | BY5: NA | BZ5: NA | CA5: NA | CB5: NA | CC5: NA | CD5: NA | CE5: NA | CF5: NA | CG5: NA | CH5: NA | CI5: NA | CJ5: input | CK5: NA | CL5: NA | CM5: NA | CN5: seeUnitData | CO5: seeUnitVal | CP5: seeUnitVal | CQ5: NA | CR5: NA
A6: a67v | B6: a67v omicron-variant gene target | C6: measurements | D6: a67v omicron-variant mutation gene target | E6: NA | F6: NA | G6: bio | H6: saSpecimenSet | I6: anyCompartmentSet | J6: sarsCov2 | K6: pcr | L6: naNomenclature | M6: NA | N6: NA | O6: NA | P6: geneticUnitSet | Q6: seeUnitAggScale | R6: otherAggrSet | S6: pcrQualitySet | T6: genMissingnessSet | U6: active | V6: 2.0.0 | W6: 2.0.0 | X6: added in V2.0.0 | Y6: input | Z6: NA | AA6: NA | AB6: NA | AC6: NA | AD6: NA | AE6: input | AF6: NA | AG6: NA | AH6: NA | AI6: NA | AJ6: NA | AK6: NA | AL6: NA | AM6: NA | AN6: NA | AO6: NA | AP6: NA | AQ6: NA | AR6: NA | AS6: NA | AT6: NA | AU6: NA | AV6: NA | AW6: NA | AX6: NA | AY6: NA | AZ6: NA | BA6: NA | BB6: NA | BC6: NA | BD6: NA | BE6: NA | BF6: NA | BG6: NA | BH6: NA | BI6: NA | BJ6: NA | BK6: NA | BL6: NA | BM6: NA | BN6: NA | BO6: NA | BP6: NA | BQ6: NA | BR6: NA | BS6: NA | BT6: NA | BU6: NA | BV6: NA | BW6: NA | BX6: NA | BY6: NA | BZ6: NA | CA6: NA | CB6: NA | CC6: NA | CD6: NA | CE6: NA | CF6: NA | CG6: NA | CH6: NA | CI6: NA | CJ6: input | CK6: NA | CL6: NA | CM6: NA | CN6: seeUnitData | CO6: seeUnitVal | CP6: seeUnitVal | CQ6: NA | CR6: NA
A7: a67vDel69Del70 | B7: Omicron Variant a67v del69 and del70 mutations | C7: measurements | D7: Omicron Variant a67v mutation mutation, and del 69 and del70 mutations co-occuring | E7: NA | F7: NA | G7: bio | H7: saSpecimenSet | I7: anyCompartmentSet | J7: omicronGrp | K7: pcr | L7: naNomenclature | M7: NA | N7: NA | O7: NA | P7: geneticUnitSet | Q7: seeUnitAggScale | R7: otherAggrSet | S7: pcrQualitySet | T7: genMissingnessSet | U7: active | V7: 2.2.0 | W7: 2.2.0 | X7: added in V2.2.0 | Y7: input | Z7: NA | AA7: NA | AB7: NA | AC7: NA | AD7: NA | AE7: input | AF7: NA | AG7: NA | AH7: NA | AI7: NA | AJ7: NA | AK7: NA | AL7: NA | AM7: NA | AN7: NA | AO7: NA | AP7: NA | AQ7: NA | AR7: NA | AS7: NA | AT7: NA | AU7: NA | AV7: NA | AW7: NA | AX7: NA | AY7: NA | AZ7: NA | BA7: NA | BB7: NA | BC7: NA | BD7: NA | BE7: NA | BF7: NA | BG7: NA | BH7: NA | BI7: NA | BJ7: NA | BK7: NA | BL7: NA | BM7: NA | BN7: NA | BO7: NA | BP7: NA | BQ7: NA | BR7: NA | BS7: NA | BT7: NA | BU7: NA | BV7: NA | BW7: NA | BX7: NA | BY7: NA | BZ7: NA | CA7: NA | CB7: NA | CC7: NA | CD7: NA | CE7: NA | CF7: NA | CG7: NA | CH7: NA | CI7: NA | CJ7: input | CK7: NA | CL7: NA | CM7: NA | CN7: seeUnitData | CO7: seeUnitVal | CP7: seeUnitVal | CQ7: NA | CR7: NA
A8: aas | B8: Atline Analyzer | C8: categories | D8: Atline analyzer with sampler. | E8: An atline analyzer with sampler. | F8: NA | G8: naDomain | H8: naSpecimenSet | I8: naCompartmentSet | J8: naGroup | K8: naClass | L8: naNomenclature | M8: NA | N8: NA | O8: NA | P8: naUnitSet | Q8: naAggrScale | R8: naAggrSet | S8: NA | T8: NA | U8: active | V8: 1.0.0 | W8: 2.0.0 | X8: description wording, structure | Y8: NA | Z8: NA | AA8: NA | AB8: NA | AC8: NA | AD8: NA | AE8: NA | AF8: NA | AG8: NA | AH8: NA | AI8: NA | AJ8: NA | AK8: NA | AL8: NA | AM8: NA | AN8: NA | AO8: NA | AP8: NA | AQ8: NA | AR8: NA | AS8: NA | AT8: NA | AU8: NA | AV8: NA | AW8: NA | AX8: NA | AY8: NA | AZ8: NA | BA8: NA | BB8: NA | BC8: input | BD8: NA | BE8: NA | BF8: NA | BG8: NA | BH8: NA | BI8: NA | BJ8: NA | BK8: NA | BL8: NA | BM8: NA | BN8: NA | BO8: NA | BP8: NA | BQ8: NA | BR8: NA | BS8: NA | BT8: NA | BU8: NA | BV8: NA | BW8: NA | BX8: NA | BY8: NA | BZ8: NA | CA8: NA | CB8: NA | CC8: NA | CD8: NA | CE8: NA | CF8: NA | CG8: NA | CH8: NA | CI8: NA | CJ8: NA | CK8: NA | CL8: NA | CM8: NA | CN8: varchar | CO8: NA | CP8: NA | CQ8: 0 | CR8: 30
A9: absHum | B9: Absolute humidity | C9: measurements | D9: A measure of the total mass of water vapour present in the air per volume of air. | E9: NA | F9: NA | G9: phy | H9: siSpecimenSet | I9: anyCompartmentSet | J9: siteFeat | K9: humid | L9: naNomenclature | M9: NA | N9: NA | O9: NA | P9: absHumidUnitSet | Q9: seeUnitAggScale | R9: otherAggrSet | S9: genQualitySet | T9: genMissingnessSet | U9: active | V9: 2.0.0 | W9: 2.0.0 | X9: added in V2.0.0 | Y9: input | Z9: NA | AA9: NA | AB9: NA | AC9: NA | AD9: NA | AE9: input | AF9: NA | AG9: NA | AH9: NA | AI9: NA | AJ9: NA | AK9: NA | AL9: NA | AM9: NA | AN9: NA | AO9: NA | AP9: NA | AQ9: NA | AR9: NA | AS9: NA | AT9: NA | AU9: NA | AV9: NA | AW9: NA | AX9: NA | AY9: NA | AZ9: NA | BA9: NA | BB9: NA | BC9: NA | BD9: NA | BE9: NA | BF9: NA | BG9: NA | BH9: NA | BI9: NA | BJ9: NA | BK9: NA | BL9: NA | BM9: NA | BN9: NA | BO9: NA | BP9: NA | BQ9: NA | BR9: NA | BS9: NA | BT9: NA | BU9: NA | BV9: NA | BW9: NA | BX9: NA | BY9: NA | BZ9: NA | CA9: NA | CB9: NA | CC9: NA | CD9: NA | CE9: NA | CF9: NA | CG9: NA | CH9: NA | CI9: NA | CJ9: input | CK9: NA | CL9: NA | CM9: NA | CN9: seeUnitData | CO9: seeUnitVal | CP9: seeUnitVal | CQ9: NA | CR9: NA
A10: absHumidUnitSet | B10: Absolute humidity unit set | C10: unitSets | D10: Unit set for absolute humidity measurements. | E10: NA | F10: NA | G10: naDomain | H10: naSpecimenSet | I10: anyCompartmentSet | J10: naGroup | K10: naClass | L10: naNomenclature | M10: NA | N10: NA | O10: NA | P10: absHumidUnitSet | Q10: seeUnitAggScale | R10: naAggrSet | S10: NA | T10: NA | U10: active | V10: 2.0.0 | W10: 2.0.0 | X10: added in V2.0.0 | Y10: NA | Z10: NA | AA10: NA | AB10: NA | AC10: NA | AD10: NA | AE10: NA | AF10: NA | AG10: NA | AH10: NA | AI10: NA | AJ10: NA | AK10: NA | AL10: NA | AM10: NA | AN10: NA | AO10: NA | AP10: NA | AQ10: NA | AR10: NA | AS10: NA | AT10: NA | AU10: NA | AV10: NA | AW10: NA | AX10: NA | AY10: NA | AZ10: NA | BA10: NA | BB10: NA | BC10: NA | BD10: NA | BE10: NA | BF10: NA | BG10: NA | BH10: NA | BI10: NA | BJ10: NA | BK10: NA | BL10: NA | BM10: NA | BN10: NA | BO10: input | BP10: NA | BQ10: NA | BR10: NA | BS10: NA | BT10: NA | BU10: NA | BV10: NA | BW10: NA | BX10: NA | BY10: NA | BZ10: NA | CA10: NA | CB10: NA | CC10: NA | CD10: NA | CE10: NA | CF10: NA | CG10: NA | CH10: NA | CI10: NA | CJ10: NA | CK10: NA | CL10: NA | CM10: NA | CN10: categorical | CO10: NA | CP10: NA | CQ10: 0 | CR10: 30
A11: ac | B11: Accessions report table Shorthand | C11: shortName | D11: The abbreviated short name used to reference the report table for accessions and accessionIDs. | E11: table | F11: NA | G11: naDomain | H11: naSpecimenSet | I11: naCompartmentSet | J11: naGroup | K11: naClass | L11: naNomenclature | M11: NA | N11: NA | O11: NA | P11: naUnitSet | Q11: naAggrScale | R11: naAggrSet | S11: NA | T11: NA | U11: active | V11: 2.2.2 | W11: 2.2.2 | X11: added in V2.2.2 | Y11: NA | Z11: NA | AA11: NA | AB11: NA | AC11: NA | AD11: NA | AE11: NA | AF11: NA | AG11: NA | AH11: NA | AI11: NA | AJ11: NA | AK11: NA | AL11: NA | AM11: NA | AN11: NA | AO11: NA | AP11: NA | AQ11: NA | AR11: NA | AS11: NA | AT11: NA | AU11: NA | AV11: NA | AW11: NA | AX11: NA | AY11: NA | AZ11: NA | BA11: NA | BB11: NA | BC11: NA | BD11: NA | BE11: NA | BF11: NA | BG11: NA | BH11: NA | BI11: NA | BJ11: NA | BK11: NA | BL11: NA | BM11: NA | BN11: NA | BO11: NA | BP11: NA | BQ11: NA | BR11: NA | BS11: NA | BT11: NA | BU11: NA | BV11: NA | BW11: NA | BX11: NA | BY11: NA | BZ11: NA | CA11: NA | CB11: NA | CC11: NA | CD11: NA | CE11: NA | CF11: NA | CG11: NA | CH11: NA | CI11: NA | CJ11: input | CK11: NA | CL11: NA | CM11: NA | CN11: varchar | CO11: NA | CP11: NA | CQ11: 0 | CR11: 30
A12: academ | B12: Academic institution | C12: categories | D12: The category of organization type used for academic institutions or research groups. | E12: NA | F12: NA | G12: naDomain | H12: naSpecimenSet | I12: naCompartmentSet | J12: naGroup | K12: naClass | L12: naNomenclature | M12: NA | N12: NA | O12: NA | P12: naUnitSet | Q12: naAggrScale | R12: naAggrSet | S12: NA | T12: NA | U12: active | V12: 2.0.0 | W12: 2.0.0 | X12: added in V2.0.0 | Y12: NA | Z12: NA | AA12: NA | AB12: NA | AC12: NA | AD12: NA | AE12: NA | AF12: NA | AG12: NA | AH12: NA | AI12: NA | AJ12: NA | AK12: NA | AL12: NA | AM12: NA | AN12: NA | AO12: NA | AP12: NA | AQ12: NA | AR12: NA | AS12: NA | AT12: NA | AU12: NA | AV12: NA | AW12: NA | AX12: NA | AY12: NA | AZ12: input | BA12: NA | BB12: NA | BC12: NA | BD12: NA | BE12: NA | BF12: NA | BG12: NA | BH12: NA | BI12: NA | BJ12: NA | BK12: NA | BL12: NA | BM12: NA | BN12: NA | BO12: NA | BP12: NA | BQ12: NA | BR12: NA | BS12: NA | BT12: NA | BU12: NA | BV12: NA | BW12: NA | BX12: NA | BY12: NA | BZ12: NA | CA12: NA | CB12: NA | CC12: NA | CD12: NA | CE12: NA | CF12: NA | CG12: NA | CH12: NA | CI12: NA | CJ12: input | CK12: NA | CL12: NA | CM12: NA | CN12: varchar | CO12: NA | CP12: NA | CQ12: 0 | CR12: 30
... A1617: delayArriv | B1617: Delayed Arrival or Prolonged Transit | C1617: qualityIndicators | D1617: A substantial delay (ie. of more than 14 days) between sample collection and the start of analysis. | E1617: NA | F1617: NA | G1617: naDomain | H1617: naSpecimenSet | I1617: naCompartmentSet | J1617: naGroup | K1617: naClass | L1617: naNomenclature | M1617: NA | N1617: NA | O1617: NA | P1617: naUnitSet | Q1617: naAggrScale | R1617: naAggrSet | S1617: NA | T1617: NA | U1617: active | V1617: 2.2.3 | W1617: 2.2.3 | X1617: added in V2.2.3 | Y1617: NA | Z1617: NA | AA1617: NA | AB1617: NA | AC1617: NA | AD1617: NA | AE1617: NA | AF1617: NA | AG1617: NA | AH1617: NA | AI1617: NA | AJ1617: NA | AK1617: NA | AL1617: NA | AM1617: NA | AN1617: NA | AO1617: NA | AP1617: NA | AQ1617: NA | AR1617: NA | AS1617: NA | AT1617: NA | AU1617: NA | AV1617: NA | AW1617: NA | AX1617: NA | AY1617: NA | AZ1617: NA | BA1617: NA | BB1617: NA | BC1617: NA | BD1617: NA | BE1617: NA | BF1617: NA | BG1617: NA | BH1617: NA | BI1617: NA | BJ1617: NA | BK1617: NA | BL1617: NA | BM1617: NA | BN1617: NA | BO1617: NA | BP1617: NA | BQ1617: NA | BR1617: NA | BS1617: NA | BT1617: NA | BU1617: input | BV1617: NA | BW1617: NA | BX1617: NA | BY1617: NA | BZ1617: NA | CA1617: NA | CB1617: NA | CC1617: NA | CD1617: NA | CE1617: NA | CF1617: NA | CG1617: NA | CH1617: NA | CI1617: NA | CJ1617: NA | CK1617: NA | CL1617: NA | CM1617: NA | CN1617: varchar | CO1617: NA | CP1617: NA | CQ1617: 0 | CR1617: 30

Sheet sets
A1: setCompID | B1: setID | C1: setType | D1: partID | E1: label | F1: enumeration | G1: status | H1: firstReleased | I1: lastUpdated | J1: changes | K1: notes
A2: absHumidUnitSet_gm3 | B2: absHumidUnitSet | C2: unitSets | D2: gm3 | E2: Gram per cubic metre | F2: 1 | G2: active | H2: 2.0.0 | I2: 2.0.0
A3: airCompartmentSet_air | B3: airCompartmentSet | C3: compartmentSets | D3: air | E3: Air compartment | F3: 1 | G3: active | H3: 2.0.0 | I3: 2.0.0
A4: airportSheetSet_airportLists | B4: airportSheetSet | C4: dictSets | D4: airportLists | E4: Airport lists worksheet | F4: 1 | G4: active | H4: 2.0.0 | I4: 2.0.0
A5: airportSheetSet_airportTemplate | B5: airportSheetSet | C5: dictSets | D5: airportTemplate | E5: Airport Surveillance Template | F5: 2 | G5: active | H5: 2.0.0 | I5: 2.0.0
A6: airSurfaceCompartmentSet_air | B6: airSurfaceCompartmentSet | C6: compartmentSets | D6: air | E6: Air compartment | F6: 1 | G6: active | H6: 2.0.0 | I6: 2.0.0
A7: airSurfaceCompartmentSet_surf | B7: airSurfaceCompartmentSet | C7: compartmentSets | D7: surf | E7: Surface compartment | F7: 2 | G7: active | H7: 2.0.0 | I7: 2.0.0
A8: airWaterCompartmentSet_air | B8: airWaterCompartmentSet | C8: compartmentSets | D8: air | E8: Air compartment | F8: 1 | G8: active | H8: 2.0.0 | I8: 2.0.0
A9: alleleUnitSet_ct | B9: alleleUnitSet | C9: unitSets | D9: ct | E9: Cycle threshold or quantification cycle (Ct or Cq) | F9: 1 | G9: active | H9: 2.0.0 | I9: 2.0.0
A10: alleleUnitSet_doc | B10: alleleUnitSet | C10: unitSets | D10: doc | E10: Depth of coverage | F10: 2 | G10: active | H10: 2.0.0 | I10: 2.0.0
A11: alleleUnitSet_gcCrA | B11: alleleUnitSet | C11: unitSets | D11: gcCrA | E11: Gene copies per copy of crAssphage | F11: 3 | G11: active | H11: 2.0.0 | I11: 2.0.0
A12: alleleUnitSet_gCGS | B12: alleleUnitSet | C12: unitSets | D12: gCGS | E12: Gene copies per gram solids | F12: 4 | G12: active | H12: 2.0.0 | I12: 2.0.0
A13: alleleUnitSet_gcMl | B13: alleleUnitSet | C13: unitSets | D13: gcMl | E13: Gene copies per mL | F13: 5 | G13: active | H13: 2.0.0 | I13: 2.0.0
A14: alleleUnitSet_gcDay100k | B14: alleleUnitSet | C14: unitSets | D14: gcDay100k | E14: gene copies per day per 100,000 people | F14: 6 | G14: active | H14: 2.0.0 | I14: 3.0.0 | J14: updated partID
A15: alleleUnitSet_det | B15: alleleUnitSet | C15: unitSets | D15: det | E15: Detected | F15: 7 | G15: active | H15: 1.1.0 | I15: 2.0.0
A16: alleleUnitSet_gcPpmov | B16: alleleUnitSet | C16: unitSets | D16: gcPpmov | E16: Gene copies per PMMoV copy | F16: 8 | G16: active | H16: 2.0.0 | I16: 2.0.0
A17: alleleUnitSet_slope | B17: alleleUnitSet | C17: unitSets | D17: slope | E17: slope | F17: 9 | G17: active | H17: 2.0.0 | I17: 2.0.0
A18: alleleUnitSet_inter | B18: alleleUnitSet | C18: unitSets | D18: inter | E18: Intercept | F18: 10 | G18: active | H18: 2.0.0 | I18: 2.0.0
A19: alleleUnitSet_efficient | B19: alleleUnitSet | C19: unitSets | D19: efficient | E19: Efficiency | F19: 11 | G19: active | H19: 2.0.0 | I19: 2.0.0
A20: alleleUnitSet_r2 | B20: alleleUnitSet | C20: unitSets | D20: r2 | E20: R squared | F20: 12 | G20: active | H20: 2.0.0 | I20: 2.0.0
A21: anyCompartmentSet_air | B21: anyCompartmentSet | C21: compartmentSets | D21: air | E21: Air compartment | F21: 1 | G21: active | H21: 2.0.0 | I21: 2.0.0
A22: anyCompartmentSet_surf | B22: anyCompartmentSet | C22: compartmentSets | D22: surf | E22: Surface compartment | F22: 2 | G22: active | H22: 2.0.0 | I22: 2.0.0
A23: anyCompartmentSet_wat | B23: anyCompartmentSet | C23: compartmentSets | D23: wat | E23: Water compartment | F23: 3 | G23: active | H23: 2.0.0 | I23: 2.0.0
A24: anySpecimenSet_pop | B24: anySpecimenSet | C24: specimenSets | D24: pop | E24: Population | F24: 1 | G24: active | H24: 2.0.0 | I24: 2.0.0
A25: anySpecimenSet_sa | B25: anySpecimenSet | C25: specimenSets | D25: sa | E25: Sample | F25: 2 | G25: active | H25: 2.0.0 | I25: 2.0.0
A26: anySpecimenSet_sit | B26: anySpecimenSet | C26: specimenSets | D26: sit | E26: Site | F26: 3 | G26: active | H26: 2.0.0 | I26: 2.0.0
... A178: geneticUnitSet_gcCrA | B178: geneticUnitSet | C178: unitSets | D178: gcCrA | E178: Gene copies per copy of crAssphage | F178: 7 | G178: active | H178: 2.0.0 | I178: 2.0.0
A179: geneticUnitSet_gcDay100k | B179: geneticUnitSet | C179: unitSets | D179: gcDay100k | E179: gene copies per day per 100,000 people | F179: 8 | G179: active | H179: 2.0.0 | I179: 3.0.0 | J179: updated partID
A180: geneticUnitSet_gCGS | B180: geneticUnitSet | C180: unitSets | D180: gCGS | E180: Gene copies per gram solids | F180: 9 | G180: active | H180: 2.0.0 | I180: 2.0.0
A181: geneticUnitSet_gcMl | B181: geneticUnitSet | C181: unitSets | D181: gcMl | E181: Gene copies per mL | F181: 10 | G181: active | H181: 2.0.0 | I181: 2.0.0
A182: geneticUnitSet_gcPpmov | B182: geneticUnitSet | C182: unitSets | D182: gcPpmov | E182: Gene copies per PMMoV copy | F182: 11 | G182: active | H182: 2.0.0 | I182: 2.0.0
A183: geneticUnitSet_gc | B183: geneticUnitSet | C183: unitSets | D183: gc | E183: Gene copies | F183: 12 | G183: active | H183: 2.0.0 | I183: 2.0.0
A184: geneticUnitSet_ct | B184: geneticUnitSet | C184: unitSets | D184: ct | E184: Cycle threshold or quantification cycle (Ct or Cq) | F184: 13 | G184: active | H184: 2.0.0 | I184: 2.0.0
A185: geneticUnitSet_slope | B185: geneticUnitSet | C185: unitSets | D185: slope | E185: slope | F185: 14 | G185: active | H185: 2.0.0 | I185: 2.0.0
A186: geneticUnitSet_inter | B186: geneticUnitSet | C186: unitSets | D186: inter | E186: Intercept | F186: 15 | G186: active | H186: 2.0.0 | I186: 2.0.0
A187: geneticUnitSet_efficient | B187: geneticUnitSet | C187: unitSets | D187: efficient | E187: Efficiency | F187: 16 | G187: active | H187: 2.0.0 | I187: 2.0.0
A188: geneticUnitSet_r2 | B188: geneticUnitSet | C188: unitSets | D188: r2 | E188: R squared | F188: 17 | G188: active | H188: 2.0.0 | I188: 2.0.0
A189: genMissingnessSet_restrict | B189: genMissingnessSet | C189: missingnessSets | D189: restrict | E189: Restricted data | F189: 0 | G189: active | H189: 2.3.0 | I189: 2.3.0
A190: genMissingnessSet_NULL | B190: genMissingnessSet | C190: missingnessSets | D190: NULL | E190: Null | F190: 555 | G190: active | H190: 2.0.0 | I190: 2.0.0
A191: genMissingnessSet_undisc | B191: genMissingnessSet | C191: missingnessSets | D191: undisc | E191: Undisclosed or Not Provided | F191: 666 | G191: active | H191: 2.0.0 | I191: 2.0.0
... A328: methodConcSet_noSep | B328: methodConcSet | C328: mmaSets | D328: noSep | E328: No Seperation or Concentration | F328: 20 | G328: active | H328: 2.2.0 | I328: 2.2.0
A329: methodConcSet_promWW | B329: methodConcSet | C329: mmaSets | D329: promWW | E329: promega wastewater large volume tna capture kit | F329: 21 | G329: active | H329: 2.2.0 | I329: 3.1.0 | J329: changed partID to correct duplication. As a result setCompID also changed.
A330: methodConcSet_zymoEnv | B330: methodConcSet | C330: mmaSets | D330: zymoEnv | E330: zymo environ water rna kit (cat. r2042) | F330: 22 | G330: active | H330: 2.2.0 | I330: 3.1.0 | J330: changed partID to correct duplication. As a result setCompID also changed.
A331: methodConcSet_memMgCl3 | B331: methodConcSet | C331: mmaSets | D331: memMgCl3 | E331: membrane filtration with addition of mgcl3 | F331: 23 | G331: active | H331: 2.2.0 | I331: 2.2.0
A332: methodConcSet_watConcBuff | B332: methodConcSet | C332: mmaSets | D332: watConcBuff | E332: water concentrating buffer (R2042-1) | F332: 24 | G332: active | H332: 2.2.0 | I332: 2.2.0
A333: naAggrSet_naAggr | B333: naAggrSet | C333: aggregationSets | D333: naAggr | E333: Aggregation not applicable | F333: 1 | G333: active | H333: 2.0.0 | I333: 2.0.0
A334: naCompartmentSet_naCompartment | B334: naCompartmentSet | C334: compartmentSets | D334: naCompartment | E334: Compartment not applicable | F334: 1 | G334: active | H334: 2.0.0 | I334: 2.0.0
A335: naSpecimenSet_naSpecimen | B335: naSpecimenSet | C335: specimenSets | D335: naSpecimen | E335: Specimen not applicable | F335: 1 | G335: active | H335: 2.0.0 | I335: 2.0.0
A336: naUnitSet_naUnit | B336: naUnitSet | C336: unitSets | D336: naUnit | E336: Unit not applicable | F336: 1 | G336: active | H336: 2.0.0 | I336: 2.0.0
A337: nrNAMissingnessSet_nr | B337: nrNAMissingnessSet | C337: missingnessSets | D337: nr | E337: Not reported | F337: 777 | G337: active | H337: 2.0.0 | I337: 2.0.0
A338: nrNAMissingnessSet_NA | B338: nrNAMissingnessSet | C338: missingnessSets | D338: NA | E338: Not applicable | F338: 999 | G338: active | H338: 2.0.0 | I338: 2.0.0
A339: ogFormSet_phesODMFormV1 | B339: ogFormSet | C339: mmaSets | D339: phesODMFormV1 | E339: PHES-ODM Version 1 Format | F339: 1 | G339: active | H339: 2.3.0 | I339: 2.3.0
A340: ogFormSet_pha4geForm | B340: ogFormSet | C340: mmaSets | D340: pha4geForm | E340: PHA4GE Format | F340: 2 | G340: active | H340: 2.3.0 | I340: 2.3.0
A341: ogFormSet_nwssForm | B341: ogFormSet | C341: mmaSets | D341: nwssForm | E341: US-CDC NWSS Format | F341: 3 | G341: active | H341: 2.3.0 | I341: 2.3.0
A342: ogFormSet_ncbiForm | B342: ogFormSet | C342: mmaSets | D342: ncbiForm | E342: NCBI Format | F342: 4 | G342: active | H342: 2.3.0 | I342: 2.3.0
... A391: pcrActSet_rt | B391: pcrActSet | C391: mmaSets | D391: rt | E391: reverse transcription | F391: 1 | G391: active | H391: 2.0.0 | I391: 2.0.0
A392: pcrActSet_pAct | B392: pcrActSet | C392: mmaSets | D392: pAct | E392: polymerase activation | F392: 2 | G392: active | H392: 2.0.0 | I392: 3.0.0 | J392: updated partID
A393: pcrActSet_denat | B393: pcrActSet | C393: mmaSets | D393: denat | E393: denaturation | F393: 3 | G393: active | H393: 2.0.0 | I393: 2.0.0
A394: pcrActSet_anneal | B394: pcrActSet | C394: mmaSets | D394: anneal | E394: annealing/extension | F394: 4 | G394: active | H394: 2.0.0 | I394: 2.0.0
A395: pcrQualitySet_flagAI | B395: pcrQualitySet | C395: qualityIndSets | D395: flagAI | E395: AI - Inhibition present but addressed | F395: 1 | G395: active | H395: 2.0.0 | I395: 2.0.0
A396: pcrQualitySet_flagB | B396: pcrQualitySet | C396: qualityIndSets | D396: flagB | E396: B - Trace levels of contamination | F396: 2 | G396: active | H396: 2.0.0 | I396: 2.0.0
A397: pcrQualitySet_expFail | B397: pcrQualitySet | C397: qualityIndSets | D397: expFail | E397: Experiment Failed | F397: 3 | G397: active | H397: 2.0.0 | I397: 2.0.0
A398: pcrQualitySet_flagFI | B398: pcrQualitySet | C398: qualityIndSets | D398: flagFI | E398: FI - Inhibition present and unaddressed | F398: 4 | G398: active | H398: 2.0.0 | I398: 2.0.0
A399: pcrQualitySet_flagJ | B399: pcrQualitySet | C399: qualityIndSets | D399: flagJ | E399: J - Weak signal extrapolation | F399: 5 | G399: active | H399: 2.0.0 | I399: 2.0.0
A400: pcrQualitySet_flagND | B400: pcrQualitySet | C400: qualityIndSets | D400: flagND | E400: ND - Non-detect | F400: 6 | G400: active | H400: 2.0.0 | I400: 2.0.0
A401: pcrQualitySet_noConcern | B401: pcrQualitySet | C401: qualityIndSets | D401: noConcern | E401: No quality concerns | F401: 7 | G401: active | H401: 2.0.0 | I401: 2.0.0
A402: pcrQualitySet_flagUJ | B402: pcrQualitySet | C402: qualityIndSets | D402: flagUJ | E402: UJ - Trace signal extrapolation | F402: 8 | G402: active | H402: 2.0.0 | I402: 2.0.0
A403: pcrQualitySet_flagUQ | B403: pcrQualitySet | C403: qualityIndSets | D403: flagUQ | E403: UQ - Unquantifiable | F403: 9 | G403: active | H403: 2.0.0 | I403: 2.0.0
A404: pcrQualitySet_oor | B404: pcrQualitySet | C404: qualityIndSets | D404: oor | E404: Value out of range | F404: 10 | G404: active | H404: 2.0.0 | I404: 2.0.0
... A678: speedUnitSet_rpm | B678: speedUnitSet | C678: unitSets | D678: rpm | E678: Revolutions per minute (RPM) | F678: 2 | G678: active | H678: 2.2.0 | I678: 2.2.0
A679: speedUnitSet_mps | B679: speedUnitSet | C679: unitSets | D679: mps | E679: Metres per second | F679: 3 | G679: active | H679: 2.2.0 | I679: 3.0.0 | J679: part ID changed from "ms" to "mps"
A680: spikeMatSet_clari | B680: spikeMatSet | C680: mmaSets | D680: clari | E680: Clarified sample | F680: 1 | G680: active | H680: 1.0.0 | I680: 2.0.0
A681: spikeMatSet_samConc | B681: spikeMatSet | C681: mmaSets | D681: samConc | E681: Sample concentrate | F681: 2 | G681: active | H681: 1.0.0 | I681: 3.0.0 | J681: partID changed/updated
A682: spikeMatSet_deso | B682: spikeMatSet | C682: mmaSets | D682: deso | E682: Dewatered solids | F682: 3 | G682: active | H682: 1.0.0 | I682: 2.0.0
A683: spikeMatSet_lysi | B683: spikeMatSet | C683: mmaSets | D683: lysi | E683: Lysis buffer | F683: 4 | G683: active | H683: 2.0.0 | I683: 2.0.0
A684: spikeMatSet_raws | B684: spikeMatSet | C684: mmaSets | D684: raws | E684: Raw wastewater | F684: 5 | G684: active | H684: 1.0.0 | I684: 2.0.0
A685: spikeMatSet_rppw | B685: spikeMatSet | C685: mmaSets | D685: rppw | E685: Raw post-pasteurized wastewater | F685: 6 | G685: active | H685: 1.0.0 | I685: 2.0.0
A686: spikeTargetSet_bcovCul | B686: spikeTargetSet | C686: mmaSets | D686: bcovCul | E686: bcov culture spike target | F686: 1 | G686: active | H686: 2.0.0 | I686: 2.0.0
A687: spikeTargetSet_bcovVac | B687: spikeTargetSet | C687: mmaSets | D687: bcovVac | E687: bcov vaccine spike target | F687: 2 | G687: active | H687: 2.0.0 | I687: 2.0.0
A688: spikeTargetSet_brsvCul | B688: spikeTargetSet | C688: mmaSets | D688: brsvCul | E688: brsv culture spike target | F688: 3 | G688: active | H688: 2.0.0 | I688: 2.0.0
A689: spikeTargetSet_brsvVac | B689: spikeTargetSet | C689: mmaSets | D689: brsvVac | E689: brsv vaccine spike target | F689: 4 | G689: active | H689: 2.0.0 | I689: 2.0.0
A690: spikeTargetSet_heatInacSARS | B690: spikeTargetSet | C690: mmaSets | D690: heatInacSARS | E690: Heat inactivated sars-cov-2 virus spike target | F690: 5 | G690: active | H690: 2.0.0 | I690: 2.0.0
A691: spikeTargetSet_hepGRnaMat | B691: spikeTargetSet | C691: mmaSets | D691: hepGRnaMat | E691: hep g armored rna spike target | F691: 6 | G691: active | H691: 2.0.0 | I691: 2.0.0
A692: spikeTargetSet_ms2ColMat | B692: spikeTargetSet | C692: mmaSets | D692: ms2ColMat | E692: ms2 coliphage spike target | F692: 7 | G692: active | H692: 2.0.0 | I692: 2.0.0
A693: spikeTargetSet_muCoMat | B693: spikeTargetSet | C693: mmaSets | D693: muCoMat | E693: murine coronavirus spike target | F693: 8 | G693: active | H693: 2.0.0 | I693: 2.0.0
... A780: wideSpecimenSet_hSp | B780: wideSpecimenSet | C780: specimenSets | D780: hSp | E780: See Header for Specimen | F780: 5 | G780: active | H780: 2.2.0 | I780: 2.2.0
A781: windSpeedUnitSet_mps | B781: windSpeedUnitSet | C781: unitSets | D781: mps | E781: Metres per second | F781: 1 | G781: active | H781: 2.0.0 | I781: 3.0.0 | J781: part ID changed from "ms" to "mps"
A782: purposeSet_cali | B782: purposeSet | C782: mmaSets | D782: cali | E782: Calibration purpose | F782: 25 | G782: active | H782: 3.0.1 | I782: 3.0.1
A783: geoRefMissingnessSet_NULL | B783: geoRefMissingnessSet | C783: missingnessSets | D783: NULL | E783: Null | F783: 1 | G783: active | H783: 3.0.1 | I783: 3.0.1
A784: humidUnitSet_gm3 | B784: humidUnitSet | C784: unitSets | D784: gm3 | E784: Gram per cubic metre | F784: 1 | G784: active | H784: 3.0.1 | I784: 3.0.1
A785: humidUnitSet_perc | B785: humidUnitSet | C785: unitSets | D785: perc | E785: Percent | F785: 2 | G785: active | H785: 3.0.1 | I785: 3.0.1
A786: humidUnitSet_ratio | B786: humidUnitSet | C786: unitSets | D786: ratio | E786: Ratio | F786: 3 | G786: active | H786: 3.0.1 | I786: 3.0.1
A787: humidUnitSet_hUn | B787: humidUnitSet | C787: unitSets | D787: hUn | E787: See Header for Unit | F787: 4 | G787: active | H787: 3.0.1 | I787: 3.0.1
A788: setTypeSet_specimenSets | B788: setTypeSet | C788: mmaSets | D788: specimenSets | E788: Specimen sets | F788: 1 | G788: active | H788: 3.0.1 | I788: 3.0.1
A789: setTypeSet_qualityIndSets | B789: setTypeSet | C789: mmaSets | D789: qualityIndSets | E789: Quality indicator sets | F789: 2 | G789: active | H789: 3.0.1 | I789: 3.0.1
A790: setTypeSet_compartmentSets | B790: setTypeSet | C790: mmaSets | D790: compartmentSets | E790: Compartment sets | F790: 3 | G790: active | H790: 3.0.1 | I790: 3.0.1
A791: setTypeSet_aggregationSets | B791: setTypeSet | C791: mmaSets | D791: aggregationSets | E791: Aggregation sets | F791: 4 | G791: active | H791: 3.0.1 | I791: 3.0.1
A792: setTypeSet_mmaSets | B792: setTypeSet | C792: mmaSets | D792: mmaSets | E792: Measure, method, or attribute sets | F792: 5 | G792: active | H792: 3.0.1 | I792: 3.0.1
A793: setTypeSet_unitSets | B793: setTypeSet | C793: mmaSets | D793: unitSets | E793: Unit sets | F793: 6 | G793: active | H793: 3.0.1 | I793: 3.0.1
... A796: setTypeSet_dictSets | B796: setTypeSet | C796: mmaSets | D796: dictSets | E796: Dictionary set type | F796: 9 | G796: active | H796: 3.0.1 | I796: 3.0.1
...

Sheet wideNames
A1: wideName | B1: label | C1: charLength | D1: descr | E1: source | F1: wideMeasure | G1: wideProtocol | H1: wideAttribute | I1: wideNameType | J1: reportTableName | K1: reportTableInput | L1: partTypeName | M1: partTypeInput | N1: compartmentName | O1: compartmentInput | P1: specimenName | Q1: specimenInput | R1: fractionName | S1: fractionInput | T1: measureName | U1: measureInput | V1: methodName | W1: methodInput | X1: unitName | Y1: unitInput | Z1: aggregationName | AA1: aggregationInput | AB1: index | AC1: attributeName | AD1: attributeInput | AE1: tag
A2: =IF(I2="attributes",H2,IF(I2="measurements",F2,G2)) -> 0 | B2: SampleID -Wide | C2: =LEN(A2) -> 0 | D2: A field for recording the unique identifier for a sample in a wide, or combined long and wide table. | E2: EU Airport template | F2: =IF(I2="measurements",IF(AE2="",_xlfn.CONCAT(O2,"_",Q2,"_",S2,"_",U2,"_",Y2,"_",AA2,"_",AB2,"_",AD2),_xlfn.CONCAT(O2,"_",Q2,"_",S2,"_",U2,"_",Y2,"_",AA2,"_",AB2,"_",AD2,".odm",AE2)),"NA") -> 0 | G2: =IF(I2="methods",IF(L2="measurement",IF(AE2="",_xlfn.CONCAT(K2,"_",M2,"_",O2,"_",Q2,"_",S2,"_",U2,"_",Y2,"_",AA2,"_",AB2,"_",AD2),_xlfn.CONCAT(K2,"_",M2,"_",O2,"_",Q2,"_",S2,"_",U2,"_",Y2,"_",AA2,"_",AB2,"_",AD2,".odm",AE2)),IF(AE2="",_xlfn.CONCAT(K2,"_",M2,"_",W2,"_",AD2),_xlfn.CONCAT(K2,"_",M2,"_",W2,"_",AD2,".odm",AE2))),"NA") -> 0 | H2: =IF(I2="attributes",IF(AE2="",_xlfn.CONCAT(K2,"_",AD2),_xlfn.CONCAT(K2,"_",AD2,".odm",AE2)),"NA") -> 0 | I2: attributes | J2: Sample report table Shorthand | K2: =IFERROR(VLOOKUP(J2,'wideName-Dropdowns'!$A:$B,2,FALSE),"") -> 0 | M2: =IFERROR(VLOOKUP(L2,'wideName-Dropdowns'!$C:$D,2,FALSE),"") -> 0 | O2: =IFERROR(VLOOKUP(N2,'wideName-Dropdowns'!$E:$F,2,FALSE),"") -> 0 | Q2: =IFERROR(VLOOKUP(P2,'wideName-Dropdowns'!$G:$H,2,FALSE),"") -> 0 | S2: =IFERROR(VLOOKUP(R2,'wideName-Dropdowns'!$I:$J,2,FALSE),"") -> 0 | U2: =IFERROR(VLOOKUP(T2,'wideName-Dropdowns'!$K:$L,2,FALSE),"") -> 0 | W2: =IFERROR(VLOOKUP(V2,'wideName-Dropdowns'!$M:$N,2,FALSE),"") -> 0 | Y2: =IFERROR(VLOOKUP(X2,'wideName-Dropdowns'!$O:$P,2,FALSE),"") -> 0 | AA2: =IFERROR(VLOOKUP(Z2,'wideName-Dropdowns'!$Q:$R,2,FALSE),"") -> 0 | AC2: Sample ID | AD2: =IFERROR(VLOOKUP(AC2,'wideName-Dropdowns'!$S:$T,2,FALSE),"") -> 0
A3: =IF(I3="attributes",H3,IF(I3="measurements",F3,G3)) -> 0 | B3: Airport IATA code | C3: =LEN(A3) -> 0 | D3: Airport IATA code for sampling, used as a parent site ID for organizing sub-sites in the airport. | E3: EU Airport template | F3: =IF(I3="measurements",IF(AE3="",_xlfn.CONCAT(O3,"_",Q3,"_",S3,"_",U3,"_",Y3,"_",AA3,"_",AB3,"_",AD3),_xlfn.CONCAT(O3,"_",Q3,"_",S3,"_",U3,"_",Y3,"_",AA3,"_",AB3,"_",AD3,".odm",AE3)),"NA") -> 0 | G3: =IF(I3="methods",IF(L3="measurement",IF(AE3="",_xlfn.CONCAT(K3,"_",M3,"_",O3,"_",Q3,"_",S3,"_",U3,"_",Y3,"_",AA3,"_",AB3,"_",AD3),_xlfn.CONCAT(K3,"_",M3,"_",O3,"_",Q3,"_",S3,"_",U3,"_",Y3,"_",AA3,"_",AB3,"_",AD3,".odm",AE3)),IF(AE3="",_xlfn.CONCAT(K3,"_",M3,"_",W3,"_",AD3),_xlfn.CONCAT(K3,"_",M3,"_",W3,"_",AD3,".odm",AE3))),"NA") -> 0 | H3: =IF(I3="attributes",IF(AE3="",_xlfn.CONCAT(K3,"_",AD3),_xlfn.CONCAT(K3,"_",AD3,".odm",AE3)),"NA") -> 0 | I3: attributes | J3: Sites table Shorthand | K3: =IFERROR(VLOOKUP(J3,'wideName-Dropdowns'!$A:$B,2,FALSE),"") -> 0 | M3: =IFERROR(VLOOKUP(L3,'wideName-Dropdowns'!$C:$D,2,FALSE),"") -> 0 | O3: =IFERROR(VLOOKUP(N3,'wideName-Dropdowns'!$E:$F,2,FALSE),"") -> 0 | Q3: =IFERROR(VLOOKUP(P3,'wideName-Dropdowns'!$G:$H,2,FALSE),"") -> 0 | S3: =IFERROR(VLOOKUP(R3,'wideName-Dropdowns'!$I:$J,2,FALSE),"") -> 0 | U3: =IFERROR(VLOOKUP(T3,'wideName-Dropdowns'!$K:$L,2,FALSE),"") -> 0 | W3: =IFERROR(VLOOKUP(V3,'wideName-Dropdowns'!$M:$N,2,FALSE),"") -> 0 | Y3: =IFERROR(VLOOKUP(X3,'wideName-Dropdowns'!$O:$P,2,FALSE),"") -> 0 | AA3: =IFERROR(VLOOKUP(Z3,'wideName-Dropdowns'!$Q:$R,2,FALSE),"") -> 0 | AC3: Parent Site ID | AD3: =IFERROR(VLOOKUP(AC3,'wideName-Dropdowns'!$S:$T,2,FALSE),"") -> 0
A4: =IF(I4="attributes",H4,IF(I4="measurements",F4,G4)) -> 0 | B4: Sample shed - wide | C4: =LEN(A4) -> 0 | D4: A geographic area, physical space, or structure. A sample is taken from a sampleshed for a representative measurement of a substance(s) in a wide, or combined long and wide table. | E4: EU Airport template | F4: =IF(I4="measurements",IF(AE4="",_xlfn.CONCAT(O4,"_",Q4,"_",S4,"_",U4,"_",Y4,"_",AA4,"_",AB4,"_",AD4),_xlfn.CONCAT(O4,"_",Q4,"_",S4,"_",U4,"_",Y4,"_",AA4,"_",AB4,"_",AD4,".odm",AE4)),"NA") -> 0 | G4: =IF(I4="methods",IF(L4="measurement",IF(AE4="",_xlfn.CONCAT(K4,"_",M4,"_",O4,"_",Q4,"_",S4,"_",U4,"_",Y4,"_",AA4,"_",AB4,"_",AD4),_xlfn.CONCAT(K4,"_",M4,"_",O4,"_",Q4,"_",S4,"_",U4,"_",Y4,"_",AA4,"_",AB4,"_",AD4,".odm",AE4)),IF(AE4="",_xlfn.CONCAT(K4,"_",M4,"_",W4,"_",AD4),_xlfn.CONCAT(K4,"_",M4,"_",W4,"_",AD4,".odm",AE4))),"NA") -> 0 | H4: =IF(I4="attributes",IF(AE4="",_xlfn.CONCAT(K4,"_",AD4),_xlfn.CONCAT(K4,"_",AD4,".odm",AE4)),"NA") -> 0 | I4: attributes | J4: Sites table Shorthand | K4: =IFERROR(VLOOKUP(J4,'wideName-Dropdowns'!$A:$B,2,FALSE),"") -> 0 | M4: =IFERROR(VLOOKUP(L4,'wideName-Dropdowns'!$C:$D,2,FALSE),"") -> 0 | O4: =IFERROR(VLOOKUP(N4,'wideName-Dropdowns'!$E:$F,2,FALSE),"") -> 0 | Q4: =IFERROR(VLOOKUP(P4,'wideName-Dropdowns'!$G:$H,2,FALSE),"") -> 0 | S4: =IFERROR(VLOOKUP(R4,'wideName-Dropdowns'!$I:$J,2,FALSE),"") -> 0 | U4: =IFERROR(VLOOKUP(T4,'wideName-Dropdowns'!$K:$L,2,FALSE),"") -> 0 | W4: =IFERROR(VLOOKUP(V4,'wideName-Dropdowns'!$M:$N,2,FALSE),"") -> 0 | Y4: =IFERROR(VLOOKUP(X4,'wideName-Dropdowns'!$O:$P,2,FALSE),"") -> 0 | AA4: =IFERROR(VLOOKUP(Z4,'wideName-Dropdowns'!$Q:$R,2,FALSE),"") -> 0 | AC4: Sample shed | AD4: =IFERROR(VLOOKUP(AC4,'wideName-Dropdowns'!$S:$T,2,FALSE),"") -> 0
A5: =IF(I5="attributes",H5,IF(I5="measurements",F5,G5)) -> 0 | B5: Site | C5: =LEN(A5) -> 0 | D5: A field for recording the unique identifier for a site in a wide, or combined long and wide table. | E5: EU Airport template | F5: =IF(I5="measurements",IF(AE5="",_xlfn.CONCAT(O5,"_",Q5,"_",S5,"_",U5,"_",Y5,"_",AA5,"_",AB5,"_",AD5),_xlfn.CONCAT(O5,"_",Q5,"_",S5,"_",U5,"_",Y5,"_",AA5,"_",AB5,"_",AD5,".odm",AE5)),"NA") -> 0 | G5: =IF(I5="methods",IF(L5="measurement",IF(AE5="",_xlfn.CONCAT(K5,"_",M5,"_",O5,"_",Q5,"_",S5,"_",U5,"_",Y5,"_",AA5,"_",AB5,"_",AD5),_xlfn.CONCAT(K5,"_",M5,"_",O5,"_",Q5,"_",S5,"_",U5,"_",Y5,"_",AA5,"_",AB5,"_",AD5,".odm",AE5)),IF(AE5="",_xlfn.CONCAT(K5,"_",M5,"_",W5,"_",AD5),_xlfn.CONCAT(K5,"_",M5,"_",W5,"_",AD5,".odm",AE5))),"NA") -> 0 | H5: =IF(I5="attributes",IF(AE5="",_xlfn.CONCAT(K5,"_",AD5),_xlfn.CONCAT(K5,"_",AD5,".odm",AE5)),"NA") -> 0 | I5: attributes | J5: Sites table Shorthand | K5: =IFERROR(VLOOKUP(J5,'wideName-Dropdowns'!$A:$B,2,FALSE),"") -> 0 | M5: =IFERROR(VLOOKUP(L5,'wideName-Dropdowns'!$C:$D,2,FALSE),"") -> 0 | O5: =IFERROR(VLOOKUP(N5,'wideName-Dropdowns'!$E:$F,2,FALSE),"") -> 0 | Q5: =IFERROR(VLOOKUP(P5,'wideName-Dropdowns'!$G:$H,2,FALSE),"") -> 0 | S5: =IFERROR(VLOOKUP(R5,'wideName-Dropdowns'!$I:$J,2,FALSE),"") -> 0 | U5: =IFERROR(VLOOKUP(T5,'wideName-Dropdowns'!$K:$L,2,FALSE),"") -> 0 | W5: =IFERROR(VLOOKUP(V5,'wideName-Dropdowns'!$M:$N,2,FALSE),"") -> 0 | Y5: =IFERROR(VLOOKUP(X5,'wideName-Dropdowns'!$O:$P,2,FALSE),"") -> 0 | AA5: =IFERROR(VLOOKUP(Z5,'wideName-Dropdowns'!$Q:$R,2,FALSE),"") -> 0 | AC5: Site ID | AD5: =IFERROR(VLOOKUP(AC5,'wideName-Dropdowns'!$S:$T,2,FALSE),"") -> 0
A6: =IF(I6="attributes",H6,IF(I6="measurements",F6,G6)) -> 0 | B6: Population served (PE) | C6: =LEN(A6) -> 0 | D6: A field for reporting the attribute of a site, which specifies the population of/population served by a given site in a wide or combined long-and-wide table. | E6: EU Airport template | F6: =IF(I6="measurements",IF(AE6="",_xlfn.CONCAT(O6,"_",Q6,"_",S6,"_",U6,"_",Y6,"_",AA6,"_",AB6,"_",AD6),_xlfn.CONCAT(O6,"_",Q6,"_",S6,"_",U6,"_",Y6,"_",AA6,"_",AB6,"_",AD6,".odm",AE6)),"NA") -> 0 | G6: =IF(I6="methods",IF(L6="measurement",IF(AE6="",_xlfn.CONCAT(K6,"_",M6,"_",O6,"_",Q6,"_",S6,"_",U6,"_",Y6,"_",AA6,"_",AB6,"_",AD6),_xlfn.CONCAT(K6,"_",M6,"_",O6,"_",Q6,"_",S6,"_",U6,"_",Y6,"_",AA6,"_",AB6,"_",AD6,".odm",AE6)),IF(AE6="",_xlfn.CONCAT(K6,"_",M6,"_",W6,"_",AD6),_xlfn.CONCAT(K6,"_",M6,"_",W6,"_",AD6,".odm",AE6))),"NA") -> 0 | H6: =IF(I6="attributes",IF(AE6="",_xlfn.CONCAT(K6,"_",AD6),_xlfn.CONCAT(K6,"_",AD6,".odm",AE6)),"NA") -> 0 | I6: measurements | J6: Measure report table Shorthand | K6: =IFERROR(VLOOKUP(J6,'wideName-Dropdowns'!$A:$B,2,FALSE),"") -> 0 | L6: Measures Part-type Shorthand | M6: =IFERROR(VLOOKUP(L6,'wideName-Dropdowns'!$C:$D,2,FALSE),"") -> 0 | N6: Human compartment | O6: =IFERROR(VLOOKUP(N6,'wideName-Dropdowns'!$E:$F,2,FALSE),"") -> 0 | P6: Site | Q6: =IFERROR(VLOOKUP(P6,'wideName-Dropdowns'!$G:$H,2,FALSE),"") -> 0 | R6: Not applicable | S6: =IFERROR(VLOOKUP(R6,'wideName-Dropdowns'!$I:$J,2,FALSE),"") -> 0 | T6: Population Served | U6: =IFERROR(VLOOKUP(T6,'wideName-Dropdowns'!$K:$L,2,FALSE),"") -> 0 | W6: =IFERROR(VLOOKUP(V6,'wideName-Dropdowns'!$M:$N,2,FALSE),"") -> 0 | X6: Number of people | Y6: =IFERROR(VLOOKUP(X6,'wideName-Dropdowns'!$O:$P,2,FALSE),"") -> 0 | Z6: Total amount or count - the sum | AA6: =IFERROR(VLOOKUP(Z6,'wideName-Dropdowns'!$Q:$R,2,FALSE),"") -> 0 | AB6: NA | AC6: Value | AD6: =IFERROR(VLOOKUP(AC6,'wideName-Dropdowns'!$S:$T,2,FALSE),"") -> 0
A7: =IF(I7="attributes",H7,IF(I7="measurements",F7,G7)) -> 0 | B7: Collection start date/time - wide | C7: =LEN(A7) -> 0 | D7: For integrated time averaged samples this is the date, time and timezone the sample was started being taken in a wide or combined long-and-wide table. | E7: EU Airport template | F7: =IF(I7="measurements",IF(AE7="",_xlfn.CONCAT(O7,"_",Q7,"_",S7,"_",U7,"_",Y7,"_",AA7,"_",AB7,"_",AD7),_xlfn.CONCAT(O7,"_",Q7,"_",S7,"_",U7,"_",Y7,"_",AA7,"_",AB7,"_",AD7,".odm",AE7)),"NA") -> 0 | G7: =IF(I7="methods",IF(L7="measurement",IF(AE7="",_xlfn.CONCAT(K7,"_",M7,"_",O7,"_",Q7,"_",S7,"_",U7,"_",Y7,"_",AA7,"_",AB7,"_",AD7),_xlfn.CONCAT(K7,"_",M7,"_",O7,"_",Q7,"_",S7,"_",U7,"_",Y7,"_",AA7,"_",AB7,"_",AD7,".odm",AE7)),IF(AE7="",_xlfn.CONCAT(K7,"_",M7,"_",W7,"_",AD7),_xlfn.CONCAT(K7,"_",M7,"_",W7,"_",AD7,".odm",AE7))),"NA") -> 0 | H7: =IF(I7="attributes",IF(AE7="",_xlfn.CONCAT(K7,"_",AD7),_xlfn.CONCAT(K7,"_",AD7,".odm",AE7)),"NA") -> 0 | I7: attributes | J7: Sample report table Shorthand | K7: =IFERROR(VLOOKUP(J7,'wideName-Dropdowns'!$A:$B,2,FALSE),"") -> 0 | M7: =IFERROR(VLOOKUP(L7,'wideName-Dropdowns'!$C:$D,2,FALSE),"") -> 0 | O7: =IFERROR(VLOOKUP(N7,'wideName-Dropdowns'!$E:$F,2,FALSE),"") -> 0 | Q7: =IFERROR(VLOOKUP(P7,'wideName-Dropdowns'!$G:$H,2,FALSE),"") -> 0 | S7: =IFERROR(VLOOKUP(R7,'wideName-Dropdowns'!$I:$J,2,FALSE),"") -> 0 | U7: =IFERROR(VLOOKUP(T7,'wideName-Dropdowns'!$K:$L,2,FALSE),"") -> 0 | W7: =IFERROR(VLOOKUP(V7,'wideName-Dropdowns'!$M:$N,2,FALSE),"") -> 0 | Y7: =IFERROR(VLOOKUP(X7,'wideName-Dropdowns'!$O:$P,2,FALSE),"") -> 0 | AA7: =IFERROR(VLOOKUP(Z7,'wideName-Dropdowns'!$Q:$R,2,FALSE),"") -> 0 | AC7: Collection date time start | AD7: =IFERROR(VLOOKUP(AC7,'wideName-Dropdowns'!$S:$T,2,FALSE),"") -> 0
A8: =IF(I8="attributes",H8,IF(I8="measurements",F8,G8)) -> 0 | B8: Collection type - wide | C8: =LEN(A8) -> 0 | D8: The type of sample collection in a wide or combined long-and-wide table. | E8: EU Airport template | F8: =IF(I8="measurements",IF(AE8="",_xlfn.CONCAT(O8,"_",Q8,"_",S8,"_",U8,"_",Y8,"_",AA8,"_",AB8,"_",AD8),_xlfn.CONCAT(O8,"_",Q8,"_",S8,"_",U8,"_",Y8,"_",AA8,"_",AB8,"_",AD8,".odm",AE8)),"NA") -> 0 | G8: =IF(I8="methods",IF(L8="measurement",IF(AE8="",_xlfn.CONCAT(K8,"_",M8,"_",O8,"_",Q8,"_",S8,"_",U8,"_",Y8,"_",AA8,"_",AB8,"_",AD8),_xlfn.CONCAT(K8,"_",M8,"_",O8,"_",Q8,"_",S8,"_",U8,"_",Y8,"_",AA8,"_",AB8,"_",AD8,".odm",AE8)),IF(AE8="",_xlfn.CONCAT(K8,"_",M8,"_",W8,"_",AD8),_xlfn.CONCAT(K8,"_",M8,"_",W8,"_",AD8,".odm",AE8))),"NA") -> 0 | H8: =IF(I8="attributes",IF(AE8="",_xlfn.CONCAT(K8,"_",AD8),_xlfn.CONCAT(K8,"_",AD8,".odm",AE8)),"NA") -> 0 | I8: attributes | J8: Sample report table Shorthand | K8: =IFERROR(VLOOKUP(J8,'wideName-Dropdowns'!$A:$B,2,FALSE),"") -> 0 | M8: =IFERROR(VLOOKUP(L8,'wideName-Dropdowns'!$C:$D,2,FALSE),"") -> 0 | O8: =IFERROR(VLOOKUP(N8,'wideName-Dropdowns'!$E:$F,2,FALSE),"") -> 0 | Q8: =IFERROR(VLOOKUP(P8,'wideName-Dropdowns'!$G:$H,2,FALSE),"") -> 0 | S8: =IFERROR(VLOOKUP(R8,'wideName-Dropdowns'!$I:$J,2,FALSE),"") -> 0 | U8: =IFERROR(VLOOKUP(T8,'wideName-Dropdowns'!$K:$L,2,FALSE),"") -> 0 | W8: =IFERROR(VLOOKUP(V8,'wideName-Dropdowns'!$M:$N,2,FALSE),"") -> 0 | Y8: =IFERROR(VLOOKUP(X8,'wideName-Dropdowns'!$O:$P,2,FALSE),"") -> 0 | AA8: =IFERROR(VLOOKUP(Z8,'wideName-Dropdowns'!$Q:$R,2,FALSE),"") -> 0 | AC8: Sample collection type | AD8: =IFERROR(VLOOKUP(AC8,'wideName-Dropdowns'!$S:$T,2,FALSE),"") -> 0
A9: sm_2_collPer_collNum | B9: Composite collection number.period - wide | C9: =LEN(A9) -> 0 | D9: Composite collection number.period in a wide or combined long-and-wide table. | E9: EU Airport template | F9: =IF(I9="measurements",IF(AE9="",_xlfn.CONCAT(O9,"_",Q9,"_",S9,"_",U9,"_",Y9,"_",AA9,"_",AB9,"_",AD9),_xlfn.CONCAT(O9,"_",Q9,"_",S9,"_",U9,"_",Y9,"_",AA9,"_",AB9,"_",AD9,".odm",AE9)),"NA") -> 0 | G9: =IF(I9="methods",IF(L9="measurement",IF(AE9="",_xlfn.CONCAT(K9,"_",M9,"_",O9,"_",Q9,"_",S9,"_",U9,"_",Y9,"_",AA9,"_",AB9,"_",AD9),_xlfn.CONCAT(K9,"_",M9,"_",O9,"_",Q9,"_",S9,"_",U9,"_",Y9,"_",AA9,"_",AB9,"_",AD9,".odm",AE9)),IF(AE9="",_xlfn.CONCAT(K9,"_",M9,"_",W9,"_",AD9),_xlfn.CONCAT(K9,"_",M9,"_",W9,"_",AD9,".odm",AE9))),"NA") -> 0 | H9: =IF(I9="attributes",IF(AE9="",_xlfn.CONCAT(K9,"_",AD9),_xlfn.CONCAT(K9,"_",AD9,".odm",AE9)),"NA") -> 0 | I9: exceptions | K9: =IFERROR(VLOOKUP(J9,'wideName-Dropdowns'!$A:$B,2,FALSE),"") -> 0 | M9: =IFERROR(VLOOKUP(L9,'wideName-Dropdowns'!$C:$D,2,FALSE),"") -> 0 | O9: =IFERROR(VLOOKUP(N9,'wideName-Dropdowns'!$E:$F,2,FALSE),"") -> 0 | Q9: =IFERROR(VLOOKUP(P9,'wideName-Dropdowns'!$G:$H,2,FALSE),"") -> 0 | S9: =IFERROR(VLOOKUP(R9,'wideName-Dropdowns'!$I:$J,2,FALSE),"") -> 0 | U9: =IFERROR(VLOOKUP(T9,'wideName-Dropdowns'!$K:$L,2,FALSE),"") -> 0 | W9: =IFERROR(VLOOKUP(V9,'wideName-Dropdowns'!$M:$N,2,FALSE),"") -> 0 | Y9: =IFERROR(VLOOKUP(X9,'wideName-Dropdowns'!$O:$P,2,FALSE),"") -> 0 | AA9: =IFERROR(VLOOKUP(Z9,'wideName-Dropdowns'!$Q:$R,2,FALSE),"") -> 0 | AD9: =IFERROR(VLOOKUP(AC9,'wideName-Dropdowns'!$S:$T,2,FALSE),"") -> 0
A10: =IF(I10="attributes",H10,IF(I10="measurements",F10,G10)) -> 0 | B10: Pooled | C10: =LEN(A10) -> 0 | D10: Binary indicator for whether a sample is pooled/made by combining multiple distinct samples. | E10: EU Airport template | F10: =IF(I10="measurements",IF(AE10="",_xlfn.CONCAT(O10,"_",Q10,"_",S10,"_",U10,"_",Y10,"_",AA10,"_",AB10,"_",AD10),_xlfn.CONCAT(O10,"_",Q10,"_",S10,"_",U10,"_",Y10,"_",AA10,"_",AB10,"_",AD10,".odm",AE10)),"NA") -> 0 | G10: =IF(I10="methods",IF(L10="measurement",IF(AE10="",_xlfn.CONCAT(K10,"_",M10,"_",O10,"_",Q10,"_",S10,"_",U10,"_",Y10,"_",AA10,"_",AB10,"_",AD10),_xlfn.CONCAT(K10,"_",M10,"_",O10,"_",Q10,"_",S10,"_",U10,"_",Y10,"_",AA10,"_",AB10,"_",AD10,".odm",AE10)),IF(AE10="",_xlfn.CONCAT(K10,"_",M10,"_",W10,"_",AD10),_xlfn.CONCAT(K10,"_",M10,"_",W10,"_",AD10,".odm",AE10))),"NA") -> 0 | H10: =IF(I10="attributes",IF(AE10="",_xlfn.CONCAT(K10,"_",AD10),_xlfn.CONCAT(K10,"_",AD10,".odm",AE10)),"NA") -> 0 | I10: attributes | J10: Sample report table Shorthand | K10: =IFERROR(VLOOKUP(J10,'wideName-Dropdowns'!$A:$B,2,FALSE),"") -> 0 | M10: =IFERROR(VLOOKUP(L10,'wideName-Dropdowns'!$C:$D,2,FALSE),"") -> 0 | O10: =IFERROR(VLOOKUP(N10,'wideName-Dropdowns'!$E:$F,2,FALSE),"") -> 0 | Q10: =IFERROR(VLOOKUP(P10,'wideName-Dropdowns'!$G:$H,2,FALSE),"") -> 0 | S10: =IFERROR(VLOOKUP(R10,'wideName-Dropdowns'!$I:$J,2,FALSE),"") -> 0 | U10: =IFERROR(VLOOKUP(T10,'wideName-Dropdowns'!$K:$L,2,FALSE),"") -> 0 | W10: =IFERROR(VLOOKUP(V10,'wideName-Dropdowns'!$M:$N,2,FALSE),"") -> 0 | Y10: =IFERROR(VLOOKUP(X10,'wideName-Dropdowns'!$O:$P,2,FALSE),"") -> 0 | AA10: =IFERROR(VLOOKUP(Z10,'wideName-Dropdowns'!$Q:$R,2,FALSE),"") -> 0 | AC10: Pooled | AD10: =IFERROR(VLOOKUP(AC10,'wideName-Dropdowns'!$S:$T,2,FALSE),"") -> 0
A11: =IF(I11="attributes",H11,IF(I11="measurements",F11,G11)) -> 0 | B11: Analysis date/time start | C11: =LEN(A11) -> 0 | D11: Date, time, and timezone of when the analysis was started. | E11: EU Airport template | F11: =IF(I11="measurements",IF(AE11="",_xlfn.CONCAT(O11,"_",Q11,"_",S11,"_",U11,"_",Y11,"_",AA11,"_",AB11,"_",AD11),_xlfn.CONCAT(O11,"_",Q11,"_",S11,"_",U11,"_",Y11,"_",AA11,"_",AB11,"_",AD11,".odm",AE11)),"NA") -> 0 | G11: =IF(I11="methods",IF(L11="measurement",IF(AE11="",_xlfn.CONCAT(K11,"_",M11,"_",O11,"_",Q11,"_",S11,"_",U11,"_",Y11,"_",AA11,"_",AB11,"_",AD11),_xlfn.CONCAT(K11,"_",M11,"_",O11,"_",Q11,"_",S11,"_",U11,"_",Y11,"_",AA11,"_",AB11,"_",AD11,".odm",AE11)),IF(AE11="",_xlfn.CONCAT(K11,"_",M11,"_",W11,"_",AD11),_xlfn.CONCAT(K11,"_",M11,"_",W11,"_",AD11,".odm",AE11))),"NA") -> 0 | H11: =IF(I11="attributes",IF(AE11="",_xlfn.CONCAT(K11,"_",AD11),_xlfn.CONCAT(K11,"_",AD11,".odm",AE11)),"NA") -> 0 | I11: attributes | J11: Measure report table Shorthand | K11: =IFERROR(VLOOKUP(J11,'wideName-Dropdowns'!$A:$B,2,FALSE),"") -> 0 | M11: =IFERROR(VLOOKUP(L11,'wideName-Dropdowns'!$C:$D,2,FALSE),"") -> 0 | O11: =IFERROR(VLOOKUP(N11,'wideName-Dropdowns'!$E:$F,2,FALSE),"") -> 0 | Q11: =IFERROR(VLOOKUP(P11,'wideName-Dropdowns'!$G:$H,2,FALSE),"") -> 0 | S11: =IFERROR(VLOOKUP(R11,'wideName-Dropdowns'!$I:$J,2,FALSE),"") -> 0 | U11: =IFERROR(VLOOKUP(T11,'wideName-Dropdowns'!$K:$L,2,FALSE),"") -> 0 | W11: =IFERROR(VLOOKUP(V11,'wideName-Dropdowns'!$M:$N,2,FALSE),"") -> 0 | Y11: =IFERROR(VLOOKUP(X11,'wideName-Dropdowns'!$O:$P,2,FALSE),"") -> 0 | AA11: =IFERROR(VLOOKUP(Z11,'wideName-Dropdowns'!$Q:$R,2,FALSE),"") -> 0 | AC11: Analysis date start | AD11: =IFERROR(VLOOKUP(AC11,'wideName-Dropdowns'!$S:$T,2,FALSE),"") -> 0
A12: =IF(I12="attributes",H12,IF(I12="measurements",F12,G12)) -> 0 | B12: Analysis date/time end | C12: =LEN(A12) -> 0 | D12: Date, time, and timezone of when the analysis was completed. | E12: EU Airport template | F12: =IF(I12="measurements",IF(AE12="",_xlfn.CONCAT(O12,"_",Q12,"_",S12,"_",U12,"_",Y12,"_",AA12,"_",AB12,"_",AD12),_xlfn.CONCAT(O12,"_",Q12,"_",S12,"_",U12,"_",Y12,"_",AA12,"_",AB12,"_",AD12,".odm",AE12)),"NA") -> 0 | G12: =IF(I12="methods",IF(L12="measurement",IF(AE12="",_xlfn.CONCAT(K12,"_",M12,"_",O12,"_",Q12,"_",S12,"_",U12,"_",Y12,"_",AA12,"_",AB12,"_",AD12),_xlfn.CONCAT(K12,"_",M12,"_",O12,"_",Q12,"_",S12,"_",U12,"_",Y12,"_",AA12,"_",AB12,"_",AD12,".odm",AE12)),IF(AE12="",_xlfn.CONCAT(K12,"_",M12,"_",W12,"_",AD12),_xlfn.CONCAT(K12,"_",M12,"_",W12,"_",AD12,".odm",AE12))),"NA") -> 0 | H12: =IF(I12="attributes",IF(AE12="",_xlfn.CONCAT(K12,"_",AD12),_xlfn.CONCAT(K12,"_",AD12,".odm",AE12)),"NA") -> 0 | I12: attributes | J12: Measure report table Shorthand | K12: =IFERROR(VLOOKUP(J12,'wideName-Dropdowns'!$A:$B,2,FALSE),"") -> 0 | M12: =IFERROR(VLOOKUP(L12,'wideName-Dropdowns'!$C:$D,2,FALSE),"") -> 0 | O12: =IFERROR(VLOOKUP(N12,'wideName-Dropdowns'!$E:$F,2,FALSE),"") -> 0 | Q12: =IFERROR(VLOOKUP(P12,'wideName-Dropdowns'!$G:$H,2,FALSE),"") -> 0 | S12: =IFERROR(VLOOKUP(R12,'wideName-Dropdowns'!$I:$J,2,FALSE),"") -> 0 | U12: =IFERROR(VLOOKUP(T12,'wideName-Dropdowns'!$K:$L,2,FALSE),"") -> 0 | W12: =IFERROR(VLOOKUP(V12,'wideName-Dropdowns'!$M:$N,2,FALSE),"") -> 0 | Y12: =IFERROR(VLOOKUP(X12,'wideName-Dropdowns'!$O:$P,2,FALSE),"") -> 0 | AA12: =IFERROR(VLOOKUP(Z12,'wideName-Dropdowns'!$Q:$R,2,FALSE),"") -> 0 | AC12: Analysis date end | AD12: =IFERROR(VLOOKUP(AC12,'wideName-Dropdowns'!$S:$T,2,FALSE),"") -> 0
A13: =IF(I13="attributes",H13,IF(I13="measurements",F13,G13)) -> 0 | B13: Fraction analyzed | C13: =LEN(A13) -> 0 | D13: The fraction of the wastewater used for analysis and measurement. | E13: EU Airport template | F13: =IF(I13="measurements",IF(AE13="",_xlfn.CONCAT(O13,"_",Q13,"_",S13,"_",U13,"_",Y13,"_",AA13,"_",AB13,"_",AD13),_xlfn.CONCAT(O13,"_",Q13,"_",S13,"_",U13,"_",Y13,"_",AA13,"_",AB13,"_",AD13,".odm",AE13)),"NA") -> 0 | G13: =IF(I13="methods",IF(L13="measurement",IF(AE13="",_xlfn.CONCAT(K13,"_",M13,"_",O13,"_",Q13,"_",S13,"_",U13,"_",Y13,"_",AA13,"_",AB13,"_",AD13),_xlfn.CONCAT(K13,"_",M13,"_",O13,"_",Q13,"_",S13,"_",U13,"_",Y13,"_",AA13,"_",AB13,"_",AD13,".odm",AE13)),IF(AE13="",_xlfn.CONCAT(K13,"_",M13,"_",W13,"_",AD13),_xlfn.CONCAT(K13,"_",M13,"_",W13,"_",AD13,".odm",AE13))),"NA") -> 0 | H13: =IF(I13="attributes",IF(AE13="",_xlfn.CONCAT(K13,"_",AD13),_xlfn.CONCAT(K13,"_",AD13,".odm",AE13)),"NA") -> 0 | I13: attributes | J13: Measure report table Shorthand | K13: =IFERROR(VLOOKUP(J13,'wideName-Dropdowns'!$A:$B,2,FALSE),"") -> 0 | M13: =IFERROR(VLOOKUP(L13,'wideName-Dropdowns'!$C:$D,2,FALSE),"") -> 0 | O13: =IFERROR(VLOOKUP(N13,'wideName-Dropdowns'!$E:$F,2,FALSE),"") -> 0 | Q13: =IFERROR(VLOOKUP(P13,'wideName-Dropdowns'!$G:$H,2,FALSE),"") -> 0 | S13: =IFERROR(VLOOKUP(R13,'wideName-Dropdowns'!$I:$J,2,FALSE),"") -> 0 | U13: =IFERROR(VLOOKUP(T13,'wideName-Dropdowns'!$K:$L,2,FALSE),"") -> 0 | W13: =IFERROR(VLOOKUP(V13,'wideName-Dropdowns'!$M:$N,2,FALSE),"") -> 0 | Y13: =IFERROR(VLOOKUP(X13,'wideName-Dropdowns'!$O:$P,2,FALSE),"") -> 0 | AA13: =IFERROR(VLOOKUP(Z13,'wideName-Dropdowns'!$Q:$R,2,FALSE),"") -> 0 | AC13: Fraction analyzed | AD13: =IFERROR(VLOOKUP(AC13,'wideName-Dropdowns'!$S:$T,2,FALSE),"") -> 0
A14: =IF(I14="attributes",H14,IF(I14="measurements",F14,G14)) -> 0 | B14: Sample type | C14: =LEN(A14) -> 0 | D14: The type of sample. | E14: EU Airport template | F14: =IF(I14="measurements",IF(AE14="",_xlfn.CONCAT(O14,"_",Q14,"_",S14,"_",U14,"_",Y14,"_",AA14,"_",AB14,"_",AD14),_xlfn.CONCAT(O14,"_",Q14,"_",S14,"_",U14,"_",Y14,"_",AA14,"_",AB14,"_",AD14,".odm",AE14)),"NA") -> 0 | G14: =IF(I14="methods",IF(L14="measurement",IF(AE14="",_xlfn.CONCAT(K14,"_",M14,"_",O14,"_",Q14,"_",S14,"_",U14,"_",Y14,"_",AA14,"_",AB14,"_",AD14),_xlfn.CONCAT(K14,"_",M14,"_",O14,"_",Q14,"_",S14,"_",U14,"_",Y14,"_",AA14,"_",AB14,"_",AD14,".odm",AE14)),IF(AE14="",_xlfn.CONCAT(K14,"_",M14,"_",W14,"_",AD14),_xlfn.CONCAT(K14,"_",M14,"_",W14,"_",AD14,".odm",AE14))),"NA") -> 0 | H14: =IF(I14="attributes",IF(AE14="",_xlfn.CONCAT(K14,"_",AD14),_xlfn.CONCAT(K14,"_",AD14,".odm",AE14)),"NA") -> 0 | I14: attributes | J14: Sample report table Shorthand | K14: =IFERROR(VLOOKUP(J14,'wideName-Dropdowns'!$A:$B,2,FALSE),"") -> 0 | M14: =IFERROR(VLOOKUP(L14,'wideName-Dropdowns'!$C:$D,2,FALSE),"") -> 0 | O14: =IFERROR(VLOOKUP(N14,'wideName-Dropdowns'!$E:$F,2,FALSE),"") -> 0 | Q14: =IFERROR(VLOOKUP(P14,'wideName-Dropdowns'!$G:$H,2,FALSE),"") -> 0 | S14: =IFERROR(VLOOKUP(R14,'wideName-Dropdowns'!$I:$J,2,FALSE),"") -> 0 | U14: =IFERROR(VLOOKUP(T14,'wideName-Dropdowns'!$K:$L,2,FALSE),"") -> 0 | W14: =IFERROR(VLOOKUP(V14,'wideName-Dropdowns'!$M:$N,2,FALSE),"") -> 0 | Y14: =IFERROR(VLOOKUP(X14,'wideName-Dropdowns'!$O:$P,2,FALSE),"") -> 0 | AA14: =IFERROR(VLOOKUP(Z14,'wideName-Dropdowns'!$Q:$R,2,FALSE),"") -> 0 | AC14: Sample material | AD14: =IFERROR(VLOOKUP(AC14,'wideName-Dropdowns'!$S:$T,2,FALSE),"") -> 0
A15: ps_met_wat_sa_hFr_OR_2_pcrmeth_seqStrat_value | B15: Method used | C15: =LEN(A15) -> 0 | D15: The value for either the PCR method used, or the sequencing strategy used to obstain a measure in a wide or combined long-and-wide table. | E15: EU Airport template | F15: =IF(I15="measurements",IF(AE15="",_xlfn.CONCAT(O15,"_",Q15,"_",S15,"_",U15,"_",Y15,"_",AA15,"_",AB15,"_",AD15),_xlfn.CONCAT(O15,"_",Q15,"_",S15,"_",U15,"_",Y15,"_",AA15,"_",AB15,"_",AD15,".odm",AE15)),"NA") -> 0 | G15: =IF(I15="methods",IF(L15="measurement",IF(AE15="",_xlfn.CONCAT(K15,"_",M15,"_",O15,"_",Q15,"_",S15,"_",U15,"_",Y15,"_",AA15,"_",AB15,"_",AD15),_xlfn.CONCAT(K15,"_",M15,"_",O15,"_",Q15,"_",S15,"_",U15,"_",Y15,"_",AA15,"_",AB15,"_",AD15,".odm",AE15)),IF(AE15="",_xlfn.CONCAT(K15,"_",M15,"_",W15,"_",AD15),_xlfn.CONCAT(K15,"_",M15,"_",W15,"_",AD15,".odm",AE15))),"NA") -> 0 | H15: =IF(I15="attributes",IF(AE15="",_xlfn.CONCAT(K15,"_",AD15),_xlfn.CONCAT(K15,"_",AD15,".odm",AE15)),"NA") -> 0 | I15: exceptions | K15: =IFERROR(VLOOKUP(J15,'wideName-Dropdowns'!$A:$B,2,FALSE),"") -> 0 | M15: =IFERROR(VLOOKUP(L15,'wideName-Dropdowns'!$C:$D,2,FALSE),"") -> 0 | O15: =IFERROR(VLOOKUP(N15,'wideName-Dropdowns'!$E:$F,2,FALSE),"") -> 0 | Q15: =IFERROR(VLOOKUP(P15,'wideName-Dropdowns'!$G:$H,2,FALSE),"") -> 0 | S15: =IFERROR(VLOOKUP(R15,'wideName-Dropdowns'!$I:$J,2,FALSE),"") -> 0 | U15: =IFERROR(VLOOKUP(T15,'wideName-Dropdowns'!$K:$L,2,FALSE),"") -> 0 | W15: =IFERROR(VLOOKUP(V15,'wideName-Dropdowns'!$M:$N,2,FALSE),"") -> 0 | Y15: =IFERROR(VLOOKUP(X15,'wideName-Dropdowns'!$O:$P,2,FALSE),"") -> 0 | AA15: =IFERROR(VLOOKUP(Z15,'wideName-Dropdowns'!$Q:$R,2,FALSE),"") -> 0 | AD15: =IFERROR(VLOOKUP(AC15,'wideName-Dropdowns'!$S:$T,2,FALSE),"") -> 0
A16: =IF(I16="attributes",H16,IF(I16="measurements",F16,G16)) -> 0 | B16: Protocol citation link | C16: =LEN(A16) -> 0 | D16: Reference link for a specific protocol. | E16: EU Airport template | F16: =IF(I16="measurements",IF(AE16="",_xlfn.CONCAT(O16,"_",Q16,"_",S16,"_",U16,"_",Y16,"_",AA16,"_",AB16,"_",AD16),_xlfn.CONCAT(O16,"_",Q16,"_",S16,"_",U16,"_",Y16,"_",AA16,"_",AB16,"_",AD16,".odm",AE16)),"NA") -> 0 | G16: =IF(I16="methods",IF(L16="measurement",IF(AE16="",_xlfn.CONCAT(K16,"_",M16,"_",O16,"_",Q16,"_",S16,"_",U16,"_",Y16,"_",AA16,"_",AB16,"_",AD16),_xlfn.CONCAT(K16,"_",M16,"_",O16,"_",Q16,"_",S16,"_",U16,"_",Y16,"_",AA16,"_",AB16,"_",AD16,".odm",AE16)),IF(AE16="",_xlfn.CONCAT(K16,"_",M16,"_",W16,"_",AD16),_xlfn.CONCAT(K16,"_",M16,"_",W16,"_",AD16,".odm",AE16))),"NA") -> 0 | H16: =IF(I16="attributes",IF(AE16="",_xlfn.CONCAT(K16,"_",AD16),_xlfn.CONCAT(K16,"_",AD16,".odm",AE16)),"NA") -> 0 | I16: attributes | J16: Protocols table Shorthand | K16: =IFERROR(VLOOKUP(J16,'wideName-Dropdowns'!$A:$B,2,FALSE),"") -> 0 | M16: =IFERROR(VLOOKUP(L16,'wideName-Dropdowns'!$C:$D,2,FALSE),"") -> 0 | O16: =IFERROR(VLOOKUP(N16,'wideName-Dropdowns'!$E:$F,2,FALSE),"") -> 0 | Q16: =IFERROR(VLOOKUP(P16,'wideName-Dropdowns'!$G:$H,2,FALSE),"") -> 0 | S16: =IFERROR(VLOOKUP(R16,'wideName-Dropdowns'!$I:$J,2,FALSE),"") -> 0 | U16: =IFERROR(VLOOKUP(T16,'wideName-Dropdowns'!$K:$L,2,FALSE),"") -> 0 | W16: =IFERROR(VLOOKUP(V16,'wideName-Dropdowns'!$M:$N,2,FALSE),"") -> 0 | Y16: =IFERROR(VLOOKUP(X16,'wideName-Dropdowns'!$O:$P,2,FALSE),"") -> 0 | AA16: =IFERROR(VLOOKUP(Z16,'wideName-Dropdowns'!$Q:$R,2,FALSE),"") -> 0 | AC16: Reference link | AD16: =IFERROR(VLOOKUP(AC16,'wideName-Dropdowns'!$S:$T,2,FALSE),"") -> 0
A17: =IF(I17="attributes",H17,IF(I17="measurements",F17,G17)) -> 0 | B17: Target Type | C17: =LEN(A17) -> 0 | D17: The genetic "target type" as defined using ODM classes in a wide or combined long-and-wide table. | E17: EU Airport template | F17: =IF(I17="measurements",IF(AE17="",_xlfn.CONCAT(O17,"_",Q17,"_",S17,"_",U17,"_",Y17,"_",AA17,"_",AB17,"_",AD17),_xlfn.CONCAT(O17,"_",Q17,"_",S17,"_",U17,"_",Y17,"_",AA17,"_",AB17,"_",AD17,".odm",AE17)),"NA") -> 0 | G17: =IF(I17="methods",IF(L17="measurement",IF(AE17="",_xlfn.CONCAT(K17,"_",M17,"_",O17,"_",Q17,"_",S17,"_",U17,"_",Y17,"_",AA17,"_",AB17,"_",AD17),_xlfn.CONCAT(K17,"_",M17,"_",O17,"_",Q17,"_",S17,"_",U17,"_",Y17,"_",AA17,"_",AB17,"_",AD17,".odm",AE17)),IF(AE17="",_xlfn.CONCAT(K17,"_",M17,"_",W17,"_",AD17),_xlfn.CONCAT(K17,"_",M17,"_",W17,"_",AD17,".odm",AE17))),"NA") -> 0 | H17: =IF(I17="attributes",IF(AE17="",_xlfn.CONCAT(K17,"_",AD17),_xlfn.CONCAT(K17,"_",AD17,".odm",AE17)),"NA") -> 0 | I17: attributes | J17: Measure report table Shorthand | K17: =IFERROR(VLOOKUP(J17,'wideName-Dropdowns'!$A:$B,2,FALSE),"") -> 0 | M17: =IFERROR(VLOOKUP(L17,'wideName-Dropdowns'!$C:$D,2,FALSE),"") -> 0 | O17: =IFERROR(VLOOKUP(N17,'wideName-Dropdowns'!$E:$F,2,FALSE),"") -> 0 | Q17: =IFERROR(VLOOKUP(P17,'wideName-Dropdowns'!$G:$H,2,FALSE),"") -> 0 | S17: =IFERROR(VLOOKUP(R17,'wideName-Dropdowns'!$I:$J,2,FALSE),"") -> 0 | U17: =IFERROR(VLOOKUP(T17,'wideName-Dropdowns'!$K:$L,2,FALSE),"") -> 0 | W17: =IFERROR(VLOOKUP(V17,'wideName-Dropdowns'!$M:$N,2,FALSE),"") -> 0 | Y17: =IFERROR(VLOOKUP(X17,'wideName-Dropdowns'!$O:$P,2,FALSE),"") -> 0 | AA17: =IFERROR(VLOOKUP(Z17,'wideName-Dropdowns'!$Q:$R,2,FALSE),"") -> 0 | AC17: Class | AD17: =IFERROR(VLOOKUP(AC17,'wideName-Dropdowns'!$S:$T,2,FALSE),"") -> 0
A18: =IF(I18="attributes",H18,IF(I18="measurements",F18,G18)) -> 0 | B18: Target | C18: =LEN(A18) -> 0 | D18: The genetic target or measure of an analysis in a wide or combined long-and-wide table. | E18: EU Airport template | F18: =IF(I18="measurements",IF(AE18="",_xlfn.CONCAT(O18,"_",Q18,"_",S18,"_",U18,"_",Y18,"_",AA18,"_",AB18,"_",AD18),_xlfn.CONCAT(O18,"_",Q18,"_",S18,"_",U18,"_",Y18,"_",AA18,"_",AB18,"_",AD18,".odm",AE18)),"NA") -> 0 | G18: =IF(I18="methods",IF(L18="measurement",IF(AE18="",_xlfn.CONCAT(K18,"_",M18,"_",O18,"_",Q18,"_",S18,"_",U18,"_",Y18,"_",AA18,"_",AB18,"_",AD18),_xlfn.CONCAT(K18,"_",M18,"_",O18,"_",Q18,"_",S18,"_",U18,"_",Y18,"_",AA18,"_",AB18,"_",AD18,".odm",AE18)),IF(AE18="",_xlfn.CONCAT(K18,"_",M18,"_",W18,"_",AD18),_xlfn.CONCAT(K18,"_",M18,"_",W18,"_",AD18,".odm",AE18))),"NA") -> 0 | H18: =IF(I18="attributes",IF(AE18="",_xlfn.CONCAT(K18,"_",AD18),_xlfn.CONCAT(K18,"_",AD18,".odm",AE18)),"NA") -> 0 | I18: attributes | J18: Measure report table Shorthand | K18: =IFERROR(VLOOKUP(J18,'wideName-Dropdowns'!$A:$B,2,FALSE),"") -> 0 | M18: =IFERROR(VLOOKUP(L18,'wideName-Dropdowns'!$C:$D,2,FALSE),"") -> 0 | O18: =IFERROR(VLOOKUP(N18,'wideName-Dropdowns'!$E:$F,2,FALSE),"") -> 0 | Q18: =IFERROR(VLOOKUP(P18,'wideName-Dropdowns'!$G:$H,2,FALSE),"") -> 0 | S18: =IFERROR(VLOOKUP(R18,'wideName-Dropdowns'!$I:$J,2,FALSE),"") -> 0 | U18: =IFERROR(VLOOKUP(T18,'wideName-Dropdowns'!$K:$L,2,FALSE),"") -> 0 | W18: =IFERROR(VLOOKUP(V18,'wideName-Dropdowns'!$M:$N,2,FALSE),"") -> 0 | Y18: =IFERROR(VLOOKUP(X18,'wideName-Dropdowns'!$O:$P,2,FALSE),"") -> 0 | AA18: =IFERROR(VLOOKUP(Z18,'wideName-Dropdowns'!$Q:$R,2,FALSE),"") -> 0 | AC18: Measure | AD18: =IFERROR(VLOOKUP(AC18,'wideName-Dropdowns'!$S:$T,2,FALSE),"") -> 0
A19: wat_sa_hFr_OR_3_otherM_otherA_otherV_hUn_hAg_value | B19: Target Other Specify | C19: =LEN(A19) -> 0 | D19: Value for an unlisted genetic target for either a mutation, an allele, or a variant in a wide or combined long-and-wide table. | E19: EU Airport template | F19: =IF(I19="measurements",IF(AE19="",_xlfn.CONCAT(O19,"_",Q19,"_",S19,"_",U19,"_",Y19,"_",AA19,"_",AB19,"_",AD19),_xlfn.CONCAT(O19,"_",Q19,"_",S19,"_",U19,"_",Y19,"_",AA19,"_",AB19,"_",AD19,".odm",AE19)),"NA") -> 0 | G19: =IF(I19="methods",IF(L19="measurement",IF(AE19="",_xlfn.CONCAT(K19,"_",M19,"_",O19,"_",Q19,"_",S19,"_",U19,"_",Y19,"_",AA19,"_",AB19,"_",AD19),_xlfn.CONCAT(K19,"_",M19,"_",O19,"_",Q19,"_",S19,"_",U19,"_",Y19,"_",AA19,"_",AB19,"_",AD19,".odm",AE19)),IF(AE19="",_xlfn.CONCAT(K19,"_",M19,"_",W19,"_",AD19),_xlfn.CONCAT(K19,"_",M19,"_",W19,"_",AD19,".odm",AE19))),"NA") -> 0 | H19: =IF(I19="attributes",IF(AE19="",_xlfn.CONCAT(K19,"_",AD19),_xlfn.CONCAT(K19,"_",AD19,".odm",AE19)),"NA") -> 0 | I19: exceptions | K19: =IFERROR(VLOOKUP(J19,'wideName-Dropdowns'!$A:$B,2,FALSE),"") -> 0 | M19: =IFERROR(VLOOKUP(L19,'wideName-Dropdowns'!$C:$D,2,FALSE),"") -> 0 | O19: =IFERROR(VLOOKUP(N19,'wideName-Dropdowns'!$E:$F,2,FALSE),"") -> 0 | Q19: =IFERROR(VLOOKUP(P19,'wideName-Dropdowns'!$G:$H,2,FALSE),"") -> 0 | S19: =IFERROR(VLOOKUP(R19,'wideName-Dropdowns'!$I:$J,2,FALSE),"") -> 0 | U19: =IFERROR(VLOOKUP(T19,'wideName-Dropdowns'!$K:$L,2,FALSE),"") -> 0 | W19: =IFERROR(VLOOKUP(V19,'wideName-Dropdowns'!$M:$N,2,FALSE),"") -> 0 | Y19: =IFERROR(VLOOKUP(X19,'wideName-Dropdowns'!$O:$P,2,FALSE),"") -> 0 | AA19: =IFERROR(VLOOKUP(Z19,'wideName-Dropdowns'!$Q:$R,2,FALSE),"") -> 0 | AD19: =IFERROR(VLOOKUP(AC19,'wideName-Dropdowns'!$S:$T,2,FALSE),"") -> 0
A20: =IF(I20="attributes",H20,IF(I20="measurements",F20,G20)) -> 0 | B20: Value - wide | C20: =LEN(A20) -> 0 | D20: Measure value in a wide or combined long-and-wide table where most details are recorded in other columns. | E20: EU Airport template | F20: =IF(I20="measurements",IF(AE20="",_xlfn.CONCAT(O20,"_",Q20,"_",S20,"_",U20,"_",Y20,"_",AA20,"_",AB20,"_",AD20),_xlfn.CONCAT(O20,"_",Q20,"_",S20,"_",U20,"_",Y20,"_",AA20,"_",AB20,"_",AD20,".odm",AE20)),"NA") -> 0 | G20: =IF(I20="methods",IF(L20="measurement",IF(AE20="",_xlfn.CONCAT(K20,"_",M20,"_",O20,"_",Q20,"_",S20,"_",U20,"_",Y20,"_",AA20,"_",AB20,"_",AD20),_xlfn.CONCAT(K20,"_",M20,"_",O20,"_",Q20,"_",S20,"_",U20,"_",Y20,"_",AA20,"_",AB20,"_",AD20,".odm",AE20)),IF(AE20="",_xlfn.CONCAT(K20,"_",M20,"_",W20,"_",AD20),_xlfn.CONCAT(K20,"_",M20,"_",W20,"_",AD20,".odm",AE20))),"NA") -> 0 | H20: =IF(I20="attributes",IF(AE20="",_xlfn.CONCAT(K20,"_",AD20),_xlfn.CONCAT(K20,"_",AD20,".odm",AE20)),"NA") -> 0 | I20: measurements | K20: =IFERROR(VLOOKUP(J20,'wideName-Dropdowns'!$A:$B,2,FALSE),"") -> 0 | M20: =IFERROR(VLOOKUP(L20,'wideName-Dropdowns'!$C:$D,2,FALSE),"") -> 0 | N20: Water compartment | O20: =IFERROR(VLOOKUP(N20,'wideName-Dropdowns'!$E:$F,2,FALSE),"") -> 0 | P20: Sample | Q20: =IFERROR(VLOOKUP(P20,'wideName-Dropdowns'!$G:$H,2,FALSE),"") -> 0 | R20: See Header for Fraction Analyzed | S20: =IFERROR(VLOOKUP(R20,'wideName-Dropdowns'!$I:$J,2,FALSE),"") -> 0 | T20: See Header for Measure | U20: =IFERROR(VLOOKUP(T20,'wideName-Dropdowns'!$K:$L,2,FALSE),"") -> 0 | W20: =IFERROR(VLOOKUP(V20,'wideName-Dropdowns'!$M:$N,2,FALSE),"") -> 0 | X20: See Header for Unit | Y20: =IFERROR(VLOOKUP(X20,'wideName-Dropdowns'!$O:$P,2,FALSE),"") -> 0 | Z20: See Header for Aggregation | AA20: =IFERROR(VLOOKUP(Z20,'wideName-Dropdowns'!$Q:$R,2,FALSE),"") -> 0 | AB20: NR | AC20: Value | AD20: =IFERROR(VLOOKUP(AC20,'wideName-Dropdowns'!$S:$T,2,FALSE),"") -> 0
A21: =IF(I21="attributes",H21,IF(I21="measurements",F21,G21)) -> 0 | B21: Unit - wide | C21: =LEN(A21) -> 0 | D21: The unit of a measure in a wide or combined long-and-wide table. | E21: EU Airport template | F21: =IF(I21="measurements",IF(AE21="",_xlfn.CONCAT(O21,"_",Q21,"_",S21,"_",U21,"_",Y21,"_",AA21,"_",AB21,"_",AD21),_xlfn.CONCAT(O21,"_",Q21,"_",S21,"_",U21,"_",Y21,"_",AA21,"_",AB21,"_",AD21,".odm",AE21)),"NA") -> 0 | G21: =IF(I21="methods",IF(L21="measurement",IF(AE21="",_xlfn.CONCAT(K21,"_",M21,"_",O21,"_",Q21,"_",S21,"_",U21,"_",Y21,"_",AA21,"_",AB21,"_",AD21),_xlfn.CONCAT(K21,"_",M21,"_",O21,"_",Q21,"_",S21,"_",U21,"_",Y21,"_",AA21,"_",AB21,"_",AD21,".odm",AE21)),IF(AE21="",_xlfn.CONCAT(K21,"_",M21,"_",W21,"_",AD21),_xlfn.CONCAT(K21,"_",M21,"_",W21,"_",AD21,".odm",AE21))),"NA") -> 0 | H21: =IF(I21="attributes",IF(AE21="",_xlfn.CONCAT(K21,"_",AD21),_xlfn.CONCAT(K21,"_",AD21,".odm",AE21)),"NA") -> 0 | I21: attributes | J21: Measure report table Shorthand | K21: =IFERROR(VLOOKUP(J21,'wideName-Dropdowns'!$A:$B,2,FALSE),"") -> 0 | M21: =IFERROR(VLOOKUP(L21,'wideName-Dropdowns'!$C:$D,2,FALSE),"") -> 0 | O21: =IFERROR(VLOOKUP(N21,'wideName-Dropdowns'!$E:$F,2,FALSE),"") -> 0 | Q21: =IFERROR(VLOOKUP(P21,'wideName-Dropdowns'!$G:$H,2,FALSE),"") -> 0 | S21: =IFERROR(VLOOKUP(R21,'wideName-Dropdowns'!$I:$J,2,FALSE),"") -> 0 | U21: =IFERROR(VLOOKUP(T21,'wideName-Dropdowns'!$K:$L,2,FALSE),"") -> 0 | W21: =IFERROR(VLOOKUP(V21,'wideName-Dropdowns'!$M:$N,2,FALSE),"") -> 0 | Y21: =IFERROR(VLOOKUP(X21,'wideName-Dropdowns'!$O:$P,2,FALSE),"") -> 0 | AA21: =IFERROR(VLOOKUP(Z21,'wideName-Dropdowns'!$Q:$R,2,FALSE),"") -> 0 | AC21: Unit | AD21: =IFERROR(VLOOKUP(AC21,'wideName-Dropdowns'!$S:$T,2,FALSE),"") -> 0
A22: =IF(I22="attributes",H22,IF(I22="measurements",F22,G22)) -> 0 | B22: Aggregation - wide | C22: =LEN(A22) -> 0 | D22: The aggregation of a measure in a wide or combined long-and-wide table. | E22: EU Airport template | F22: =IF(I22="measurements",IF(AE22="",_xlfn.CONCAT(O22,"_",Q22,"_",S22,"_",U22,"_",Y22,"_",AA22,"_",AB22,"_",AD22),_xlfn.CONCAT(O22,"_",Q22,"_",S22,"_",U22,"_",Y22,"_",AA22,"_",AB22,"_",AD22,".odm",AE22)),"NA") -> 0 | G22: =IF(I22="methods",IF(L22="measurement",IF(AE22="",_xlfn.CONCAT(K22,"_",M22,"_",O22,"_",Q22,"_",S22,"_",U22,"_",Y22,"_",AA22,"_",AB22,"_",AD22),_xlfn.CONCAT(K22,"_",M22,"_",O22,"_",Q22,"_",S22,"_",U22,"_",Y22,"_",AA22,"_",AB22,"_",AD22,".odm",AE22)),IF(AE22="",_xlfn.CONCAT(K22,"_",M22,"_",W22,"_",AD22),_xlfn.CONCAT(K22,"_",M22,"_",W22,"_",AD22,".odm",AE22))),"NA") -> 0 | H22: =IF(I22="attributes",IF(AE22="",_xlfn.CONCAT(K22,"_",AD22),_xlfn.CONCAT(K22,"_",AD22,".odm",AE22)),"NA") -> 0 | I22: attributes | J22: Measure report table Shorthand | K22: =IFERROR(VLOOKUP(J22,'wideName-Dropdowns'!$A:$B,2,FALSE),"") -> 0 | M22: =IFERROR(VLOOKUP(L22,'wideName-Dropdowns'!$C:$D,2,FALSE),"") -> 0 | O22: =IFERROR(VLOOKUP(N22,'wideName-Dropdowns'!$E:$F,2,FALSE),"") -> 0 | Q22: =IFERROR(VLOOKUP(P22,'wideName-Dropdowns'!$G:$H,2,FALSE),"") -> 0 | S22: =IFERROR(VLOOKUP(R22,'wideName-Dropdowns'!$I:$J,2,FALSE),"") -> 0 | U22: =IFERROR(VLOOKUP(T22,'wideName-Dropdowns'!$K:$L,2,FALSE),"") -> 0 | W22: =IFERROR(VLOOKUP(V22,'wideName-Dropdowns'!$M:$N,2,FALSE),"") -> 0 | Y22: =IFERROR(VLOOKUP(X22,'wideName-Dropdowns'!$O:$P,2,FALSE),"") -> 0 | AA22: =IFERROR(VLOOKUP(Z22,'wideName-Dropdowns'!$Q:$R,2,FALSE),"") -> 0 | AC22: Aggregation | AD22: =IFERROR(VLOOKUP(AC22,'wideName-Dropdowns'!$S:$T,2,FALSE),"") -> 0
A23: =IF(I23="attributes",H23,IF(I23="measurements",F23,G23)) -> 0 | B23: Sequence / Sequence URL | C23: =LEN(A23) -> 0 | D23: The reference link for a sequencing measure in a wide or combined long-and-wide table. | E23: EU Airport template | F23: =IF(I23="measurements",IF(AE23="",_xlfn.CONCAT(O23,"_",Q23,"_",S23,"_",U23,"_",Y23,"_",AA23,"_",AB23,"_",AD23),_xlfn.CONCAT(O23,"_",Q23,"_",S23,"_",U23,"_",Y23,"_",AA23,"_",AB23,"_",AD23,".odm",AE23)),"NA") -> 0 | G23: =IF(I23="methods",IF(L23="measurement",IF(AE23="",_xlfn.CONCAT(K23,"_",M23,"_",O23,"_",Q23,"_",S23,"_",U23,"_",Y23,"_",AA23,"_",AB23,"_",AD23),_xlfn.CONCAT(K23,"_",M23,"_",O23,"_",Q23,"_",S23,"_",U23,"_",Y23,"_",AA23,"_",AB23,"_",AD23,".odm",AE23)),IF(AE23="",_xlfn.CONCAT(K23,"_",M23,"_",W23,"_",AD23),_xlfn.CONCAT(K23,"_",M23,"_",W23,"_",AD23,".odm",AE23))),"NA") -> 0 | H23: =IF(I23="attributes",IF(AE23="",_xlfn.CONCAT(K23,"_",AD23),_xlfn.CONCAT(K23,"_",AD23,".odm",AE23)),"NA") -> 0 | I23: attributes | J23: Measure report table Shorthand | K23: =IFERROR(VLOOKUP(J23,'wideName-Dropdowns'!$A:$B,2,FALSE),"") -> 0 | M23: =IFERROR(VLOOKUP(L23,'wideName-Dropdowns'!$C:$D,2,FALSE),"") -> 0 | O23: =IFERROR(VLOOKUP(N23,'wideName-Dropdowns'!$E:$F,2,FALSE),"") -> 0 | Q23: =IFERROR(VLOOKUP(P23,'wideName-Dropdowns'!$G:$H,2,FALSE),"") -> 0 | S23: =IFERROR(VLOOKUP(R23,'wideName-Dropdowns'!$I:$J,2,FALSE),"") -> 0 | U23: =IFERROR(VLOOKUP(T23,'wideName-Dropdowns'!$K:$L,2,FALSE),"") -> 0 | W23: =IFERROR(VLOOKUP(V23,'wideName-Dropdowns'!$M:$N,2,FALSE),"") -> 0 | Y23: =IFERROR(VLOOKUP(X23,'wideName-Dropdowns'!$O:$P,2,FALSE),"") -> 0 | AA23: =IFERROR(VLOOKUP(Z23,'wideName-Dropdowns'!$Q:$R,2,FALSE),"") -> 0 | AC23: Reference link | AD23: =IFERROR(VLOOKUP(AC23,'wideName-Dropdowns'!$S:$T,2,FALSE),"") -> 0
A24: =IF(I24="attributes",H24,IF(I24="measurements",F24,G24)) -> 0 | B24: Chemical Oxygen Demand (mg/l) - wide | C24: =LEN(A24) -> 0 | D24: Chemical oxygen demand in a wide or combined long-and-wide table. | E24: EU Airport template | F24: =IF(I24="measurements",IF(AE24="",_xlfn.CONCAT(O24,"_",Q24,"_",S24,"_",U24,"_",Y24,"_",AA24,"_",AB24,"_",AD24),_xlfn.CONCAT(O24,"_",Q24,"_",S24,"_",U24,"_",Y24,"_",AA24,"_",AB24,"_",AD24,".odm",AE24)),"NA") -> 0 | G24: =IF(I24="methods",IF(L24="measurement",IF(AE24="",_xlfn.CONCAT(K24,"_",M24,"_",O24,"_",Q24,"_",S24,"_",U24,"_",Y24,"_",AA24,"_",AB24,"_",AD24),_xlfn.CONCAT(K24,"_",M24,"_",O24,"_",Q24,"_",S24,"_",U24,"_",Y24,"_",AA24,"_",AB24,"_",AD24,".odm",AE24)),IF(AE24="",_xlfn.CONCAT(K24,"_",M24,"_",W24,"_",AD24),_xlfn.CONCAT(K24,"_",M24,"_",W24,"_",AD24,".odm",AE24))),"NA") -> 0 | H24: =IF(I24="attributes",IF(AE24="",_xlfn.CONCAT(K24,"_",AD24),_xlfn.CONCAT(K24,"_",AD24,".odm",AE24)),"NA") -> 0 | I24: measurements | K24: =IFERROR(VLOOKUP(J24,'wideName-Dropdowns'!$A:$B,2,FALSE),"") -> 0 | M24: =IFERROR(VLOOKUP(L24,'wideName-Dropdowns'!$C:$D,2,FALSE),"") -> 0 | N24: Water compartment | O24: =IFERROR(VLOOKUP(N24,'wideName-Dropdowns'!$E:$F,2,FALSE),"") -> 0 | P24: Site | Q24: =IFERROR(VLOOKUP(P24,'wideName-Dropdowns'!$G:$H,2,FALSE),"") -> 0 | R24: Not reported | S24: =IFERROR(VLOOKUP(R24,'wideName-Dropdowns'!$I:$J,2,FALSE),"") -> 0 | T24: Chemical Oxygen Demand | U24: =IFERROR(VLOOKUP(T24,'wideName-Dropdowns'!$K:$L,2,FALSE),"") -> 0 | W24: =IFERROR(VLOOKUP(V24,'wideName-Dropdowns'!$M:$N,2,FALSE),"") -> 0 | X24: Milligrams per litre | Y24: =IFERROR(VLOOKUP(X24,'wideName-Dropdowns'!$O:$P,2,FALSE),"") -> 0 | Z24: Arithmetic mean | AA24: =IFERROR(VLOOKUP(Z24,'wideName-Dropdowns'!$Q:$R,2,FALSE),"") -> 0 | AB24: NR | AC24: Value | AD24: =IFERROR(VLOOKUP(AC24,'wideName-Dropdowns'!$S:$T,2,FALSE),"") -> 0
A25: =IF(I25="attributes",H25,IF(I25="measurements",F25,G25)) -> 0 | B25: Biochemical Oxygen Demand (mg/l) - wide | C25: =LEN(A25) -> 0 | D25: Biochemical oxygen demand in a wide or combined long-and-wide table. | E25: EU Airport template | F25: =IF(I25="measurements",IF(AE25="",_xlfn.CONCAT(O25,"_",Q25,"_",S25,"_",U25,"_",Y25,"_",AA25,"_",AB25,"_",AD25),_xlfn.CONCAT(O25,"_",Q25,"_",S25,"_",U25,"_",Y25,"_",AA25,"_",AB25,"_",AD25,".odm",AE25)),"NA") -> 0 | G25: =IF(I25="methods",IF(L25="measurement",IF(AE25="",_xlfn.CONCAT(K25,"_",M25,"_",O25,"_",Q25,"_",S25,"_",U25,"_",Y25,"_",AA25,"_",AB25,"_",AD25),_xlfn.CONCAT(K25,"_",M25,"_",O25,"_",Q25,"_",S25,"_",U25,"_",Y25,"_",AA25,"_",AB25,"_",AD25,".odm",AE25)),IF(AE25="",_xlfn.CONCAT(K25,"_",M25,"_",W25,"_",AD25),_xlfn.CONCAT(K25,"_",M25,"_",W25,"_",AD25,".odm",AE25))),"NA") -> 0 | H25: =IF(I25="attributes",IF(AE25="",_xlfn.CONCAT(K25,"_",AD25),_xlfn.CONCAT(K25,"_",AD25,".odm",AE25)),"NA") -> 0 | I25: measurements | K25: =IFERROR(VLOOKUP(J25,'wideName-Dropdowns'!$A:$B,2,FALSE),"") -> 0 | M25: =IFERROR(VLOOKUP(L25,'wideName-Dropdowns'!$C:$D,2,FALSE),"") -> 0 | N25: Water compartment | O25: =IFERROR(VLOOKUP(N25,'wideName-Dropdowns'!$E:$F,2,FALSE),"") -> 0 | P25: Site | Q25: =IFERROR(VLOOKUP(P25,'wideName-Dropdowns'!$G:$H,2,FALSE),"") -> 0 | R25: Not reported | S25: =IFERROR(VLOOKUP(R25,'wideName-Dropdowns'!$I:$J,2,FALSE),"") -> 0 | T25: 5-day total biochemical oxygen demand | U25: =IFERROR(VLOOKUP(T25,'wideName-Dropdowns'!$K:$L,2,FALSE),"") -> 0 | W25: =IFERROR(VLOOKUP(V25,'wideName-Dropdowns'!$M:$N,2,FALSE),"") -> 0 | X25: Milligrams per litre | Y25: =IFERROR(VLOOKUP(X25,'wideName-Dropdowns'!$O:$P,2,FALSE),"") -> 0 | Z25: Arithmetic mean | AA25: =IFERROR(VLOOKUP(Z25,'wideName-Dropdowns'!$Q:$R,2,FALSE),"") -> 0 | AB25: NR | AC25: Value | AD25: =IFERROR(VLOOKUP(AC25,'wideName-Dropdowns'!$S:$T,2,FALSE),"") -> 0
A26: =IF(I26="attributes",H26,IF(I26="measurements",F26,G26)) -> 0 | B26: Water conductivity (µS/cm) - wide | C26: =LEN(A26) -> 0 | D26: Wastewater or water conductivity in a wide or combined long-and-wide table. | E26: EU Airport template | F26: =IF(I26="measurements",IF(AE26="",_xlfn.CONCAT(O26,"_",Q26,"_",S26,"_",U26,"_",Y26,"_",AA26,"_",AB26,"_",AD26),_xlfn.CONCAT(O26,"_",Q26,"_",S26,"_",U26,"_",Y26,"_",AA26,"_",AB26,"_",AD26,".odm",AE26)),"NA") -> 0 | G26: =IF(I26="methods",IF(L26="measurement",IF(AE26="",_xlfn.CONCAT(K26,"_",M26,"_",O26,"_",Q26,"_",S26,"_",U26,"_",Y26,"_",AA26,"_",AB26,"_",AD26),_xlfn.CONCAT(K26,"_",M26,"_",O26,"_",Q26,"_",S26,"_",U26,"_",Y26,"_",AA26,"_",AB26,"_",AD26,".odm",AE26)),IF(AE26="",_xlfn.CONCAT(K26,"_",M26,"_",W26,"_",AD26),_xlfn.CONCAT(K26,"_",M26,"_",W26,"_",AD26,".odm",AE26))),"NA") -> 0 | H26: =IF(I26="attributes",IF(AE26="",_xlfn.CONCAT(K26,"_",AD26),_xlfn.CONCAT(K26,"_",AD26,".odm",AE26)),"NA") -> 0 | I26: measurements | K26: =IFERROR(VLOOKUP(J26,'wideName-Dropdowns'!$A:$B,2,FALSE),"") -> 0 | M26: =IFERROR(VLOOKUP(L26,'wideName-Dropdowns'!$C:$D,2,FALSE),"") -> 0 | N26: Water compartment | O26: =IFERROR(VLOOKUP(N26,'wideName-Dropdowns'!$E:$F,2,FALSE),"") -> 0 | P26: Site | Q26: =IFERROR(VLOOKUP(P26,'wideName-Dropdowns'!$G:$H,2,FALSE),"") -> 0 | R26: Not reported | S26: =IFERROR(VLOOKUP(R26,'wideName-Dropdowns'!$I:$J,2,FALSE),"") -> 0 | T26: Water conductivity | U26: =IFERROR(VLOOKUP(T26,'wideName-Dropdowns'!$K:$L,2,FALSE),"") -> 0 | W26: =IFERROR(VLOOKUP(V26,'wideName-Dropdowns'!$M:$N,2,FALSE),"") -> 0 | X26: Micro-Siemens per centimetre | Y26: =IFERROR(VLOOKUP(X26,'wideName-Dropdowns'!$O:$P,2,FALSE),"") -> 0 | Z26: Arithmetic mean | AA26: =IFERROR(VLOOKUP(Z26,'wideName-Dropdowns'!$Q:$R,2,FALSE),"") -> 0 | AB26: NR | AC26: Value | AD26: =IFERROR(VLOOKUP(AC26,'wideName-Dropdowns'!$S:$T,2,FALSE),"") -> 0
A27: =IF(I27="attributes",H27,IF(I27="measurements",F27,G27)) -> 0 | B27: pH - wide | C27: =LEN(A27) -> 0 | D27: pH of a site in a wide or combined long-and-wide table. | E27: EU Airport template | F27: =IF(I27="measurements",IF(AE27="",_xlfn.CONCAT(O27,"_",Q27,"_",S27,"_",U27,"_",Y27,"_",AA27,"_",AB27,"_",AD27),_xlfn.CONCAT(O27,"_",Q27,"_",S27,"_",U27,"_",Y27,"_",AA27,"_",AB27,"_",AD27,".odm",AE27)),"NA") -> 0 | G27: =IF(I27="methods",IF(L27="measurement",IF(AE27="",_xlfn.CONCAT(K27,"_",M27,"_",O27,"_",Q27,"_",S27,"_",U27,"_",Y27,"_",AA27,"_",AB27,"_",AD27),_xlfn.CONCAT(K27,"_",M27,"_",O27,"_",Q27,"_",S27,"_",U27,"_",Y27,"_",AA27,"_",AB27,"_",AD27,".odm",AE27)),IF(AE27="",_xlfn.CONCAT(K27,"_",M27,"_",W27,"_",AD27),_xlfn.CONCAT(K27,"_",M27,"_",W27,"_",AD27,".odm",AE27))),"NA") -> 0 | H27: =IF(I27="attributes",IF(AE27="",_xlfn.CONCAT(K27,"_",AD27),_xlfn.CONCAT(K27,"_",AD27,".odm",AE27)),"NA") -> 0 | I27: measurements | K27: =IFERROR(VLOOKUP(J27,'wideName-Dropdowns'!$A:$B,2,FALSE),"") -> 0 | M27: =IFERROR(VLOOKUP(L27,'wideName-Dropdowns'!$C:$D,2,FALSE),"") -> 0 | N27: Water compartment | O27: =IFERROR(VLOOKUP(N27,'wideName-Dropdowns'!$E:$F,2,FALSE),"") -> 0 | P27: Site | Q27: =IFERROR(VLOOKUP(P27,'wideName-Dropdowns'!$G:$H,2,FALSE),"") -> 0 | R27: Not reported | S27: =IFERROR(VLOOKUP(R27,'wideName-Dropdowns'!$I:$J,2,FALSE),"") -> 0 | T27: pH | U27: =IFERROR(VLOOKUP(T27,'wideName-Dropdowns'!$K:$L,2,FALSE),"") -> 0 | W27: =IFERROR(VLOOKUP(V27,'wideName-Dropdowns'!$M:$N,2,FALSE),"") -> 0 | X27: Unitless measure | Y27: =IFERROR(VLOOKUP(X27,'wideName-Dropdowns'!$O:$P,2,FALSE),"") -> 0 | Z27: Arithmetic mean | AA27: =IFERROR(VLOOKUP(Z27,'wideName-Dropdowns'!$Q:$R,2,FALSE),"") -> 0 | AB27: NR | AC27: Value | AD27: =IFERROR(VLOOKUP(AC27,'wideName-Dropdowns'!$S:$T,2,FALSE),"") -> 0
A28: =IF(I28="attributes",H28,IF(I28="measurements",F28,G28)) -> 0 | B28: Nitrogen concentration (mg/l) - wide | C28: =LEN(A28) -> 0 | D28: Notal nitrogen concentration at a site in a wide or combined long-and-wide table. | E28: EU Airport template | F28: =IF(I28="measurements",IF(AE28="",_xlfn.CONCAT(O28,"_",Q28,"_",S28,"_",U28,"_",Y28,"_",AA28,"_",AB28,"_",AD28),_xlfn.CONCAT(O28,"_",Q28,"_",S28,"_",U28,"_",Y28,"_",AA28,"_",AB28,"_",AD28,".odm",AE28)),"NA") -> 0 | G28: =IF(I28="methods",IF(L28="measurement",IF(AE28="",_xlfn.CONCAT(K28,"_",M28,"_",O28,"_",Q28,"_",S28,"_",U28,"_",Y28,"_",AA28,"_",AB28,"_",AD28),_xlfn.CONCAT(K28,"_",M28,"_",O28,"_",Q28,"_",S28,"_",U28,"_",Y28,"_",AA28,"_",AB28,"_",AD28,".odm",AE28)),IF(AE28="",_xlfn.CONCAT(K28,"_",M28,"_",W28,"_",AD28),_xlfn.CONCAT(K28,"_",M28,"_",W28,"_",AD28,".odm",AE28))),"NA") -> 0 | H28: =IF(I28="attributes",IF(AE28="",_xlfn.CONCAT(K28,"_",AD28),_xlfn.CONCAT(K28,"_",AD28,".odm",AE28)),"NA") -> 0 | I28: measurements | K28: =IFERROR(VLOOKUP(J28,'wideName-Dropdowns'!$A:$B,2,FALSE),"") -> 0 | M28: =IFERROR(VLOOKUP(L28,'wideName-Dropdowns'!$C:$D,2,FALSE),"") -> 0 | N28: Water compartment | O28: =IFERROR(VLOOKUP(N28,'wideName-Dropdowns'!$E:$F,2,FALSE),"") -> 0 | P28: Site | Q28: =IFERROR(VLOOKUP(P28,'wideName-Dropdowns'!$G:$H,2,FALSE),"") -> 0 | R28: Not reported | S28: =IFERROR(VLOOKUP(R28,'wideName-Dropdowns'!$I:$J,2,FALSE),"") -> 0 | T28: Total Nitrogen | U28: =IFERROR(VLOOKUP(T28,'wideName-Dropdowns'!$K:$L,2,FALSE),"") -> 0 | W28: =IFERROR(VLOOKUP(V28,'wideName-Dropdowns'!$M:$N,2,FALSE),"") -> 0 | X28: Milligrams per litre | Y28: =IFERROR(VLOOKUP(X28,'wideName-Dropdowns'!$O:$P,2,FALSE),"") -> 0 | Z28: Arithmetic mean | AA28: =IFERROR(VLOOKUP(Z28,'wideName-Dropdowns'!$Q:$R,2,FALSE),"") -> 0 | AB28: NR | AC28: Value | AD28: =IFERROR(VLOOKUP(AC28,'wideName-Dropdowns'!$S:$T,2,FALSE),"") -> 0
A29: =IF(I29="attributes",H29,IF(I29="measurements",F29,G29)) -> 0 | B29: Limit of Detection (gc) - wide | C29: =LEN(A29) -> 0 | D29: Limit of Detection of a wastewater sample in a wide or combined long-and-wide table. | E29: EU Airport template | F29: =IF(I29="measurements",IF(AE29="",_xlfn.CONCAT(O29,"_",Q29,"_",S29,"_",U29,"_",Y29,"_",AA29,"_",AB29,"_",AD29),_xlfn.CONCAT(O29,"_",Q29,"_",S29,"_",U29,"_",Y29,"_",AA29,"_",AB29,"_",AD29,".odm",AE29)),"NA") -> 0 | G29: =IF(I29="methods",IF(L29="measurement",IF(AE29="",_xlfn.CONCAT(K29,"_",M29,"_",O29,"_",Q29,"_",S29,"_",U29,"_",Y29,"_",AA29,"_",AB29,"_",AD29),_xlfn.CONCAT(K29,"_",M29,"_",O29,"_",Q29,"_",S29,"_",U29,"_",Y29,"_",AA29,"_",AB29,"_",AD29,".odm",AE29)),IF(AE29="",_xlfn.CONCAT(K29,"_",M29,"_",W29,"_",AD29),_xlfn.CONCAT(K29,"_",M29,"_",W29,"_",AD29,".odm",AE29))),"NA") -> 0 | H29: =IF(I29="attributes",IF(AE29="",_xlfn.CONCAT(K29,"_",AD29),_xlfn.CONCAT(K29,"_",AD29,".odm",AE29)),"NA") -> 0 | I29: measurements | K29: =IFERROR(VLOOKUP(J29,'wideName-Dropdowns'!$A:$B,2,FALSE),"") -> 0 | M29: =IFERROR(VLOOKUP(L29,'wideName-Dropdowns'!$C:$D,2,FALSE),"") -> 0 | N29: Water compartment | O29: =IFERROR(VLOOKUP(N29,'wideName-Dropdowns'!$E:$F,2,FALSE),"") -> 0 | P29: Sample | Q29: =IFERROR(VLOOKUP(P29,'wideName-Dropdowns'!$G:$H,2,FALSE),"") -> 0 | R29: Not reported | S29: =IFERROR(VLOOKUP(R29,'wideName-Dropdowns'!$I:$J,2,FALSE),"") -> 0 | T29: Limit of detection (LOD) - sewage | U29: =IFERROR(VLOOKUP(T29,'wideName-Dropdowns'!$K:$L,2,FALSE),"") -> 0 | W29: =IFERROR(VLOOKUP(V29,'wideName-Dropdowns'!$M:$N,2,FALSE),"") -> 0 | X29: Gene copies | Y29: =IFERROR(VLOOKUP(X29,'wideName-Dropdowns'!$O:$P,2,FALSE),"") -> 0 | Z29: Single | AA29: =IFERROR(VLOOKUP(Z29,'wideName-Dropdowns'!$Q:$R,2,FALSE),"") -> 0 | AB29: NR | AC29: Value | AD29: =IFERROR(VLOOKUP(AC29,'wideName-Dropdowns'!$S:$T,2,FALSE),"") -> 0
A30: =IF(I30="attributes",H30,IF(I30="measurements",F30,G30)) -> 0 | B30: Limit of Quantification (gc) - wide | C30: =LEN(A30) -> 0 | D30: Limit of quantification in a wide or combined long-and-wide table. | E30: EU Airport template | F30: =IF(I30="measurements",IF(AE30="",_xlfn.CONCAT(O30,"_",Q30,"_",S30,"_",U30,"_",Y30,"_",AA30,"_",AB30,"_",AD30),_xlfn.CONCAT(O30,"_",Q30,"_",S30,"_",U30,"_",Y30,"_",AA30,"_",AB30,"_",AD30,".odm",AE30)),"NA") -> 0 | G30: =IF(I30="methods",IF(L30="measurement",IF(AE30="",_xlfn.CONCAT(K30,"_",M30,"_",O30,"_",Q30,"_",S30,"_",U30,"_",Y30,"_",AA30,"_",AB30,"_",AD30),_xlfn.CONCAT(K30,"_",M30,"_",O30,"_",Q30,"_",S30,"_",U30,"_",Y30,"_",AA30,"_",AB30,"_",AD30,".odm",AE30)),IF(AE30="",_xlfn.CONCAT(K30,"_",M30,"_",W30,"_",AD30),_xlfn.CONCAT(K30,"_",M30,"_",W30,"_",AD30,".odm",AE30))),"NA") -> 0 | H30: =IF(I30="attributes",IF(AE30="",_xlfn.CONCAT(K30,"_",AD30),_xlfn.CONCAT(K30,"_",AD30,".odm",AE30)),"NA") -> 0 | I30: measurements | K30: =IFERROR(VLOOKUP(J30,'wideName-Dropdowns'!$A:$B,2,FALSE),"") -> 0 | M30: =IFERROR(VLOOKUP(L30,'wideName-Dropdowns'!$C:$D,2,FALSE),"") -> 0 | N30: Water compartment | O30: =IFERROR(VLOOKUP(N30,'wideName-Dropdowns'!$E:$F,2,FALSE),"") -> 0 | P30: Sample | Q30: =IFERROR(VLOOKUP(P30,'wideName-Dropdowns'!$G:$H,2,FALSE),"") -> 0 | R30: Not reported | S30: =IFERROR(VLOOKUP(R30,'wideName-Dropdowns'!$I:$J,2,FALSE),"") -> 0 | T30: Limit of quantification (LOQ) | U30: =IFERROR(VLOOKUP(T30,'wideName-Dropdowns'!$K:$L,2,FALSE),"") -> 0 | W30: =IFERROR(VLOOKUP(V30,'wideName-Dropdowns'!$M:$N,2,FALSE),"") -> 0 | X30: Gene copies | Y30: =IFERROR(VLOOKUP(X30,'wideName-Dropdowns'!$O:$P,2,FALSE),"") -> 0 | Z30: Single | AA30: =IFERROR(VLOOKUP(Z30,'wideName-Dropdowns'!$Q:$R,2,FALSE),"") -> 0 | AB30: NR | AC30: Value | AD30: =IFERROR(VLOOKUP(AC30,'wideName-Dropdowns'!$S:$T,2,FALSE),"") -> 0
A31: =IF(I31="attributes",H31,IF(I31="measurements",F31,G31)) -> 0 | B31: Report date - wide | C31: =LEN(A31) -> 0 | D31: Date that the measurement was reported to authorities in a wide or combined long-and-wide table. | E31: EU Airport template | F31: =IF(I31="measurements",IF(AE31="",_xlfn.CONCAT(O31,"_",Q31,"_",S31,"_",U31,"_",Y31,"_",AA31,"_",AB31,"_",AD31),_xlfn.CONCAT(O31,"_",Q31,"_",S31,"_",U31,"_",Y31,"_",AA31,"_",AB31,"_",AD31,".odm",AE31)),"NA") -> 0 | G31: =IF(I31="methods",IF(L31="measurement",IF(AE31="",_xlfn.CONCAT(K31,"_",M31,"_",O31,"_",Q31,"_",S31,"_",U31,"_",Y31,"_",AA31,"_",AB31,"_",AD31),_xlfn.CONCAT(K31,"_",M31,"_",O31,"_",Q31,"_",S31,"_",U31,"_",Y31,"_",AA31,"_",AB31,"_",AD31,".odm",AE31)),IF(AE31="",_xlfn.CONCAT(K31,"_",M31,"_",W31,"_",AD31),_xlfn.CONCAT(K31,"_",M31,"_",W31,"_",AD31,".odm",AE31))),"NA") -> 0 | H31: =IF(I31="attributes",IF(AE31="",_xlfn.CONCAT(K31,"_",AD31),_xlfn.CONCAT(K31,"_",AD31,".odm",AE31)),"NA") -> 0 | I31: attributes | J31: Measure report table Shorthand | K31: =IFERROR(VLOOKUP(J31,'wideName-Dropdowns'!$A:$B,2,FALSE),"") -> 0 | M31: =IFERROR(VLOOKUP(L31,'wideName-Dropdowns'!$C:$D,2,FALSE),"") -> 0 | O31: =IFERROR(VLOOKUP(N31,'wideName-Dropdowns'!$E:$F,2,FALSE),"") -> 0 | Q31: =IFERROR(VLOOKUP(P31,'wideName-Dropdowns'!$G:$H,2,FALSE),"") -> 0 | S31: =IFERROR(VLOOKUP(R31,'wideName-Dropdowns'!$I:$J,2,FALSE),"") -> 0 | U31: =IFERROR(VLOOKUP(T31,'wideName-Dropdowns'!$K:$L,2,FALSE),"") -> 0 | W31: =IFERROR(VLOOKUP(V31,'wideName-Dropdowns'!$M:$N,2,FALSE),"") -> 0 | Y31: =IFERROR(VLOOKUP(X31,'wideName-Dropdowns'!$O:$P,2,FALSE),"") -> 0 | AA31: =IFERROR(VLOOKUP(Z31,'wideName-Dropdowns'!$Q:$R,2,FALSE),"") -> 0 | AC31: Report date | AD31: =IFERROR(VLOOKUP(AC31,'wideName-Dropdowns'!$S:$T,2,FALSE),"") -> 0
A32: =IF(I32="attributes",H32,IF(I32="measurements",F32,G32)) -> 0 | B32: Contact person email - wide | C32: =LEN(A32) -> 0 | D32: Contact email address in a wide or combined long-and-wide table. | E32: EU Airport template | F32: =IF(I32="measurements",IF(AE32="",_xlfn.CONCAT(O32,"_",Q32,"_",S32,"_",U32,"_",Y32,"_",AA32,"_",AB32,"_",AD32),_xlfn.CONCAT(O32,"_",Q32,"_",S32,"_",U32,"_",Y32,"_",AA32,"_",AB32,"_",AD32,".odm",AE32)),"NA") -> 0 | G32: =IF(I32="methods",IF(L32="measurement",IF(AE32="",_xlfn.CONCAT(K32,"_",M32,"_",O32,"_",Q32,"_",S32,"_",U32,"_",Y32,"_",AA32,"_",AB32,"_",AD32),_xlfn.CONCAT(K32,"_",M32,"_",O32,"_",Q32,"_",S32,"_",U32,"_",Y32,"_",AA32,"_",AB32,"_",AD32,".odm",AE32)),IF(AE32="",_xlfn.CONCAT(K32,"_",M32,"_",W32,"_",AD32),_xlfn.CONCAT(K32,"_",M32,"_",W32,"_",AD32,".odm",AE32))),"NA") -> 0 | H32: =IF(I32="attributes",IF(AE32="",_xlfn.CONCAT(K32,"_",AD32),_xlfn.CONCAT(K32,"_",AD32,".odm",AE32)),"NA") -> 0 | I32: attributes | J32: Contact table Shorthand | K32: =IFERROR(VLOOKUP(J32,'wideName-Dropdowns'!$A:$B,2,FALSE),"") -> 0 | M32: =IFERROR(VLOOKUP(L32,'wideName-Dropdowns'!$C:$D,2,FALSE),"") -> 0 | O32: =IFERROR(VLOOKUP(N32,'wideName-Dropdowns'!$E:$F,2,FALSE),"") -> 0 | Q32: =IFERROR(VLOOKUP(P32,'wideName-Dropdowns'!$G:$H,2,FALSE),"") -> 0 | S32: =IFERROR(VLOOKUP(R32,'wideName-Dropdowns'!$I:$J,2,FALSE),"") -> 0 | U32: =IFERROR(VLOOKUP(T32,'wideName-Dropdowns'!$K:$L,2,FALSE),"") -> 0 | W32: =IFERROR(VLOOKUP(V32,'wideName-Dropdowns'!$M:$N,2,FALSE),"") -> 0 | Y32: =IFERROR(VLOOKUP(X32,'wideName-Dropdowns'!$O:$P,2,FALSE),"") -> 0 | AA32: =IFERROR(VLOOKUP(Z32,'wideName-Dropdowns'!$Q:$R,2,FALSE),"") -> 0 | AC32: Contact email | AD32: =IFERROR(VLOOKUP(AC32,'wideName-Dropdowns'!$S:$T,2,FALSE),"") -> 0
A33: =IF(I33="attributes",H33,IF(I33="measurements",F33,G33)) -> 0 | B33: Notes - wide | C33: =LEN(A33) -> 0 | D33: Notes on a measure in a wide or combined long-and-wide table. | E33: EU Airport template | F33: =IF(I33="measurements",IF(AE33="",_xlfn.CONCAT(O33,"_",Q33,"_",S33,"_",U33,"_",Y33,"_",AA33,"_",AB33,"_",AD33),_xlfn.CONCAT(O33,"_",Q33,"_",S33,"_",U33,"_",Y33,"_",AA33,"_",AB33,"_",AD33,".odm",AE33)),"NA") -> 0 | G33: =IF(I33="methods",IF(L33="measurement",IF(AE33="",_xlfn.CONCAT(K33,"_",M33,"_",O33,"_",Q33,"_",S33,"_",U33,"_",Y33,"_",AA33,"_",AB33,"_",AD33),_xlfn.CONCAT(K33,"_",M33,"_",O33,"_",Q33,"_",S33,"_",U33,"_",Y33,"_",AA33,"_",AB33,"_",AD33,".odm",AE33)),IF(AE33="",_xlfn.CONCAT(K33,"_",M33,"_",W33,"_",AD33),_xlfn.CONCAT(K33,"_",M33,"_",W33,"_",AD33,".odm",AE33))),"NA") -> 0 | H33: =IF(I33="attributes",IF(AE33="",_xlfn.CONCAT(K33,"_",AD33),_xlfn.CONCAT(K33,"_",AD33,".odm",AE33)),"NA") -> 0 | I33: attributes | J33: Measure report table Shorthand | K33: =IFERROR(VLOOKUP(J33,'wideName-Dropdowns'!$A:$B,2,FALSE),"") -> 0 | M33: =IFERROR(VLOOKUP(L33,'wideName-Dropdowns'!$C:$D,2,FALSE),"") -> 0 | O33: =IFERROR(VLOOKUP(N33,'wideName-Dropdowns'!$E:$F,2,FALSE),"") -> 0 | Q33: =IFERROR(VLOOKUP(P33,'wideName-Dropdowns'!$G:$H,2,FALSE),"") -> 0 | S33: =IFERROR(VLOOKUP(R33,'wideName-Dropdowns'!$I:$J,2,FALSE),"") -> 0 | U33: =IFERROR(VLOOKUP(T33,'wideName-Dropdowns'!$K:$L,2,FALSE),"") -> 0 | W33: =IFERROR(VLOOKUP(V33,'wideName-Dropdowns'!$M:$N,2,FALSE),"") -> 0 | Y33: =IFERROR(VLOOKUP(X33,'wideName-Dropdowns'!$O:$P,2,FALSE),"") -> 0 | AA33: =IFERROR(VLOOKUP(Z33,'wideName-Dropdowns'!$Q:$R,2,FALSE),"") -> 0 | AC33: Notes | AD33: =IFERROR(VLOOKUP(AC33,'wideName-Dropdowns'!$S:$T,2,FALSE),"") -> 0
A34: =IF(I34="attributes",H34,IF(I34="measurements",F34,G34)) -> 0 | B34: Data source | C34: =LEN(A34) -> 0 | D34: The dataset or source dataset for a measure. This might reference difference contributor organizations to a larger dataset. | E34: HPAIV H5N1 Template | F34: =IF(I34="measurements",IF(AE34="",_xlfn.CONCAT(O34,"_",Q34,"_",S34,"_",U34,"_",Y34,"_",AA34,"_",AB34,"_",AD34),_xlfn.CONCAT(O34,"_",Q34,"_",S34,"_",U34,"_",Y34,"_",AA34,"_",AB34,"_",AD34,".odm",AE34)),"NA") -> 0 | G34: =IF(I34="methods",IF(L34="measurement",IF(AE34="",_xlfn.CONCAT(K34,"_",M34,"_",O34,"_",Q34,"_",S34,"_",U34,"_",Y34,"_",AA34,"_",AB34,"_",AD34),_xlfn.CONCAT(K34,"_",M34,"_",O34,"_",Q34,"_",S34,"_",U34,"_",Y34,"_",AA34,"_",AB34,"_",AD34,".odm",AE34)),IF(AE34="",_xlfn.CONCAT(K34,"_",M34,"_",W34,"_",AD34),_xlfn.CONCAT(K34,"_",M34,"_",W34,"_",AD34,".odm",AE34))),"NA") -> 0 | H34: =IF(I34="attributes",IF(AE34="",_xlfn.CONCAT(K34,"_",AD34),_xlfn.CONCAT(K34,"_",AD34,".odm",AE34)),"NA") -> 0 | I34: attributes | J34: Measure report table Shorthand | K34: =IFERROR(VLOOKUP(J34,'wideName-Dropdowns'!$A:$B,2,FALSE),"") -> 0 | M34: =IFERROR(VLOOKUP(L34,'wideName-Dropdowns'!$C:$D,2,FALSE),"") -> 0 | O34: =IFERROR(VLOOKUP(N34,'wideName-Dropdowns'!$E:$F,2,FALSE),"") -> 0 | Q34: =IFERROR(VLOOKUP(P34,'wideName-Dropdowns'!$G:$H,2,FALSE),"") -> 0 | S34: =IFERROR(VLOOKUP(R34,'wideName-Dropdowns'!$I:$J,2,FALSE),"") -> 0 | U34: =IFERROR(VLOOKUP(T34,'wideName-Dropdowns'!$K:$L,2,FALSE),"") -> 0 | W34: =IFERROR(VLOOKUP(V34,'wideName-Dropdowns'!$M:$N,2,FALSE),"") -> 0 | Y34: =IFERROR(VLOOKUP(X34,'wideName-Dropdowns'!$O:$P,2,FALSE),"") -> 0 | AA34: =IFERROR(VLOOKUP(Z34,'wideName-Dropdowns'!$Q:$R,2,FALSE),"") -> 0 | AC34: Dataset ID | AD34: =IFERROR(VLOOKUP(AC34,'wideName-Dropdowns'!$S:$T,2,FALSE),"") -> 0
A35: =IF(I35="attributes",H35,IF(I35="measurements",F35,G35)) -> 0 | B35: Site jurisdiction | C35: =LEN(A35) -> 0 | D35: The unique identifier for an organization with jurisdiction over a given site. | E35: HPAIV H5N1 Template | F35: =IF(I35="measurements",IF(AE35="",_xlfn.CONCAT(O35,"_",Q35,"_",S35,"_",U35,"_",Y35,"_",AA35,"_",AB35,"_",AD35),_xlfn.CONCAT(O35,"_",Q35,"_",S35,"_",U35,"_",Y35,"_",AA35,"_",AB35,"_",AD35,".odm",AE35)),"NA") -> 0 | G35: =IF(I35="methods",IF(L35="measurement",IF(AE35="",_xlfn.CONCAT(K35,"_",M35,"_",O35,"_",Q35,"_",S35,"_",U35,"_",Y35,"_",AA35,"_",AB35,"_",AD35),_xlfn.CONCAT(K35,"_",M35,"_",O35,"_",Q35,"_",S35,"_",U35,"_",Y35,"_",AA35,"_",AB35,"_",AD35,".odm",AE35)),IF(AE35="",_xlfn.CONCAT(K35,"_",M35,"_",W35,"_",AD35),_xlfn.CONCAT(K35,"_",M35,"_",W35,"_",AD35,".odm",AE35))),"NA") -> 0 | H35: =IF(I35="attributes",IF(AE35="",_xlfn.CONCAT(K35,"_",AD35),_xlfn.CONCAT(K35,"_",AD35,".odm",AE35)),"NA") -> 0 | I35: attributes | J35: Sites table Shorthand | K35: =IFERROR(VLOOKUP(J35,'wideName-Dropdowns'!$A:$B,2,FALSE),"") -> 0 | M35: =IFERROR(VLOOKUP(L35,'wideName-Dropdowns'!$C:$D,2,FALSE),"") -> 0 | O35: =IFERROR(VLOOKUP(N35,'wideName-Dropdowns'!$E:$F,2,FALSE),"") -> 0 | Q35: =IFERROR(VLOOKUP(P35,'wideName-Dropdowns'!$G:$H,2,FALSE),"") -> 0 | S35: =IFERROR(VLOOKUP(R35,'wideName-Dropdowns'!$I:$J,2,FALSE),"") -> 0 | U35: =IFERROR(VLOOKUP(T35,'wideName-Dropdowns'!$K:$L,2,FALSE),"") -> 0 | W35: =IFERROR(VLOOKUP(V35,'wideName-Dropdowns'!$M:$N,2,FALSE),"") -> 0 | Y35: =IFERROR(VLOOKUP(X35,'wideName-Dropdowns'!$O:$P,2,FALSE),"") -> 0 | AA35: =IFERROR(VLOOKUP(Z35,'wideName-Dropdowns'!$Q:$R,2,FALSE),"") -> 0 | AC35: Primary reporting authority ID | AD35: =IFERROR(VLOOKUP(AC35,'wideName-Dropdowns'!$S:$T,2,FALSE),"") -> 0
A36: =IF(I36="attributes",H36,IF(I36="measurements",F36,G36)) -> 0 | B36: Sewershed ID | C36: =LEN(A36) -> 0 | D36: The unique identifier for the polygon/sewershed boundaries for collection point. | E36: HPAIV H5N1 Template | F36: =IF(I36="measurements",IF(AE36="",_xlfn.CONCAT(O36,"_",Q36,"_",S36,"_",U36,"_",Y36,"_",AA36,"_",AB36,"_",AD36),_xlfn.CONCAT(O36,"_",Q36,"_",S36,"_",U36,"_",Y36,"_",AA36,"_",AB36,"_",AD36,".odm",AE36)),"NA") -> 0 | G36: =IF(I36="methods",IF(L36="measurement",IF(AE36="",_xlfn.CONCAT(K36,"_",M36,"_",O36,"_",Q36,"_",S36,"_",U36,"_",Y36,"_",AA36,"_",AB36,"_",AD36),_xlfn.CONCAT(K36,"_",M36,"_",O36,"_",Q36,"_",S36,"_",U36,"_",Y36,"_",AA36,"_",AB36,"_",AD36,".odm",AE36)),IF(AE36="",_xlfn.CONCAT(K36,"_",M36,"_",W36,"_",AD36),_xlfn.CONCAT(K36,"_",M36,"_",W36,"_",AD36,".odm",AE36))),"NA") -> 0 | H36: =IF(I36="attributes",IF(AE36="",_xlfn.CONCAT(K36,"_",AD36),_xlfn.CONCAT(K36,"_",AD36,".odm",AE36)),"NA") -> 0 | I36: attributes | J36: Polygon table Shorthand | K36: =IFERROR(VLOOKUP(J36,'wideName-Dropdowns'!$A:$B,2,FALSE),"") -> 0 | M36: =IFERROR(VLOOKUP(L36,'wideName-Dropdowns'!$C:$D,2,FALSE),"") -> 0 | O36: =IFERROR(VLOOKUP(N36,'wideName-Dropdowns'!$E:$F,2,FALSE),"") -> 0 | Q36: =IFERROR(VLOOKUP(P36,'wideName-Dropdowns'!$G:$H,2,FALSE),"") -> 0 | S36: =IFERROR(VLOOKUP(R36,'wideName-Dropdowns'!$I:$J,2,FALSE),"") -> 0 | U36: =IFERROR(VLOOKUP(T36,'wideName-Dropdowns'!$K:$L,2,FALSE),"") -> 0 | W36: =IFERROR(VLOOKUP(V36,'wideName-Dropdowns'!$M:$N,2,FALSE),"") -> 0 | Y36: =IFERROR(VLOOKUP(X36,'wideName-Dropdowns'!$O:$P,2,FALSE),"") -> 0 | AA36: =IFERROR(VLOOKUP(Z36,'wideName-Dropdowns'!$Q:$R,2,FALSE),"") -> 0 | AC36: Polygon ID | AD36: =IFERROR(VLOOKUP(AC36,'wideName-Dropdowns'!$S:$T,2,FALSE),"") -> 0
A37: =IF(I37="attributes",H37,IF(I37="measurements",F37,G37)) -> 0 | B37: Site | C37: =LEN(A37) -> 0 | D37: The unique identifier for a sampling site. | E37: HPAIV H5N1 Template | F37: =IF(I37="measurements",IF(AE37="",_xlfn.CONCAT(O37,"_",Q37,"_",S37,"_",U37,"_",Y37,"_",AA37,"_",AB37,"_",AD37),_xlfn.CONCAT(O37,"_",Q37,"_",S37,"_",U37,"_",Y37,"_",AA37,"_",AB37,"_",AD37,".odm",AE37)),"NA") -> 0 | G37: =IF(I37="methods",IF(L37="measurement",IF(AE37="",_xlfn.CONCAT(K37,"_",M37,"_",O37,"_",Q37,"_",S37,"_",U37,"_",Y37,"_",AA37,"_",AB37,"_",AD37),_xlfn.CONCAT(K37,"_",M37,"_",O37,"_",Q37,"_",S37,"_",U37,"_",Y37,"_",AA37,"_",AB37,"_",AD37,".odm",AE37)),IF(AE37="",_xlfn.CONCAT(K37,"_",M37,"_",W37,"_",AD37),_xlfn.CONCAT(K37,"_",M37,"_",W37,"_",AD37,".odm",AE37))),"NA") -> 0 | H37: =IF(I37="attributes",IF(AE37="",_xlfn.CONCAT(K37,"_",AD37),_xlfn.CONCAT(K37,"_",AD37,".odm",AE37)),"NA") -> 0 | I37: attributes | J37: Sites table Shorthand | K37: =IFERROR(VLOOKUP(J37,'wideName-Dropdowns'!$A:$B,2,FALSE),"") -> 0 | M37: =IFERROR(VLOOKUP(L37,'wideName-Dropdowns'!$C:$D,2,FALSE),"") -> 0 | O37: =IFERROR(VLOOKUP(N37,'wideName-Dropdowns'!$E:$F,2,FALSE),"") -> 0 | Q37: =IFERROR(VLOOKUP(P37,'wideName-Dropdowns'!$G:$H,2,FALSE),"") -> 0 | S37: =IFERROR(VLOOKUP(R37,'wideName-Dropdowns'!$I:$J,2,FALSE),"") -> 0 | U37: =IFERROR(VLOOKUP(T37,'wideName-Dropdowns'!$K:$L,2,FALSE),"") -> 0 | W37: =IFERROR(VLOOKUP(V37,'wideName-Dropdowns'!$M:$N,2,FALSE),"") -> 0 | Y37: =IFERROR(VLOOKUP(X37,'wideName-Dropdowns'!$O:$P,2,FALSE),"") -> 0 | AA37: =IFERROR(VLOOKUP(Z37,'wideName-Dropdowns'!$Q:$R,2,FALSE),"") -> 0 | AC37: Site ID | AD37: =IFERROR(VLOOKUP(AC37,'wideName-Dropdowns'!$S:$T,2,FALSE),"") -> 0
A38: =IF(I38="attributes",H38,IF(I38="measurements",F38,G38)) -> 0 | B38: Sample shed type | C38: =LEN(A38) -> 0 | D38: The social context of the sampling site, specifying the building or location type. For example, an airplane, or a school, or a wastewater treatment plant. | E38: HPAIV H5N1 Template | F38: =IF(I38="measurements",IF(AE38="",_xlfn.CONCAT(O38,"_",Q38,"_",S38,"_",U38,"_",Y38,"_",AA38,"_",AB38,"_",AD38),_xlfn.CONCAT(O38,"_",Q38,"_",S38,"_",U38,"_",Y38,"_",AA38,"_",AB38,"_",AD38,".odm",AE38)),"NA") -> 0 | G38: =IF(I38="methods",IF(L38="measurement",IF(AE38="",_xlfn.CONCAT(K38,"_",M38,"_",O38,"_",Q38,"_",S38,"_",U38,"_",Y38,"_",AA38,"_",AB38,"_",AD38),_xlfn.CONCAT(K38,"_",M38,"_",O38,"_",Q38,"_",S38,"_",U38,"_",Y38,"_",AA38,"_",AB38,"_",AD38,".odm",AE38)),IF(AE38="",_xlfn.CONCAT(K38,"_",M38,"_",W38,"_",AD38),_xlfn.CONCAT(K38,"_",M38,"_",W38,"_",AD38,".odm",AE38))),"NA") -> 0 | H38: =IF(I38="attributes",IF(AE38="",_xlfn.CONCAT(K38,"_",AD38),_xlfn.CONCAT(K38,"_",AD38,".odm",AE38)),"NA") -> 0 | I38: attributes | J38: Sites table Shorthand | K38: =IFERROR(VLOOKUP(J38,'wideName-Dropdowns'!$A:$B,2,FALSE),"") -> 0 | M38: =IFERROR(VLOOKUP(L38,'wideName-Dropdowns'!$C:$D,2,FALSE),"") -> 0 | O38: =IFERROR(VLOOKUP(N38,'wideName-Dropdowns'!$E:$F,2,FALSE),"") -> 0 | Q38: =IFERROR(VLOOKUP(P38,'wideName-Dropdowns'!$G:$H,2,FALSE),"") -> 0 | S38: =IFERROR(VLOOKUP(R38,'wideName-Dropdowns'!$I:$J,2,FALSE),"") -> 0 | U38: =IFERROR(VLOOKUP(T38,'wideName-Dropdowns'!$K:$L,2,FALSE),"") -> 0 | W38: =IFERROR(VLOOKUP(V38,'wideName-Dropdowns'!$M:$N,2,FALSE),"") -> 0 | Y38: =IFERROR(VLOOKUP(X38,'wideName-Dropdowns'!$O:$P,2,FALSE),"") -> 0 | AA38: =IFERROR(VLOOKUP(Z38,'wideName-Dropdowns'!$Q:$R,2,FALSE),"") -> 0 | AC38: Sample shed | AD38: =IFERROR(VLOOKUP(AC38,'wideName-Dropdowns'!$S:$T,2,FALSE),"") -> 0
A39: =IF(I39="attributes",H39,IF(I39="measurements",F39,G39)) -> 0 | B39: Sampling location type | C39: =LEN(A39) -> 0 | D39: The type of site for collection in terms of the physical infrastructure. For example, a branch sewer pipeline, or a holding tank. | E39: HPAIV H5N1 Template | F39: =IF(I39="measurements",IF(AE39="",_xlfn.CONCAT(O39,"_",Q39,"_",S39,"_",U39,"_",Y39,"_",AA39,"_",AB39,"_",AD39),_xlfn.CONCAT(O39,"_",Q39,"_",S39,"_",U39,"_",Y39,"_",AA39,"_",AB39,"_",AD39,".odm",AE39)),"NA") -> 0 | G39: =IF(I39="methods",IF(L39="measurement",IF(AE39="",_xlfn.CONCAT(K39,"_",M39,"_",O39,"_",Q39,"_",S39,"_",U39,"_",Y39,"_",AA39,"_",AB39,"_",AD39),_xlfn.CONCAT(K39,"_",M39,"_",O39,"_",Q39,"_",S39,"_",U39,"_",Y39,"_",AA39,"_",AB39,"_",AD39,".odm",AE39)),IF(AE39="",_xlfn.CONCAT(K39,"_",M39,"_",W39,"_",AD39),_xlfn.CONCAT(K39,"_",M39,"_",W39,"_",AD39,".odm",AE39))),"NA") -> 0 | H39: =IF(I39="attributes",IF(AE39="",_xlfn.CONCAT(K39,"_",AD39),_xlfn.CONCAT(K39,"_",AD39,".odm",AE39)),"NA") -> 0 | I39: attributes | J39: Sites table Shorthand | K39: =IFERROR(VLOOKUP(J39,'wideName-Dropdowns'!$A:$B,2,FALSE),"") -> 0 | M39: =IFERROR(VLOOKUP(L39,'wideName-Dropdowns'!$C:$D,2,FALSE),"") -> 0 | O39: =IFERROR(VLOOKUP(N39,'wideName-Dropdowns'!$E:$F,2,FALSE),"") -> 0 | Q39: =IFERROR(VLOOKUP(P39,'wideName-Dropdowns'!$G:$H,2,FALSE),"") -> 0 | S39: =IFERROR(VLOOKUP(R39,'wideName-Dropdowns'!$I:$J,2,FALSE),"") -> 0 | U39: =IFERROR(VLOOKUP(T39,'wideName-Dropdowns'!$K:$L,2,FALSE),"") -> 0 | W39: =IFERROR(VLOOKUP(V39,'wideName-Dropdowns'!$M:$N,2,FALSE),"") -> 0 | Y39: =IFERROR(VLOOKUP(X39,'wideName-Dropdowns'!$O:$P,2,FALSE),"") -> 0 | AA39: =IFERROR(VLOOKUP(Z39,'wideName-Dropdowns'!$Q:$R,2,FALSE),"") -> 0 | AC39: Site Type | AD39: =IFERROR(VLOOKUP(AC39,'wideName-Dropdowns'!$S:$T,2,FALSE),"") -> 0
A40: =IF(I40="attributes",H40,IF(I40="measurements",F40,G40)) -> 0 | B40: Population served | C40: =LEN(A40) -> 0 | D40: The population served by a site. | E40: HPAIV H5N1 Template | F40: =IF(I40="measurements",IF(AE40="",_xlfn.CONCAT(O40,"_",Q40,"_",S40,"_",U40,"_",Y40,"_",AA40,"_",AB40,"_",AD40),_xlfn.CONCAT(O40,"_",Q40,"_",S40,"_",U40,"_",Y40,"_",AA40,"_",AB40,"_",AD40,".odm",AE40)),"NA") -> 0 | G40: =IF(I40="methods",IF(L40="measurement",IF(AE40="",_xlfn.CONCAT(K40,"_",M40,"_",O40,"_",Q40,"_",S40,"_",U40,"_",Y40,"_",AA40,"_",AB40,"_",AD40),_xlfn.CONCAT(K40,"_",M40,"_",O40,"_",Q40,"_",S40,"_",U40,"_",Y40,"_",AA40,"_",AB40,"_",AD40,".odm",AE40)),IF(AE40="",_xlfn.CONCAT(K40,"_",M40,"_",W40,"_",AD40),_xlfn.CONCAT(K40,"_",M40,"_",W40,"_",AD40,".odm",AE40))),"NA") -> 0 | H40: =IF(I40="attributes",IF(AE40="",_xlfn.CONCAT(K40,"_",AD40),_xlfn.CONCAT(K40,"_",AD40,".odm",AE40)),"NA") -> 0 | I40: measurements | J40: Measure report table Shorthand | K40: =IFERROR(VLOOKUP(J40,'wideName-Dropdowns'!$A:$B,2,FALSE),"") -> 0 | M40: =IFERROR(VLOOKUP(L40,'wideName-Dropdowns'!$C:$D,2,FALSE),"") -> 0 | N40: Human compartment | O40: =IFERROR(VLOOKUP(N40,'wideName-Dropdowns'!$E:$F,2,FALSE),"") -> 0 | P40: Site | Q40: =IFERROR(VLOOKUP(P40,'wideName-Dropdowns'!$G:$H,2,FALSE),"") -> 0 | R40: Not applicable | S40: =IFERROR(VLOOKUP(R40,'wideName-Dropdowns'!$I:$J,2,FALSE),"") -> 0 | T40: Population Served | U40: =IFERROR(VLOOKUP(T40,'wideName-Dropdowns'!$K:$L,2,FALSE),"") -> 0 | W40: =IFERROR(VLOOKUP(V40,'wideName-Dropdowns'!$M:$N,2,FALSE),"") -> 0 | X40: Number of people | Y40: =IFERROR(VLOOKUP(X40,'wideName-Dropdowns'!$O:$P,2,FALSE),"") -> 0 | Z40: Total amount or count - the sum | AA40: =IFERROR(VLOOKUP(Z40,'wideName-Dropdowns'!$Q:$R,2,FALSE),"") -> 0 | AB40: NA | AC40: Value | AD40: =IFERROR(VLOOKUP(AC40,'wideName-Dropdowns'!$S:$T,2,FALSE),"") -> 0
A41: =IF(I41="attributes",H41,IF(I41="measurements",F41,G41)) -> 0 | B41: SampleID | C41: =LEN(A41) -> 0 | D41: The unique identifier for a sample. | E41: HPAIV H5N1 Template | F41: =IF(I41="measurements",IF(AE41="",_xlfn.CONCAT(O41,"_",Q41,"_",S41,"_",U41,"_",Y41,"_",AA41,"_",AB41,"_",AD41),_xlfn.CONCAT(O41,"_",Q41,"_",S41,"_",U41,"_",Y41,"_",AA41,"_",AB41,"_",AD41,".odm",AE41)),"NA") -> 0 | G41: =IF(I41="methods",IF(L41="measurement",IF(AE41="",_xlfn.CONCAT(K41,"_",M41,"_",O41,"_",Q41,"_",S41,"_",U41,"_",Y41,"_",AA41,"_",AB41,"_",AD41),_xlfn.CONCAT(K41,"_",M41,"_",O41,"_",Q41,"_",S41,"_",U41,"_",Y41,"_",AA41,"_",AB41,"_",AD41,".odm",AE41)),IF(AE41="",_xlfn.CONCAT(K41,"_",M41,"_",W41,"_",AD41),_xlfn.CONCAT(K41,"_",M41,"_",W41,"_",AD41,".odm",AE41))),"NA") -> 0 | H41: =IF(I41="attributes",IF(AE41="",_xlfn.CONCAT(K41,"_",AD41),_xlfn.CONCAT(K41,"_",AD41,".odm",AE41)),"NA") -> 0 | I41: attributes | J41: Sample relationships table Shorthand | K41: =IFERROR(VLOOKUP(J41,'wideName-Dropdowns'!$A:$B,2,FALSE),"") -> 0 | M41: =IFERROR(VLOOKUP(L41,'wideName-Dropdowns'!$C:$D,2,FALSE),"") -> 0 | O41: =IFERROR(VLOOKUP(N41,'wideName-Dropdowns'!$E:$F,2,FALSE),"") -> 0 | Q41: =IFERROR(VLOOKUP(P41,'wideName-Dropdowns'!$G:$H,2,FALSE),"") -> 0 | S41: =IFERROR(VLOOKUP(R41,'wideName-Dropdowns'!$I:$J,2,FALSE),"") -> 0 | U41: =IFERROR(VLOOKUP(T41,'wideName-Dropdowns'!$K:$L,2,FALSE),"") -> 0 | W41: =IFERROR(VLOOKUP(V41,'wideName-Dropdowns'!$M:$N,2,FALSE),"") -> 0 | Y41: =IFERROR(VLOOKUP(X41,'wideName-Dropdowns'!$O:$P,2,FALSE),"") -> 0 | AA41: =IFERROR(VLOOKUP(Z41,'wideName-Dropdowns'!$Q:$R,2,FALSE),"") -> 0 | AC41: Sample ID | AD41: =IFERROR(VLOOKUP(AC41,'wideName-Dropdowns'!$S:$T,2,FALSE),"") -> 0
A42: =IF(I42="attributes",H42,IF(I42="measurements",F42,G42)) -> 0 | B42: Collection date/time | C42: =LEN(A42) -> 0 | D42: The date and time of sample collection. | E42: HPAIV H5N1 Template | F42: =IF(I42="measurements",IF(AE42="",_xlfn.CONCAT(O42,"_",Q42,"_",S42,"_",U42,"_",Y42,"_",AA42,"_",AB42,"_",AD42),_xlfn.CONCAT(O42,"_",Q42,"_",S42,"_",U42,"_",Y42,"_",AA42,"_",AB42,"_",AD42,".odm",AE42)),"NA") -> 0 | G42: =IF(I42="methods",IF(L42="measurement",IF(AE42="",_xlfn.CONCAT(K42,"_",M42,"_",O42,"_",Q42,"_",S42,"_",U42,"_",Y42,"_",AA42,"_",AB42,"_",AD42),_xlfn.CONCAT(K42,"_",M42,"_",O42,"_",Q42,"_",S42,"_",U42,"_",Y42,"_",AA42,"_",AB42,"_",AD42,".odm",AE42)),IF(AE42="",_xlfn.CONCAT(K42,"_",M42,"_",W42,"_",AD42),_xlfn.CONCAT(K42,"_",M42,"_",W42,"_",AD42,".odm",AE42))),"NA") -> 0 | H42: =IF(I42="attributes",IF(AE42="",_xlfn.CONCAT(K42,"_",AD42),_xlfn.CONCAT(K42,"_",AD42,".odm",AE42)),"NA") -> 0 | I42: attributes | J42: Sample relationships table Shorthand | K42: =IFERROR(VLOOKUP(J42,'wideName-Dropdowns'!$A:$B,2,FALSE),"") -> 0 | M42: =IFERROR(VLOOKUP(L42,'wideName-Dropdowns'!$C:$D,2,FALSE),"") -> 0 | O42: =IFERROR(VLOOKUP(N42,'wideName-Dropdowns'!$E:$F,2,FALSE),"") -> 0 | Q42: =IFERROR(VLOOKUP(P42,'wideName-Dropdowns'!$G:$H,2,FALSE),"") -> 0 | S42: =IFERROR(VLOOKUP(R42,'wideName-Dropdowns'!$I:$J,2,FALSE),"") -> 0 | U42: =IFERROR(VLOOKUP(T42,'wideName-Dropdowns'!$K:$L,2,FALSE),"") -> 0 | W42: =IFERROR(VLOOKUP(V42,'wideName-Dropdowns'!$M:$N,2,FALSE),"") -> 0 | Y42: =IFERROR(VLOOKUP(X42,'wideName-Dropdowns'!$O:$P,2,FALSE),"") -> 0 | AA42: =IFERROR(VLOOKUP(Z42,'wideName-Dropdowns'!$Q:$R,2,FALSE),"") -> 0 | AC42: Collection date time | AD42: =IFERROR(VLOOKUP(AC42,'wideName-Dropdowns'!$S:$T,2,FALSE),"") -> 0
A43: =IF(I43="attributes",H43,IF(I43="measurements",F43,G43)) -> 0 | B43: Collection type | C43: =LEN(A43) -> 0 | D43: The type of sample collection used to gather the sample (ie. Passive sample, grab sample, etc.) | E43: HPAIV H5N1 Template | F43: =IF(I43="measurements",IF(AE43="",_xlfn.CONCAT(O43,"_",Q43,"_",S43,"_",U43,"_",Y43,"_",AA43,"_",AB43,"_",AD43),_xlfn.CONCAT(O43,"_",Q43,"_",S43,"_",U43,"_",Y43,"_",AA43,"_",AB43,"_",AD43,".odm",AE43)),"NA") -> 0 | G43: =IF(I43="methods",IF(L43="measurement",IF(AE43="",_xlfn.CONCAT(K43,"_",M43,"_",O43,"_",Q43,"_",S43,"_",U43,"_",Y43,"_",AA43,"_",AB43,"_",AD43),_xlfn.CONCAT(K43,"_",M43,"_",O43,"_",Q43,"_",S43,"_",U43,"_",Y43,"_",AA43,"_",AB43,"_",AD43,".odm",AE43)),IF(AE43="",_xlfn.CONCAT(K43,"_",M43,"_",W43,"_",AD43),_xlfn.CONCAT(K43,"_",M43,"_",W43,"_",AD43,".odm",AE43))),"NA") -> 0 | H43: =IF(I43="attributes",IF(AE43="",_xlfn.CONCAT(K43,"_",AD43),_xlfn.CONCAT(K43,"_",AD43,".odm",AE43)),"NA") -> 0 | I43: attributes | J43: Sample relationships table Shorthand | K43: =IFERROR(VLOOKUP(J43,'wideName-Dropdowns'!$A:$B,2,FALSE),"") -> 0 | M43: =IFERROR(VLOOKUP(L43,'wideName-Dropdowns'!$C:$D,2,FALSE),"") -> 0 | O43: =IFERROR(VLOOKUP(N43,'wideName-Dropdowns'!$E:$F,2,FALSE),"") -> 0 | Q43: =IFERROR(VLOOKUP(P43,'wideName-Dropdowns'!$G:$H,2,FALSE),"") -> 0 | S43: =IFERROR(VLOOKUP(R43,'wideName-Dropdowns'!$I:$J,2,FALSE),"") -> 0 | U43: =IFERROR(VLOOKUP(T43,'wideName-Dropdowns'!$K:$L,2,FALSE),"") -> 0 | W43: =IFERROR(VLOOKUP(V43,'wideName-Dropdowns'!$M:$N,2,FALSE),"") -> 0 | Y43: =IFERROR(VLOOKUP(X43,'wideName-Dropdowns'!$O:$P,2,FALSE),"") -> 0 | AA43: =IFERROR(VLOOKUP(Z43,'wideName-Dropdowns'!$Q:$R,2,FALSE),"") -> 0 | AC43: Sample collection type | AD43: =IFERROR(VLOOKUP(AC43,'wideName-Dropdowns'!$S:$T,2,FALSE),"") -> 0
A44: =IF(I44="attributes",H44,IF(I44="measurements",F44,G44)) -> 0 | B44: Composite collection period | C44: =LEN(A44) -> 0 | D44: Used for composite samples, this specifies the time period for sample collection. | E44: HPAIV H5N1 Template | F44: =IF(I44="measurements",IF(AE44="",_xlfn.CONCAT(O44,"_",Q44,"_",S44,"_",U44,"_",Y44,"_",AA44,"_",AB44,"_",AD44),_xlfn.CONCAT(O44,"_",Q44,"_",S44,"_",U44,"_",Y44,"_",AA44,"_",AB44,"_",AD44,".odm",AE44)),"NA") -> 0 | G44: =IF(I44="methods",IF(L44="measurement",IF(AE44="",_xlfn.CONCAT(K44,"_",M44,"_",O44,"_",Q44,"_",S44,"_",U44,"_",Y44,"_",AA44,"_",AB44,"_",AD44),_xlfn.CONCAT(K44,"_",M44,"_",O44,"_",Q44,"_",S44,"_",U44,"_",Y44,"_",AA44,"_",AB44,"_",AD44,".odm",AE44)),IF(AE44="",_xlfn.CONCAT(K44,"_",M44,"_",W44,"_",AD44),_xlfn.CONCAT(K44,"_",M44,"_",W44,"_",AD44,".odm",AE44))),"NA") -> 0 | H44: =IF(I44="attributes",IF(AE44="",_xlfn.CONCAT(K44,"_",AD44),_xlfn.CONCAT(K44,"_",AD44,".odm",AE44)),"NA") -> 0 | I44: attributes | J44: Sample relationships table Shorthand | K44: =IFERROR(VLOOKUP(J44,'wideName-Dropdowns'!$A:$B,2,FALSE),"") -> 0 | M44: =IFERROR(VLOOKUP(L44,'wideName-Dropdowns'!$C:$D,2,FALSE),"") -> 0 | O44: =IFERROR(VLOOKUP(N44,'wideName-Dropdowns'!$E:$F,2,FALSE),"") -> 0 | Q44: =IFERROR(VLOOKUP(P44,'wideName-Dropdowns'!$G:$H,2,FALSE),"") -> 0 | S44: =IFERROR(VLOOKUP(R44,'wideName-Dropdowns'!$I:$J,2,FALSE),"") -> 0 | U44: =IFERROR(VLOOKUP(T44,'wideName-Dropdowns'!$K:$L,2,FALSE),"") -> 0 | W44: =IFERROR(VLOOKUP(V44,'wideName-Dropdowns'!$M:$N,2,FALSE),"") -> 0 | Y44: =IFERROR(VLOOKUP(X44,'wideName-Dropdowns'!$O:$P,2,FALSE),"") -> 0 | AA44: =IFERROR(VLOOKUP(Z44,'wideName-Dropdowns'!$Q:$R,2,FALSE),"") -> 0 | AC44: Collection period | AD44: =IFERROR(VLOOKUP(AC44,'wideName-Dropdowns'!$S:$T,2,FALSE),"") -> 0
A45: =IF(I45="attributes",H45,IF(I45="measurements",F45,G45)) -> 0 | B45: Composite collection number | C45: =LEN(A45) -> 0 | D45: Used for composite samples, this specifies the number of sub-samples taken for build the composite. | E45: HPAIV H5N1 Template | F45: =IF(I45="measurements",IF(AE45="",_xlfn.CONCAT(O45,"_",Q45,"_",S45,"_",U45,"_",Y45,"_",AA45,"_",AB45,"_",AD45),_xlfn.CONCAT(O45,"_",Q45,"_",S45,"_",U45,"_",Y45,"_",AA45,"_",AB45,"_",AD45,".odm",AE45)),"NA") -> 0 | G45: =IF(I45="methods",IF(L45="measurement",IF(AE45="",_xlfn.CONCAT(K45,"_",M45,"_",O45,"_",Q45,"_",S45,"_",U45,"_",Y45,"_",AA45,"_",AB45,"_",AD45),_xlfn.CONCAT(K45,"_",M45,"_",O45,"_",Q45,"_",S45,"_",U45,"_",Y45,"_",AA45,"_",AB45,"_",AD45,".odm",AE45)),IF(AE45="",_xlfn.CONCAT(K45,"_",M45,"_",W45,"_",AD45),_xlfn.CONCAT(K45,"_",M45,"_",W45,"_",AD45,".odm",AE45))),"NA") -> 0 | H45: =IF(I45="attributes",IF(AE45="",_xlfn.CONCAT(K45,"_",AD45),_xlfn.CONCAT(K45,"_",AD45,".odm",AE45)),"NA") -> 0 | I45: attributes | J45: Sample relationships table Shorthand | K45: =IFERROR(VLOOKUP(J45,'wideName-Dropdowns'!$A:$B,2,FALSE),"") -> 0 | M45: =IFERROR(VLOOKUP(L45,'wideName-Dropdowns'!$C:$D,2,FALSE),"") -> 0 | O45: =IFERROR(VLOOKUP(N45,'wideName-Dropdowns'!$E:$F,2,FALSE),"") -> 0 | Q45: =IFERROR(VLOOKUP(P45,'wideName-Dropdowns'!$G:$H,2,FALSE),"") -> 0 | S45: =IFERROR(VLOOKUP(R45,'wideName-Dropdowns'!$I:$J,2,FALSE),"") -> 0 | U45: =IFERROR(VLOOKUP(T45,'wideName-Dropdowns'!$K:$L,2,FALSE),"") -> 0 | W45: =IFERROR(VLOOKUP(V45,'wideName-Dropdowns'!$M:$N,2,FALSE),"") -> 0 | Y45: =IFERROR(VLOOKUP(X45,'wideName-Dropdowns'!$O:$P,2,FALSE),"") -> 0 | AA45: =IFERROR(VLOOKUP(Z45,'wideName-Dropdowns'!$Q:$R,2,FALSE),"") -> 0 | AC45: Collection number | AD45: =IFERROR(VLOOKUP(AC45,'wideName-Dropdowns'!$S:$T,2,FALSE),"") -> 0
A46: =IF(I46="attributes",H46,IF(I46="measurements",F46,G46)) -> 0 | B46: Pooled | C46: =LEN(A46) -> 0 | D46: A binary indicaotr for whether the sample is pooled or not. | E46: HPAIV H5N1 Template | F46: =IF(I46="measurements",IF(AE46="",_xlfn.CONCAT(O46,"_",Q46,"_",S46,"_",U46,"_",Y46,"_",AA46,"_",AB46,"_",AD46),_xlfn.CONCAT(O46,"_",Q46,"_",S46,"_",U46,"_",Y46,"_",AA46,"_",AB46,"_",AD46,".odm",AE46)),"NA") -> 0 | G46: =IF(I46="methods",IF(L46="measurement",IF(AE46="",_xlfn.CONCAT(K46,"_",M46,"_",O46,"_",Q46,"_",S46,"_",U46,"_",Y46,"_",AA46,"_",AB46,"_",AD46),_xlfn.CONCAT(K46,"_",M46,"_",O46,"_",Q46,"_",S46,"_",U46,"_",Y46,"_",AA46,"_",AB46,"_",AD46,".odm",AE46)),IF(AE46="",_xlfn.CONCAT(K46,"_",M46,"_",W46,"_",AD46),_xlfn.CONCAT(K46,"_",M46,"_",W46,"_",AD46,".odm",AE46))),"NA") -> 0 | H46: =IF(I46="attributes",IF(AE46="",_xlfn.CONCAT(K46,"_",AD46),_xlfn.CONCAT(K46,"_",AD46,".odm",AE46)),"NA") -> 0 | I46: attributes | J46: Sample relationships table Shorthand | K46: =IFERROR(VLOOKUP(J46,'wideName-Dropdowns'!$A:$B,2,FALSE),"") -> 0 | M46: =IFERROR(VLOOKUP(L46,'wideName-Dropdowns'!$C:$D,2,FALSE),"") -> 0 | O46: =IFERROR(VLOOKUP(N46,'wideName-Dropdowns'!$E:$F,2,FALSE),"") -> 0 | Q46: =IFERROR(VLOOKUP(P46,'wideName-Dropdowns'!$G:$H,2,FALSE),"") -> 0 | S46: =IFERROR(VLOOKUP(R46,'wideName-Dropdowns'!$I:$J,2,FALSE),"") -> 0 | U46: =IFERROR(VLOOKUP(T46,'wideName-Dropdowns'!$K:$L,2,FALSE),"") -> 0 | W46: =IFERROR(VLOOKUP(V46,'wideName-Dropdowns'!$M:$N,2,FALSE),"") -> 0 | Y46: =IFERROR(VLOOKUP(X46,'wideName-Dropdowns'!$O:$P,2,FALSE),"") -> 0 | AA46: =IFERROR(VLOOKUP(Z46,'wideName-Dropdowns'!$Q:$R,2,FALSE),"") -> 0 | AC46: Pooled | AD46: =IFERROR(VLOOKUP(AC46,'wideName-Dropdowns'!$S:$T,2,FALSE),"") -> 0
A47: =IF(I47="attributes",H47,IF(I47="measurements",F47,G47)) -> 0 | B47: Analysis date/time start | C47: =LEN(A47) -> 0 | D47: The date and time that analysis was started. | E47: HPAIV H5N1 Template | F47: =IF(I47="measurements",IF(AE47="",_xlfn.CONCAT(O47,"_",Q47,"_",S47,"_",U47,"_",Y47,"_",AA47,"_",AB47,"_",AD47),_xlfn.CONCAT(O47,"_",Q47,"_",S47,"_",U47,"_",Y47,"_",AA47,"_",AB47,"_",AD47,".odm",AE47)),"NA") -> 0 | G47: =IF(I47="methods",IF(L47="measurement",IF(AE47="",_xlfn.CONCAT(K47,"_",M47,"_",O47,"_",Q47,"_",S47,"_",U47,"_",Y47,"_",AA47,"_",AB47,"_",AD47),_xlfn.CONCAT(K47,"_",M47,"_",O47,"_",Q47,"_",S47,"_",U47,"_",Y47,"_",AA47,"_",AB47,"_",AD47,".odm",AE47)),IF(AE47="",_xlfn.CONCAT(K47,"_",M47,"_",W47,"_",AD47),_xlfn.CONCAT(K47,"_",M47,"_",W47,"_",AD47,".odm",AE47))),"NA") -> 0 | H47: =IF(I47="attributes",IF(AE47="",_xlfn.CONCAT(K47,"_",AD47),_xlfn.CONCAT(K47,"_",AD47,".odm",AE47)),"NA") -> 0 | I47: attributes | J47: Measure report table Shorthand | K47: =IFERROR(VLOOKUP(J47,'wideName-Dropdowns'!$A:$B,2,FALSE),"") -> 0 | M47: =IFERROR(VLOOKUP(L47,'wideName-Dropdowns'!$C:$D,2,FALSE),"") -> 0 | O47: =IFERROR(VLOOKUP(N47,'wideName-Dropdowns'!$E:$F,2,FALSE),"") -> 0 | Q47: =IFERROR(VLOOKUP(P47,'wideName-Dropdowns'!$G:$H,2,FALSE),"") -> 0 | S47: =IFERROR(VLOOKUP(R47,'wideName-Dropdowns'!$I:$J,2,FALSE),"") -> 0 | U47: =IFERROR(VLOOKUP(T47,'wideName-Dropdowns'!$K:$L,2,FALSE),"") -> 0 | W47: =IFERROR(VLOOKUP(V47,'wideName-Dropdowns'!$M:$N,2,FALSE),"") -> 0 | Y47: =IFERROR(VLOOKUP(X47,'wideName-Dropdowns'!$O:$P,2,FALSE),"") -> 0 | AA47: =IFERROR(VLOOKUP(Z47,'wideName-Dropdowns'!$Q:$R,2,FALSE),"") -> 0 | AC47: Analysis date start | AD47: =IFERROR(VLOOKUP(AC47,'wideName-Dropdowns'!$S:$T,2,FALSE),"") -> 0
A48: =IF(I48="attributes",H48,IF(I48="measurements",F48,G48)) -> 0 | B48: Analysis date/time end | C48: =LEN(A48) -> 0 | D48: The date and time when analysis was complete. | E48: HPAIV H5N1 Template | F48: =IF(I48="measurements",IF(AE48="",_xlfn.CONCAT(O48,"_",Q48,"_",S48,"_",U48,"_",Y48,"_",AA48,"_",AB48,"_",AD48),_xlfn.CONCAT(O48,"_",Q48,"_",S48,"_",U48,"_",Y48,"_",AA48,"_",AB48,"_",AD48,".odm",AE48)),"NA") -> 0 | G48: =IF(I48="methods",IF(L48="measurement",IF(AE48="",_xlfn.CONCAT(K48,"_",M48,"_",O48,"_",Q48,"_",S48,"_",U48,"_",Y48,"_",AA48,"_",AB48,"_",AD48),_xlfn.CONCAT(K48,"_",M48,"_",O48,"_",Q48,"_",S48,"_",U48,"_",Y48,"_",AA48,"_",AB48,"_",AD48,".odm",AE48)),IF(AE48="",_xlfn.CONCAT(K48,"_",M48,"_",W48,"_",AD48),_xlfn.CONCAT(K48,"_",M48,"_",W48,"_",AD48,".odm",AE48))),"NA") -> 0 | H48: =IF(I48="attributes",IF(AE48="",_xlfn.CONCAT(K48,"_",AD48),_xlfn.CONCAT(K48,"_",AD48,".odm",AE48)),"NA") -> 0 | I48: attributes | J48: Measure report table Shorthand | K48: =IFERROR(VLOOKUP(J48,'wideName-Dropdowns'!$A:$B,2,FALSE),"") -> 0 | M48: =IFERROR(VLOOKUP(L48,'wideName-Dropdowns'!$C:$D,2,FALSE),"") -> 0 | O48: =IFERROR(VLOOKUP(N48,'wideName-Dropdowns'!$E:$F,2,FALSE),"") -> 0 | Q48: =IFERROR(VLOOKUP(P48,'wideName-Dropdowns'!$G:$H,2,FALSE),"") -> 0 | S48: =IFERROR(VLOOKUP(R48,'wideName-Dropdowns'!$I:$J,2,FALSE),"") -> 0 | U48: =IFERROR(VLOOKUP(T48,'wideName-Dropdowns'!$K:$L,2,FALSE),"") -> 0 | W48: =IFERROR(VLOOKUP(V48,'wideName-Dropdowns'!$M:$N,2,FALSE),"") -> 0 | Y48: =IFERROR(VLOOKUP(X48,'wideName-Dropdowns'!$O:$P,2,FALSE),"") -> 0 | AA48: =IFERROR(VLOOKUP(Z48,'wideName-Dropdowns'!$Q:$R,2,FALSE),"") -> 0 | AC48: Analysis date end | AD48: =IFERROR(VLOOKUP(AC48,'wideName-Dropdowns'!$S:$T,2,FALSE),"") -> 0
A49: =IF(I49="attributes",H49,IF(I49="measurements",F49,G49)) -> 0 | B49: Fraction analyzed | C49: =LEN(A49) -> 0 | D49: The fraction of the wastewater used for analysis and measurement. | E49: HPAIV H5N1 Template | F49: =IF(I49="measurements",IF(AE49="",_xlfn.CONCAT(O49,"_",Q49,"_",S49,"_",U49,"_",Y49,"_",AA49,"_",AB49,"_",AD49),_xlfn.CONCAT(O49,"_",Q49,"_",S49,"_",U49,"_",Y49,"_",AA49,"_",AB49,"_",AD49,".odm",AE49)),"NA") -> 0 | G49: =IF(I49="methods",IF(L49="measurement",IF(AE49="",_xlfn.CONCAT(K49,"_",M49,"_",O49,"_",Q49,"_",S49,"_",U49,"_",Y49,"_",AA49,"_",AB49,"_",AD49),_xlfn.CONCAT(K49,"_",M49,"_",O49,"_",Q49,"_",S49,"_",U49,"_",Y49,"_",AA49,"_",AB49,"_",AD49,".odm",AE49)),IF(AE49="",_xlfn.CONCAT(K49,"_",M49,"_",W49,"_",AD49),_xlfn.CONCAT(K49,"_",M49,"_",W49,"_",AD49,".odm",AE49))),"NA") -> 0 | H49: =IF(I49="attributes",IF(AE49="",_xlfn.CONCAT(K49,"_",AD49),_xlfn.CONCAT(K49,"_",AD49,".odm",AE49)),"NA") -> 0 | I49: attributes | J49: Measure report table Shorthand | K49: =IFERROR(VLOOKUP(J49,'wideName-Dropdowns'!$A:$B,2,FALSE),"") -> 0 | M49: =IFERROR(VLOOKUP(L49,'wideName-Dropdowns'!$C:$D,2,FALSE),"") -> 0 | O49: =IFERROR(VLOOKUP(N49,'wideName-Dropdowns'!$E:$F,2,FALSE),"") -> 0 | Q49: =IFERROR(VLOOKUP(P49,'wideName-Dropdowns'!$G:$H,2,FALSE),"") -> 0 | S49: =IFERROR(VLOOKUP(R49,'wideName-Dropdowns'!$I:$J,2,FALSE),"") -> 0 | U49: =IFERROR(VLOOKUP(T49,'wideName-Dropdowns'!$K:$L,2,FALSE),"") -> 0 | W49: =IFERROR(VLOOKUP(V49,'wideName-Dropdowns'!$M:$N,2,FALSE),"") -> 0 | Y49: =IFERROR(VLOOKUP(X49,'wideName-Dropdowns'!$O:$P,2,FALSE),"") -> 0 | AA49: =IFERROR(VLOOKUP(Z49,'wideName-Dropdowns'!$Q:$R,2,FALSE),"") -> 0 | AC49: Fraction analyzed | AD49: =IFERROR(VLOOKUP(AC49,'wideName-Dropdowns'!$S:$T,2,FALSE),"") -> 0
A50: =IF(I50="attributes",H50,IF(I50="measurements",F50,G50)) -> 0 | B50: Sample type | C50: =LEN(A50) -> 0 | D50: The type of material that comprises the sample (ie. Primary effluent, de-watered solids, etc.) | E50: HPAIV H5N1 Template | F50: =IF(I50="measurements",IF(AE50="",_xlfn.CONCAT(O50,"_",Q50,"_",S50,"_",U50,"_",Y50,"_",AA50,"_",AB50,"_",AD50),_xlfn.CONCAT(O50,"_",Q50,"_",S50,"_",U50,"_",Y50,"_",AA50,"_",AB50,"_",AD50,".odm",AE50)),"NA") -> 0 | G50: =IF(I50="methods",IF(L50="measurement",IF(AE50="",_xlfn.CONCAT(K50,"_",M50,"_",O50,"_",Q50,"_",S50,"_",U50,"_",Y50,"_",AA50,"_",AB50,"_",AD50),_xlfn.CONCAT(K50,"_",M50,"_",O50,"_",Q50,"_",S50,"_",U50,"_",Y50,"_",AA50,"_",AB50,"_",AD50,".odm",AE50)),IF(AE50="",_xlfn.CONCAT(K50,"_",M50,"_",W50,"_",AD50),_xlfn.CONCAT(K50,"_",M50,"_",W50,"_",AD50,".odm",AE50))),"NA") -> 0 | H50: =IF(I50="attributes",IF(AE50="",_xlfn.CONCAT(K50,"_",AD50),_xlfn.CONCAT(K50,"_",AD50,".odm",AE50)),"NA") -> 0 | I50: attributes | J50: Sample relationships table Shorthand | K50: =IFERROR(VLOOKUP(J50,'wideName-Dropdowns'!$A:$B,2,FALSE),"") -> 0 | M50: =IFERROR(VLOOKUP(L50,'wideName-Dropdowns'!$C:$D,2,FALSE),"") -> 0 | O50: =IFERROR(VLOOKUP(N50,'wideName-Dropdowns'!$E:$F,2,FALSE),"") -> 0 | Q50: =IFERROR(VLOOKUP(P50,'wideName-Dropdowns'!$G:$H,2,FALSE),"") -> 0 | S50: =IFERROR(VLOOKUP(R50,'wideName-Dropdowns'!$I:$J,2,FALSE),"") -> 0 | U50: =IFERROR(VLOOKUP(T50,'wideName-Dropdowns'!$K:$L,2,FALSE),"") -> 0 | W50: =IFERROR(VLOOKUP(V50,'wideName-Dropdowns'!$M:$N,2,FALSE),"") -> 0 | Y50: =IFERROR(VLOOKUP(X50,'wideName-Dropdowns'!$O:$P,2,FALSE),"") -> 0 | AA50: =IFERROR(VLOOKUP(Z50,'wideName-Dropdowns'!$Q:$R,2,FALSE),"") -> 0 | AC50: Sample material | AD50: =IFERROR(VLOOKUP(AC50,'wideName-Dropdowns'!$S:$T,2,FALSE),"") -> 0
A51: =IF(I51="attributes",H51,IF(I51="measurements",F51,G51)) -> 0 | B51: PCR method used | C51: =LEN(A51) -> 0 | D51: The PCR method used for measuring genes of interest. | E51: HPAIV H5N1 Template | F51: =IF(I51="measurements",IF(AE51="",_xlfn.CONCAT(O51,"_",Q51,"_",S51,"_",U51,"_",Y51,"_",AA51,"_",AB51,"_",AD51),_xlfn.CONCAT(O51,"_",Q51,"_",S51,"_",U51,"_",Y51,"_",AA51,"_",AB51,"_",AD51,".odm",AE51)),"NA") -> 0 | G51: =IF(I51="methods",IF(L51="measurement",IF(AE51="",_xlfn.CONCAT(K51,"_",M51,"_",O51,"_",Q51,"_",S51,"_",U51,"_",Y51,"_",AA51,"_",AB51,"_",AD51),_xlfn.CONCAT(K51,"_",M51,"_",O51,"_",Q51,"_",S51,"_",U51,"_",Y51,"_",AA51,"_",AB51,"_",AD51,".odm",AE51)),IF(AE51="",_xlfn.CONCAT(K51,"_",M51,"_",W51,"_",AD51),_xlfn.CONCAT(K51,"_",M51,"_",W51,"_",AD51,".odm",AE51))),"NA") -> 0 | H51: =IF(I51="attributes",IF(AE51="",_xlfn.CONCAT(K51,"_",AD51),_xlfn.CONCAT(K51,"_",AD51,".odm",AE51)),"NA") -> 0 | I51: methods | J51: Protocol steps table Shorthand | K51: =IFERROR(VLOOKUP(J51,'wideName-Dropdowns'!$A:$B,2,FALSE),"") -> 0 | L51: Methods part-type Shorthand | M51: =IFERROR(VLOOKUP(L51,'wideName-Dropdowns'!$C:$D,2,FALSE),"") -> 0 | N51: Water compartment | O51: =IFERROR(VLOOKUP(N51,'wideName-Dropdowns'!$E:$F,2,FALSE),"") -> 0 | P51: Sample | Q51: =IFERROR(VLOOKUP(P51,'wideName-Dropdowns'!$G:$H,2,FALSE),"") -> 0 | S51: =IFERROR(VLOOKUP(R51,'wideName-Dropdowns'!$I:$J,2,FALSE),"") -> 0 | U51: =IFERROR(VLOOKUP(T51,'wideName-Dropdowns'!$K:$L,2,FALSE),"") -> 0 | V51: PCR method | W51: =IFERROR(VLOOKUP(V51,'wideName-Dropdowns'!$M:$N,2,FALSE),"") -> 0 | X51: Unit not applicable | Y51: =IFERROR(VLOOKUP(X51,'wideName-Dropdowns'!$O:$P,2,FALSE),"") -> 0 | Z51: Aggregation not applicable | AA51: =IFERROR(VLOOKUP(Z51,'wideName-Dropdowns'!$Q:$R,2,FALSE),"") -> 0 | AC51: Value | AD51: =IFERROR(VLOOKUP(AC51,'wideName-Dropdowns'!$S:$T,2,FALSE),"") -> 0
A52: =IF(I52="attributes",H52,IF(I52="measurements",F52,G52)) -> 0 | B52: Protocol citation link | C52: =LEN(A52) -> 0 | D52: The URL or link to the materials or details on the analysis protocol. | E52: HPAIV H5N1 Template | F52: =IF(I52="measurements",IF(AE52="",_xlfn.CONCAT(O52,"_",Q52,"_",S52,"_",U52,"_",Y52,"_",AA52,"_",AB52,"_",AD52),_xlfn.CONCAT(O52,"_",Q52,"_",S52,"_",U52,"_",Y52,"_",AA52,"_",AB52,"_",AD52,".odm",AE52)),"NA") -> 0 | G52: =IF(I52="methods",IF(L52="measurement",IF(AE52="",_xlfn.CONCAT(K52,"_",M52,"_",O52,"_",Q52,"_",S52,"_",U52,"_",Y52,"_",AA52,"_",AB52,"_",AD52),_xlfn.CONCAT(K52,"_",M52,"_",O52,"_",Q52,"_",S52,"_",U52,"_",Y52,"_",AA52,"_",AB52,"_",AD52,".odm",AE52)),IF(AE52="",_xlfn.CONCAT(K52,"_",M52,"_",W52,"_",AD52),_xlfn.CONCAT(K52,"_",M52,"_",W52,"_",AD52,".odm",AE52))),"NA") -> 0 | H52: =IF(I52="attributes",IF(AE52="",_xlfn.CONCAT(K52,"_",AD52),_xlfn.CONCAT(K52,"_",AD52,".odm",AE52)),"NA") -> 0 | I52: attributes | J52: Protocols table Shorthand | K52: =IFERROR(VLOOKUP(J52,'wideName-Dropdowns'!$A:$B,2,FALSE),"") -> 0 | M52: =IFERROR(VLOOKUP(L52,'wideName-Dropdowns'!$C:$D,2,FALSE),"") -> 0 | O52: =IFERROR(VLOOKUP(N52,'wideName-Dropdowns'!$E:$F,2,FALSE),"") -> 0 | Q52: =IFERROR(VLOOKUP(P52,'wideName-Dropdowns'!$G:$H,2,FALSE),"") -> 0 | S52: =IFERROR(VLOOKUP(R52,'wideName-Dropdowns'!$I:$J,2,FALSE),"") -> 0 | U52: =IFERROR(VLOOKUP(T52,'wideName-Dropdowns'!$K:$L,2,FALSE),"") -> 0 | W52: =IFERROR(VLOOKUP(V52,'wideName-Dropdowns'!$M:$N,2,FALSE),"") -> 0 | Y52: =IFERROR(VLOOKUP(X52,'wideName-Dropdowns'!$O:$P,2,FALSE),"") -> 0 | AA52: =IFERROR(VLOOKUP(Z52,'wideName-Dropdowns'!$Q:$R,2,FALSE),"") -> 0 | AC52: Reference link | AD52: =IFERROR(VLOOKUP(AC52,'wideName-Dropdowns'!$S:$T,2,FALSE),"") -> 0
A53: =IF(I53="attributes",H53,IF(I53="measurements",F53,G53)) -> 0 | B53: Target Type | C53: =LEN(A53) -> 0 | D53: The genetic "target type" as defined using ODM groups in a wide or combined long-and-wide table. | E53: HPAIV H5N1 Template | F53: =IF(I53="measurements",IF(AE53="",_xlfn.CONCAT(O53,"_",Q53,"_",S53,"_",U53,"_",Y53,"_",AA53,"_",AB53,"_",AD53),_xlfn.CONCAT(O53,"_",Q53,"_",S53,"_",U53,"_",Y53,"_",AA53,"_",AB53,"_",AD53,".odm",AE53)),"NA") -> 0 | G53: =IF(I53="methods",IF(L53="measurement",IF(AE53="",_xlfn.CONCAT(K53,"_",M53,"_",O53,"_",Q53,"_",S53,"_",U53,"_",Y53,"_",AA53,"_",AB53,"_",AD53),_xlfn.CONCAT(K53,"_",M53,"_",O53,"_",Q53,"_",S53,"_",U53,"_",Y53,"_",AA53,"_",AB53,"_",AD53,".odm",AE53)),IF(AE53="",_xlfn.CONCAT(K53,"_",M53,"_",W53,"_",AD53),_xlfn.CONCAT(K53,"_",M53,"_",W53,"_",AD53,".odm",AE53))),"NA") -> 0 | H53: =IF(I53="attributes",IF(AE53="",_xlfn.CONCAT(K53,"_",AD53),_xlfn.CONCAT(K53,"_",AD53,".odm",AE53)),"NA") -> 0 | I53: attributes | J53: Measure report table Shorthand | K53: =IFERROR(VLOOKUP(J53,'wideName-Dropdowns'!$A:$B,2,FALSE),"") -> 0 | M53: =IFERROR(VLOOKUP(L53,'wideName-Dropdowns'!$C:$D,2,FALSE),"") -> 0 | O53: =IFERROR(VLOOKUP(N53,'wideName-Dropdowns'!$E:$F,2,FALSE),"") -> 0 | Q53: =IFERROR(VLOOKUP(P53,'wideName-Dropdowns'!$G:$H,2,FALSE),"") -> 0 | S53: =IFERROR(VLOOKUP(R53,'wideName-Dropdowns'!$I:$J,2,FALSE),"") -> 0 | U53: =IFERROR(VLOOKUP(T53,'wideName-Dropdowns'!$K:$L,2,FALSE),"") -> 0 | W53: =IFERROR(VLOOKUP(V53,'wideName-Dropdowns'!$M:$N,2,FALSE),"") -> 0 | Y53: =IFERROR(VLOOKUP(X53,'wideName-Dropdowns'!$O:$P,2,FALSE),"") -> 0 | AA53: =IFERROR(VLOOKUP(Z53,'wideName-Dropdowns'!$Q:$R,2,FALSE),"") -> 0 | AC53: Group | AD53: =IFERROR(VLOOKUP(AC53,'wideName-Dropdowns'!$S:$T,2,FALSE),"") -> 0
A54: =IF(I54="attributes",H54,IF(I54="measurements",F54,G54)) -> 0 | B54: Target | C54: =LEN(A54) -> 0 | D54: The genetic target or measure of an analysis in a wide or combined long-and-wide table. | E54: HPAIV H5N1 Template | F54: =IF(I54="measurements",IF(AE54="",_xlfn.CONCAT(O54,"_",Q54,"_",S54,"_",U54,"_",Y54,"_",AA54,"_",AB54,"_",AD54),_xlfn.CONCAT(O54,"_",Q54,"_",S54,"_",U54,"_",Y54,"_",AA54,"_",AB54,"_",AD54,".odm",AE54)),"NA") -> 0 | G54: =IF(I54="methods",IF(L54="measurement",IF(AE54="",_xlfn.CONCAT(K54,"_",M54,"_",O54,"_",Q54,"_",S54,"_",U54,"_",Y54,"_",AA54,"_",AB54,"_",AD54),_xlfn.CONCAT(K54,"_",M54,"_",O54,"_",Q54,"_",S54,"_",U54,"_",Y54,"_",AA54,"_",AB54,"_",AD54,".odm",AE54)),IF(AE54="",_xlfn.CONCAT(K54,"_",M54,"_",W54,"_",AD54),_xlfn.CONCAT(K54,"_",M54,"_",W54,"_",AD54,".odm",AE54))),"NA") -> 0 | H54: =IF(I54="attributes",IF(AE54="",_xlfn.CONCAT(K54,"_",AD54),_xlfn.CONCAT(K54,"_",AD54,".odm",AE54)),"NA") -> 0 | I54: attributes | J54: Measure report table Shorthand | K54: =IFERROR(VLOOKUP(J54,'wideName-Dropdowns'!$A:$B,2,FALSE),"") -> 0 | M54: =IFERROR(VLOOKUP(L54,'wideName-Dropdowns'!$C:$D,2,FALSE),"") -> 0 | O54: =IFERROR(VLOOKUP(N54,'wideName-Dropdowns'!$E:$F,2,FALSE),"") -> 0 | Q54: =IFERROR(VLOOKUP(P54,'wideName-Dropdowns'!$G:$H,2,FALSE),"") -> 0 | S54: =IFERROR(VLOOKUP(R54,'wideName-Dropdowns'!$I:$J,2,FALSE),"") -> 0 | U54: =IFERROR(VLOOKUP(T54,'wideName-Dropdowns'!$K:$L,2,FALSE),"") -> 0 | W54: =IFERROR(VLOOKUP(V54,'wideName-Dropdowns'!$M:$N,2,FALSE),"") -> 0 | Y54: =IFERROR(VLOOKUP(X54,'wideName-Dropdowns'!$O:$P,2,FALSE),"") -> 0 | AA54: =IFERROR(VLOOKUP(Z54,'wideName-Dropdowns'!$Q:$R,2,FALSE),"") -> 0 | AC54: Measure | AD54: =IFERROR(VLOOKUP(AC54,'wideName-Dropdowns'!$S:$T,2,FALSE),"") -> 0
A55: =IF(I55="attributes",H55,IF(I55="measurements",F55,G55)) -> 0 | B55: Value | C55: =LEN(A55) -> 0 | D55: Measure value in a wide or combined long-and-wide table where most details are recorded in other columns. | E55: HPAIV H5N1 Template | F55: =IF(I55="measurements",IF(AE55="",_xlfn.CONCAT(O55,"_",Q55,"_",S55,"_",U55,"_",Y55,"_",AA55,"_",AB55,"_",AD55),_xlfn.CONCAT(O55,"_",Q55,"_",S55,"_",U55,"_",Y55,"_",AA55,"_",AB55,"_",AD55,".odm",AE55)),"NA") -> 0 | G55: =IF(I55="methods",IF(L55="measurement",IF(AE55="",_xlfn.CONCAT(K55,"_",M55,"_",O55,"_",Q55,"_",S55,"_",U55,"_",Y55,"_",AA55,"_",AB55,"_",AD55),_xlfn.CONCAT(K55,"_",M55,"_",O55,"_",Q55,"_",S55,"_",U55,"_",Y55,"_",AA55,"_",AB55,"_",AD55,".odm",AE55)),IF(AE55="",_xlfn.CONCAT(K55,"_",M55,"_",W55,"_",AD55),_xlfn.CONCAT(K55,"_",M55,"_",W55,"_",AD55,".odm",AE55))),"NA") -> 0 | H55: =IF(I55="attributes",IF(AE55="",_xlfn.CONCAT(K55,"_",AD55),_xlfn.CONCAT(K55,"_",AD55,".odm",AE55)),"NA") -> 0 | I55: measurements | K55: =IFERROR(VLOOKUP(J55,'wideName-Dropdowns'!$A:$B,2,FALSE),"") -> 0 | M55: =IFERROR(VLOOKUP(L55,'wideName-Dropdowns'!$C:$D,2,FALSE),"") -> 0 | N55: Water compartment | O55: =IFERROR(VLOOKUP(N55,'wideName-Dropdowns'!$E:$F,2,FALSE),"") -> 0 | P55: Sample | Q55: =IFERROR(VLOOKUP(P55,'wideName-Dropdowns'!$G:$H,2,FALSE),"") -> 0 | R55: See Header for Fraction Analyzed | S55: =IFERROR(VLOOKUP(R55,'wideName-Dropdowns'!$I:$J,2,FALSE),"") -> 0 | T55: See Header for Measure | U55: =IFERROR(VLOOKUP(T55,'wideName-Dropdowns'!$K:$L,2,FALSE),"") -> 0 | W55: =IFERROR(VLOOKUP(V55,'wideName-Dropdowns'!$M:$N,2,FALSE),"") -> 0 | X55: See Header for Unit | Y55: =IFERROR(VLOOKUP(X55,'wideName-Dropdowns'!$O:$P,2,FALSE),"") -> 0 | Z55: See Header for Aggregation | AA55: =IFERROR(VLOOKUP(Z55,'wideName-Dropdowns'!$Q:$R,2,FALSE),"") -> 0 | AB55: NR | AC55: Value | AD55: =IFERROR(VLOOKUP(AC55,'wideName-Dropdowns'!$S:$T,2,FALSE),"") -> 0
A56: =IF(I56="attributes",H56,IF(I56="measurements",F56,G56)) -> 0 | B56: Unit | C56: =LEN(A56) -> 0 | D56: The unit of a measure in a wide or combined long-and-wide table. | E56: HPAIV H5N1 Template | F56: =IF(I56="measurements",IF(AE56="",_xlfn.CONCAT(O56,"_",Q56,"_",S56,"_",U56,"_",Y56,"_",AA56,"_",AB56,"_",AD56),_xlfn.CONCAT(O56,"_",Q56,"_",S56,"_",U56,"_",Y56,"_",AA56,"_",AB56,"_",AD56,".odm",AE56)),"NA") -> 0 | G56: =IF(I56="methods",IF(L56="measurement",IF(AE56="",_xlfn.CONCAT(K56,"_",M56,"_",O56,"_",Q56,"_",S56,"_",U56,"_",Y56,"_",AA56,"_",AB56,"_",AD56),_xlfn.CONCAT(K56,"_",M56,"_",O56,"_",Q56,"_",S56,"_",U56,"_",Y56,"_",AA56,"_",AB56,"_",AD56,".odm",AE56)),IF(AE56="",_xlfn.CONCAT(K56,"_",M56,"_",W56,"_",AD56),_xlfn.CONCAT(K56,"_",M56,"_",W56,"_",AD56,".odm",AE56))),"NA") -> 0 | H56: =IF(I56="attributes",IF(AE56="",_xlfn.CONCAT(K56,"_",AD56),_xlfn.CONCAT(K56,"_",AD56,".odm",AE56)),"NA") -> 0 | I56: attributes | J56: Measure report table Shorthand | K56: =IFERROR(VLOOKUP(J56,'wideName-Dropdowns'!$A:$B,2,FALSE),"") -> 0 | M56: =IFERROR(VLOOKUP(L56,'wideName-Dropdowns'!$C:$D,2,FALSE),"") -> 0 | O56: =IFERROR(VLOOKUP(N56,'wideName-Dropdowns'!$E:$F,2,FALSE),"") -> 0 | Q56: =IFERROR(VLOOKUP(P56,'wideName-Dropdowns'!$G:$H,2,FALSE),"") -> 0 | S56: =IFERROR(VLOOKUP(R56,'wideName-Dropdowns'!$I:$J,2,FALSE),"") -> 0 | U56: =IFERROR(VLOOKUP(T56,'wideName-Dropdowns'!$K:$L,2,FALSE),"") -> 0 | W56: =IFERROR(VLOOKUP(V56,'wideName-Dropdowns'!$M:$N,2,FALSE),"") -> 0 | Y56: =IFERROR(VLOOKUP(X56,'wideName-Dropdowns'!$O:$P,2,FALSE),"") -> 0 | AA56: =IFERROR(VLOOKUP(Z56,'wideName-Dropdowns'!$Q:$R,2,FALSE),"") -> 0 | AC56: Unit | AD56: =IFERROR(VLOOKUP(AC56,'wideName-Dropdowns'!$S:$T,2,FALSE),"") -> 0
A57: =IF(I57="attributes",H57,IF(I57="measurements",F57,G57)) -> 0 | B57: Aggregation | C57: =LEN(A57) -> 0 | D57: The aggregation of a measure in a wide or combined long-and-wide table. | E57: HPAIV H5N1 Template | F57: =IF(I57="measurements",IF(AE57="",_xlfn.CONCAT(O57,"_",Q57,"_",S57,"_",U57,"_",Y57,"_",AA57,"_",AB57,"_",AD57),_xlfn.CONCAT(O57,"_",Q57,"_",S57,"_",U57,"_",Y57,"_",AA57,"_",AB57,"_",AD57,".odm",AE57)),"NA") -> 0 | G57: =IF(I57="methods",IF(L57="measurement",IF(AE57="",_xlfn.CONCAT(K57,"_",M57,"_",O57,"_",Q57,"_",S57,"_",U57,"_",Y57,"_",AA57,"_",AB57,"_",AD57),_xlfn.CONCAT(K57,"_",M57,"_",O57,"_",Q57,"_",S57,"_",U57,"_",Y57,"_",AA57,"_",AB57,"_",AD57,".odm",AE57)),IF(AE57="",_xlfn.CONCAT(K57,"_",M57,"_",W57,"_",AD57),_xlfn.CONCAT(K57,"_",M57,"_",W57,"_",AD57,".odm",AE57))),"NA") -> 0 | H57: =IF(I57="attributes",IF(AE57="",_xlfn.CONCAT(K57,"_",AD57),_xlfn.CONCAT(K57,"_",AD57,".odm",AE57)),"NA") -> 0 | I57: attributes | J57: Measure report table Shorthand | K57: =IFERROR(VLOOKUP(J57,'wideName-Dropdowns'!$A:$B,2,FALSE),"") -> 0 | M57: =IFERROR(VLOOKUP(L57,'wideName-Dropdowns'!$C:$D,2,FALSE),"") -> 0 | O57: =IFERROR(VLOOKUP(N57,'wideName-Dropdowns'!$E:$F,2,FALSE),"") -> 0 | Q57: =IFERROR(VLOOKUP(P57,'wideName-Dropdowns'!$G:$H,2,FALSE),"") -> 0 | S57: =IFERROR(VLOOKUP(R57,'wideName-Dropdowns'!$I:$J,2,FALSE),"") -> 0 | U57: =IFERROR(VLOOKUP(T57,'wideName-Dropdowns'!$K:$L,2,FALSE),"") -> 0 | W57: =IFERROR(VLOOKUP(V57,'wideName-Dropdowns'!$M:$N,2,FALSE),"") -> 0 | Y57: =IFERROR(VLOOKUP(X57,'wideName-Dropdowns'!$O:$P,2,FALSE),"") -> 0 | AA57: =IFERROR(VLOOKUP(Z57,'wideName-Dropdowns'!$Q:$R,2,FALSE),"") -> 0 | AC57: Aggregation | AD57: =IFERROR(VLOOKUP(AC57,'wideName-Dropdowns'!$S:$T,2,FALSE),"") -> 0
A58: =IF(I58="attributes",H58,IF(I58="measurements",F58,G58)) -> 0 | B58: Chemical Oxygen Demand (mg/l) | C58: =LEN(A58) -> 0 | D58: Chemical oxygen demand in a wide or combined long-and-wide table. | E58: HPAIV H5N1 Template | F58: =IF(I58="measurements",IF(AE58="",_xlfn.CONCAT(O58,"_",Q58,"_",S58,"_",U58,"_",Y58,"_",AA58,"_",AB58,"_",AD58),_xlfn.CONCAT(O58,"_",Q58,"_",S58,"_",U58,"_",Y58,"_",AA58,"_",AB58,"_",AD58,".odm",AE58)),"NA") -> 0 | G58: =IF(I58="methods",IF(L58="measurement",IF(AE58="",_xlfn.CONCAT(K58,"_",M58,"_",O58,"_",Q58,"_",S58,"_",U58,"_",Y58,"_",AA58,"_",AB58,"_",AD58),_xlfn.CONCAT(K58,"_",M58,"_",O58,"_",Q58,"_",S58,"_",U58,"_",Y58,"_",AA58,"_",AB58,"_",AD58,".odm",AE58)),IF(AE58="",_xlfn.CONCAT(K58,"_",M58,"_",W58,"_",AD58),_xlfn.CONCAT(K58,"_",M58,"_",W58,"_",AD58,".odm",AE58))),"NA") -> 0 | H58: =IF(I58="attributes",IF(AE58="",_xlfn.CONCAT(K58,"_",AD58),_xlfn.CONCAT(K58,"_",AD58,".odm",AE58)),"NA") -> 0 | I58: measurements | K58: =IFERROR(VLOOKUP(J58,'wideName-Dropdowns'!$A:$B,2,FALSE),"") -> 0 | M58: =IFERROR(VLOOKUP(L58,'wideName-Dropdowns'!$C:$D,2,FALSE),"") -> 0 | N58: Water compartment | O58: =IFERROR(VLOOKUP(N58,'wideName-Dropdowns'!$E:$F,2,FALSE),"") -> 0 | P58: Site | Q58: =IFERROR(VLOOKUP(P58,'wideName-Dropdowns'!$G:$H,2,FALSE),"") -> 0 | R58: Not reported | S58: =IFERROR(VLOOKUP(R58,'wideName-Dropdowns'!$I:$J,2,FALSE),"") -> 0 | T58: Chemical Oxygen Demand | U58: =IFERROR(VLOOKUP(T58,'wideName-Dropdowns'!$K:$L,2,FALSE),"") -> 0 | W58: =IFERROR(VLOOKUP(V58,'wideName-Dropdowns'!$M:$N,2,FALSE),"") -> 0 | X58: Milligrams per litre | Y58: =IFERROR(VLOOKUP(X58,'wideName-Dropdowns'!$O:$P,2,FALSE),"") -> 0 | Z58: Arithmetic mean | AA58: =IFERROR(VLOOKUP(Z58,'wideName-Dropdowns'!$Q:$R,2,FALSE),"") -> 0 | AB58: NR | AC58: Value | AD58: =IFERROR(VLOOKUP(AC58,'wideName-Dropdowns'!$S:$T,2,FALSE),"") -> 0
A59: =IF(I59="attributes",H59,IF(I59="measurements",F59,G59)) -> 0 | B59: Biochemical Oxygen Demand (mg/l) | C59: =LEN(A59) -> 0 | D59: Biochemical oxygen demand in a wide or combined long-and-wide table. | E59: HPAIV H5N1 Template | F59: =IF(I59="measurements",IF(AE59="",_xlfn.CONCAT(O59,"_",Q59,"_",S59,"_",U59,"_",Y59,"_",AA59,"_",AB59,"_",AD59),_xlfn.CONCAT(O59,"_",Q59,"_",S59,"_",U59,"_",Y59,"_",AA59,"_",AB59,"_",AD59,".odm",AE59)),"NA") -> 0 | G59: =IF(I59="methods",IF(L59="measurement",IF(AE59="",_xlfn.CONCAT(K59,"_",M59,"_",O59,"_",Q59,"_",S59,"_",U59,"_",Y59,"_",AA59,"_",AB59,"_",AD59),_xlfn.CONCAT(K59,"_",M59,"_",O59,"_",Q59,"_",S59,"_",U59,"_",Y59,"_",AA59,"_",AB59,"_",AD59,".odm",AE59)),IF(AE59="",_xlfn.CONCAT(K59,"_",M59,"_",W59,"_",AD59),_xlfn.CONCAT(K59,"_",M59,"_",W59,"_",AD59,".odm",AE59))),"NA") -> 0 | H59: =IF(I59="attributes",IF(AE59="",_xlfn.CONCAT(K59,"_",AD59),_xlfn.CONCAT(K59,"_",AD59,".odm",AE59)),"NA") -> 0 | I59: measurements | K59: =IFERROR(VLOOKUP(J59,'wideName-Dropdowns'!$A:$B,2,FALSE),"") -> 0 | M59: =IFERROR(VLOOKUP(L59,'wideName-Dropdowns'!$C:$D,2,FALSE),"") -> 0 | N59: Water compartment | O59: =IFERROR(VLOOKUP(N59,'wideName-Dropdowns'!$E:$F,2,FALSE),"") -> 0 | P59: Site | Q59: =IFERROR(VLOOKUP(P59,'wideName-Dropdowns'!$G:$H,2,FALSE),"") -> 0 | R59: Not reported | S59: =IFERROR(VLOOKUP(R59,'wideName-Dropdowns'!$I:$J,2,FALSE),"") -> 0 | T59: 5-day total biochemical oxygen demand | U59: =IFERROR(VLOOKUP(T59,'wideName-Dropdowns'!$K:$L,2,FALSE),"") -> 0 | W59: =IFERROR(VLOOKUP(V59,'wideName-Dropdowns'!$M:$N,2,FALSE),"") -> 0 | X59: Milligrams per litre | Y59: =IFERROR(VLOOKUP(X59,'wideName-Dropdowns'!$O:$P,2,FALSE),"") -> 0 | Z59: Arithmetic mean | AA59: =IFERROR(VLOOKUP(Z59,'wideName-Dropdowns'!$Q:$R,2,FALSE),"") -> 0 | AB59: NR | AC59: Value | AD59: =IFERROR(VLOOKUP(AC59,'wideName-Dropdowns'!$S:$T,2,FALSE),"") -> 0
A60: =IF(I60="attributes",H60,IF(I60="measurements",F60,G60)) -> 0 | B60: Water conductivity (µS/cm) | C60: =LEN(A60) -> 0 | D60: Wastewater or water conductivity in a wide or combined long-and-wide table. | E60: HPAIV H5N1 Template | F60: =IF(I60="measurements",IF(AE60="",_xlfn.CONCAT(O60,"_",Q60,"_",S60,"_",U60,"_",Y60,"_",AA60,"_",AB60,"_",AD60),_xlfn.CONCAT(O60,"_",Q60,"_",S60,"_",U60,"_",Y60,"_",AA60,"_",AB60,"_",AD60,".odm",AE60)),"NA") -> 0 | G60: =IF(I60="methods",IF(L60="measurement",IF(AE60="",_xlfn.CONCAT(K60,"_",M60,"_",O60,"_",Q60,"_",S60,"_",U60,"_",Y60,"_",AA60,"_",AB60,"_",AD60),_xlfn.CONCAT(K60,"_",M60,"_",O60,"_",Q60,"_",S60,"_",U60,"_",Y60,"_",AA60,"_",AB60,"_",AD60,".odm",AE60)),IF(AE60="",_xlfn.CONCAT(K60,"_",M60,"_",W60,"_",AD60),_xlfn.CONCAT(K60,"_",M60,"_",W60,"_",AD60,".odm",AE60))),"NA") -> 0 | H60: =IF(I60="attributes",IF(AE60="",_xlfn.CONCAT(K60,"_",AD60),_xlfn.CONCAT(K60,"_",AD60,".odm",AE60)),"NA") -> 0 | I60: measurements | K60: =IFERROR(VLOOKUP(J60,'wideName-Dropdowns'!$A:$B,2,FALSE),"") -> 0 | M60: =IFERROR(VLOOKUP(L60,'wideName-Dropdowns'!$C:$D,2,FALSE),"") -> 0 | N60: Water compartment | O60: =IFERROR(VLOOKUP(N60,'wideName-Dropdowns'!$E:$F,2,FALSE),"") -> 0 | P60: Site | Q60: =IFERROR(VLOOKUP(P60,'wideName-Dropdowns'!$G:$H,2,FALSE),"") -> 0 | R60: Not reported | S60: =IFERROR(VLOOKUP(R60,'wideName-Dropdowns'!$I:$J,2,FALSE),"") -> 0 | T60: Water conductivity | U60: =IFERROR(VLOOKUP(T60,'wideName-Dropdowns'!$K:$L,2,FALSE),"") -> 0 | W60: =IFERROR(VLOOKUP(V60,'wideName-Dropdowns'!$M:$N,2,FALSE),"") -> 0 | X60: Micro-Siemens per centimetre | Y60: =IFERROR(VLOOKUP(X60,'wideName-Dropdowns'!$O:$P,2,FALSE),"") -> 0 | Z60: Arithmetic mean | AA60: =IFERROR(VLOOKUP(Z60,'wideName-Dropdowns'!$Q:$R,2,FALSE),"") -> 0 | AB60: NR | AC60: Value | AD60: =IFERROR(VLOOKUP(AC60,'wideName-Dropdowns'!$S:$T,2,FALSE),"") -> 0
A61: =IF(I61="attributes",H61,IF(I61="measurements",F61,G61)) -> 0 | B61: pH | C61: =LEN(A61) -> 0 | D61: pH of a site in a wide or combined long-and-wide table. | E61: HPAIV H5N1 Template | F61: =IF(I61="measurements",IF(AE61="",_xlfn.CONCAT(O61,"_",Q61,"_",S61,"_",U61,"_",Y61,"_",AA61,"_",AB61,"_",AD61),_xlfn.CONCAT(O61,"_",Q61,"_",S61,"_",U61,"_",Y61,"_",AA61,"_",AB61,"_",AD61,".odm",AE61)),"NA") -> 0 | G61: =IF(I61="methods",IF(L61="measurement",IF(AE61="",_xlfn.CONCAT(K61,"_",M61,"_",O61,"_",Q61,"_",S61,"_",U61,"_",Y61,"_",AA61,"_",AB61,"_",AD61),_xlfn.CONCAT(K61,"_",M61,"_",O61,"_",Q61,"_",S61,"_",U61,"_",Y61,"_",AA61,"_",AB61,"_",AD61,".odm",AE61)),IF(AE61="",_xlfn.CONCAT(K61,"_",M61,"_",W61,"_",AD61),_xlfn.CONCAT(K61,"_",M61,"_",W61,"_",AD61,".odm",AE61))),"NA") -> 0 | H61: =IF(I61="attributes",IF(AE61="",_xlfn.CONCAT(K61,"_",AD61),_xlfn.CONCAT(K61,"_",AD61,".odm",AE61)),"NA") -> 0 | I61: measurements | K61: =IFERROR(VLOOKUP(J61,'wideName-Dropdowns'!$A:$B,2,FALSE),"") -> 0 | M61: =IFERROR(VLOOKUP(L61,'wideName-Dropdowns'!$C:$D,2,FALSE),"") -> 0 | N61: Water compartment | O61: =IFERROR(VLOOKUP(N61,'wideName-Dropdowns'!$E:$F,2,FALSE),"") -> 0 | P61: Site | Q61: =IFERROR(VLOOKUP(P61,'wideName-Dropdowns'!$G:$H,2,FALSE),"") -> 0 | R61: Not reported | S61: =IFERROR(VLOOKUP(R61,'wideName-Dropdowns'!$I:$J,2,FALSE),"") -> 0 | T61: pH | U61: =IFERROR(VLOOKUP(T61,'wideName-Dropdowns'!$K:$L,2,FALSE),"") -> 0 | W61: =IFERROR(VLOOKUP(V61,'wideName-Dropdowns'!$M:$N,2,FALSE),"") -> 0 | X61: Unitless measure | Y61: =IFERROR(VLOOKUP(X61,'wideName-Dropdowns'!$O:$P,2,FALSE),"") -> 0 | Z61: Arithmetic mean | AA61: =IFERROR(VLOOKUP(Z61,'wideName-Dropdowns'!$Q:$R,2,FALSE),"") -> 0 | AB61: NR | AC61: Value | AD61: =IFERROR(VLOOKUP(AC61,'wideName-Dropdowns'!$S:$T,2,FALSE),"") -> 0
A62: =IF(I62="attributes",H62,IF(I62="measurements",F62,G62)) -> 0 | B62: Nitrogen concentration (mg/l) | C62: =LEN(A62) -> 0 | D62: Notal nitrogen concentration at a site in a wide or combined long-and-wide table. | E62: HPAIV H5N1 Template | F62: =IF(I62="measurements",IF(AE62="",_xlfn.CONCAT(O62,"_",Q62,"_",S62,"_",U62,"_",Y62,"_",AA62,"_",AB62,"_",AD62),_xlfn.CONCAT(O62,"_",Q62,"_",S62,"_",U62,"_",Y62,"_",AA62,"_",AB62,"_",AD62,".odm",AE62)),"NA") -> 0 | G62: =IF(I62="methods",IF(L62="measurement",IF(AE62="",_xlfn.CONCAT(K62,"_",M62,"_",O62,"_",Q62,"_",S62,"_",U62,"_",Y62,"_",AA62,"_",AB62,"_",AD62),_xlfn.CONCAT(K62,"_",M62,"_",O62,"_",Q62,"_",S62,"_",U62,"_",Y62,"_",AA62,"_",AB62,"_",AD62,".odm",AE62)),IF(AE62="",_xlfn.CONCAT(K62,"_",M62,"_",W62,"_",AD62),_xlfn.CONCAT(K62,"_",M62,"_",W62,"_",AD62,".odm",AE62))),"NA") -> 0 | H62: =IF(I62="attributes",IF(AE62="",_xlfn.CONCAT(K62,"_",AD62),_xlfn.CONCAT(K62,"_",AD62,".odm",AE62)),"NA") -> 0 | I62: measurements | K62: =IFERROR(VLOOKUP(J62,'wideName-Dropdowns'!$A:$B,2,FALSE),"") -> 0 | M62: =IFERROR(VLOOKUP(L62,'wideName-Dropdowns'!$C:$D,2,FALSE),"") -> 0 | N62: Water compartment | O62: =IFERROR(VLOOKUP(N62,'wideName-Dropdowns'!$E:$F,2,FALSE),"") -> 0 | P62: Site | Q62: =IFERROR(VLOOKUP(P62,'wideName-Dropdowns'!$G:$H,2,FALSE),"") -> 0 | R62: Not reported | S62: =IFERROR(VLOOKUP(R62,'wideName-Dropdowns'!$I:$J,2,FALSE),"") -> 0 | T62: Total Nitrogen | U62: =IFERROR(VLOOKUP(T62,'wideName-Dropdowns'!$K:$L,2,FALSE),"") -> 0 | W62: =IFERROR(VLOOKUP(V62,'wideName-Dropdowns'!$M:$N,2,FALSE),"") -> 0 | X62: Milligrams per litre | Y62: =IFERROR(VLOOKUP(X62,'wideName-Dropdowns'!$O:$P,2,FALSE),"") -> 0 | Z62: Arithmetic mean | AA62: =IFERROR(VLOOKUP(Z62,'wideName-Dropdowns'!$Q:$R,2,FALSE),"") -> 0 | AB62: NR | AC62: Value | AD62: =IFERROR(VLOOKUP(AC62,'wideName-Dropdowns'!$S:$T,2,FALSE),"") -> 0
A63: =IF(I63="attributes",H63,IF(I63="measurements",F63,G63)) -> 0 | B63: Limit of Detection (gc) | C63: =LEN(A63) -> 0 | D63: Limit of Detection of a wastewater sample in a wide or combined long-and-wide table. | E63: HPAIV H5N1 Template | F63: =IF(I63="measurements",IF(AE63="",_xlfn.CONCAT(O63,"_",Q63,"_",S63,"_",U63,"_",Y63,"_",AA63,"_",AB63,"_",AD63),_xlfn.CONCAT(O63,"_",Q63,"_",S63,"_",U63,"_",Y63,"_",AA63,"_",AB63,"_",AD63,".odm",AE63)),"NA") -> 0 | G63: =IF(I63="methods",IF(L63="measurement",IF(AE63="",_xlfn.CONCAT(K63,"_",M63,"_",O63,"_",Q63,"_",S63,"_",U63,"_",Y63,"_",AA63,"_",AB63,"_",AD63),_xlfn.CONCAT(K63,"_",M63,"_",O63,"_",Q63,"_",S63,"_",U63,"_",Y63,"_",AA63,"_",AB63,"_",AD63,".odm",AE63)),IF(AE63="",_xlfn.CONCAT(K63,"_",M63,"_",W63,"_",AD63),_xlfn.CONCAT(K63,"_",M63,"_",W63,"_",AD63,".odm",AE63))),"NA") -> 0 | H63: =IF(I63="attributes",IF(AE63="",_xlfn.CONCAT(K63,"_",AD63),_xlfn.CONCAT(K63,"_",AD63,".odm",AE63)),"NA") -> 0 | I63: measurements | K63: =IFERROR(VLOOKUP(J63,'wideName-Dropdowns'!$A:$B,2,FALSE),"") -> 0 | M63: =IFERROR(VLOOKUP(L63,'wideName-Dropdowns'!$C:$D,2,FALSE),"") -> 0 | N63: Water compartment | O63: =IFERROR(VLOOKUP(N63,'wideName-Dropdowns'!$E:$F,2,FALSE),"") -> 0 | P63: Sample | Q63: =IFERROR(VLOOKUP(P63,'wideName-Dropdowns'!$G:$H,2,FALSE),"") -> 0 | R63: Not reported | S63: =IFERROR(VLOOKUP(R63,'wideName-Dropdowns'!$I:$J,2,FALSE),"") -> 0 | T63: Limit of detection (LOD) - sewage | U63: =IFERROR(VLOOKUP(T63,'wideName-Dropdowns'!$K:$L,2,FALSE),"") -> 0 | W63: =IFERROR(VLOOKUP(V63,'wideName-Dropdowns'!$M:$N,2,FALSE),"") -> 0 | X63: Gene copies | Y63: =IFERROR(VLOOKUP(X63,'wideName-Dropdowns'!$O:$P,2,FALSE),"") -> 0 | Z63: Single | AA63: =IFERROR(VLOOKUP(Z63,'wideName-Dropdowns'!$Q:$R,2,FALSE),"") -> 0 | AB63: NR | AC63: Value | AD63: =IFERROR(VLOOKUP(AC63,'wideName-Dropdowns'!$S:$T,2,FALSE),"") -> 0
A64: =IF(I64="attributes",H64,IF(I64="measurements",F64,G64)) -> 0 | B64: Limit of Quantification (gc) | C64: =LEN(A64) -> 0 | D64: Limit of quantification in a wide or combined long-and-wide table. | E64: HPAIV H5N1 Template | F64: =IF(I64="measurements",IF(AE64="",_xlfn.CONCAT(O64,"_",Q64,"_",S64,"_",U64,"_",Y64,"_",AA64,"_",AB64,"_",AD64),_xlfn.CONCAT(O64,"_",Q64,"_",S64,"_",U64,"_",Y64,"_",AA64,"_",AB64,"_",AD64,".odm",AE64)),"NA") -> 0 | G64: =IF(I64="methods",IF(L64="measurement",IF(AE64="",_xlfn.CONCAT(K64,"_",M64,"_",O64,"_",Q64,"_",S64,"_",U64,"_",Y64,"_",AA64,"_",AB64,"_",AD64),_xlfn.CONCAT(K64,"_",M64,"_",O64,"_",Q64,"_",S64,"_",U64,"_",Y64,"_",AA64,"_",AB64,"_",AD64,".odm",AE64)),IF(AE64="",_xlfn.CONCAT(K64,"_",M64,"_",W64,"_",AD64),_xlfn.CONCAT(K64,"_",M64,"_",W64,"_",AD64,".odm",AE64))),"NA") -> 0 | H64: =IF(I64="attributes",IF(AE64="",_xlfn.CONCAT(K64,"_",AD64),_xlfn.CONCAT(K64,"_",AD64,".odm",AE64)),"NA") -> 0 | I64: measurements | K64: =IFERROR(VLOOKUP(J64,'wideName-Dropdowns'!$A:$B,2,FALSE),"") -> 0 | M64: =IFERROR(VLOOKUP(L64,'wideName-Dropdowns'!$C:$D,2,FALSE),"") -> 0 | N64: Water compartment | O64: =IFERROR(VLOOKUP(N64,'wideName-Dropdowns'!$E:$F,2,FALSE),"") -> 0 | P64: Sample | Q64: =IFERROR(VLOOKUP(P64,'wideName-Dropdowns'!$G:$H,2,FALSE),"") -> 0 | R64: Not reported | S64: =IFERROR(VLOOKUP(R64,'wideName-Dropdowns'!$I:$J,2,FALSE),"") -> 0 | T64: Limit of quantification (LOQ) | U64: =IFERROR(VLOOKUP(T64,'wideName-Dropdowns'!$K:$L,2,FALSE),"") -> 0 | W64: =IFERROR(VLOOKUP(V64,'wideName-Dropdowns'!$M:$N,2,FALSE),"") -> 0 | X64: Gene copies | Y64: =IFERROR(VLOOKUP(X64,'wideName-Dropdowns'!$O:$P,2,FALSE),"") -> 0 | Z64: Single | AA64: =IFERROR(VLOOKUP(Z64,'wideName-Dropdowns'!$Q:$R,2,FALSE),"") -> 0 | AB64: NR | AC64: Value | AD64: =IFERROR(VLOOKUP(AC64,'wideName-Dropdowns'!$S:$T,2,FALSE),"") -> 0
A65: =IF(I65="attributes",H65,IF(I65="measurements",F65,G65)) -> 0 | B65: Report date | C65: =LEN(A65) -> 0 | D65: Date that the measurement was reported to authorities in a wide or combined long-and-wide table. | E65: HPAIV H5N1 Template | F65: =IF(I65="measurements",IF(AE65="",_xlfn.CONCAT(O65,"_",Q65,"_",S65,"_",U65,"_",Y65,"_",AA65,"_",AB65,"_",AD65),_xlfn.CONCAT(O65,"_",Q65,"_",S65,"_",U65,"_",Y65,"_",AA65,"_",AB65,"_",AD65,".odm",AE65)),"NA") -> 0 | G65: =IF(I65="methods",IF(L65="measurement",IF(AE65="",_xlfn.CONCAT(K65,"_",M65,"_",O65,"_",Q65,"_",S65,"_",U65,"_",Y65,"_",AA65,"_",AB65,"_",AD65),_xlfn.CONCAT(K65,"_",M65,"_",O65,"_",Q65,"_",S65,"_",U65,"_",Y65,"_",AA65,"_",AB65,"_",AD65,".odm",AE65)),IF(AE65="",_xlfn.CONCAT(K65,"_",M65,"_",W65,"_",AD65),_xlfn.CONCAT(K65,"_",M65,"_",W65,"_",AD65,".odm",AE65))),"NA") -> 0 | H65: =IF(I65="attributes",IF(AE65="",_xlfn.CONCAT(K65,"_",AD65),_xlfn.CONCAT(K65,"_",AD65,".odm",AE65)),"NA") -> 0 | I65: attributes | J65: Measure report table Shorthand | K65: =IFERROR(VLOOKUP(J65,'wideName-Dropdowns'!$A:$B,2,FALSE),"") -> 0 | M65: =IFERROR(VLOOKUP(L65,'wideName-Dropdowns'!$C:$D,2,FALSE),"") -> 0 | O65: =IFERROR(VLOOKUP(N65,'wideName-Dropdowns'!$E:$F,2,FALSE),"") -> 0 | Q65: =IFERROR(VLOOKUP(P65,'wideName-Dropdowns'!$G:$H,2,FALSE),"") -> 0 | S65: =IFERROR(VLOOKUP(R65,'wideName-Dropdowns'!$I:$J,2,FALSE),"") -> 0 | U65: =IFERROR(VLOOKUP(T65,'wideName-Dropdowns'!$K:$L,2,FALSE),"") -> 0 | W65: =IFERROR(VLOOKUP(V65,'wideName-Dropdowns'!$M:$N,2,FALSE),"") -> 0 | Y65: =IFERROR(VLOOKUP(X65,'wideName-Dropdowns'!$O:$P,2,FALSE),"") -> 0 | AA65: =IFERROR(VLOOKUP(Z65,'wideName-Dropdowns'!$Q:$R,2,FALSE),"") -> 0 | AC65: Report date | AD65: =IFERROR(VLOOKUP(AC65,'wideName-Dropdowns'!$S:$T,2,FALSE),"") -> 0
A66: =IF(I66="attributes",H66,IF(I66="measurements",F66,G66)) -> 0 | B66: Contact person email | C66: =LEN(A66) -> 0 | D66: Contact email address in a wide or combined long-and-wide table. | E66: HPAIV H5N1 Template | F66: =IF(I66="measurements",IF(AE66="",_xlfn.CONCAT(O66,"_",Q66,"_",S66,"_",U66,"_",Y66,"_",AA66,"_",AB66,"_",AD66),_xlfn.CONCAT(O66,"_",Q66,"_",S66,"_",U66,"_",Y66,"_",AA66,"_",AB66,"_",AD66,".odm",AE66)),"NA") -> 0 | G66: =IF(I66="methods",IF(L66="measurement",IF(AE66="",_xlfn.CONCAT(K66,"_",M66,"_",O66,"_",Q66,"_",S66,"_",U66,"_",Y66,"_",AA66,"_",AB66,"_",AD66),_xlfn.CONCAT(K66,"_",M66,"_",O66,"_",Q66,"_",S66,"_",U66,"_",Y66,"_",AA66,"_",AB66,"_",AD66,".odm",AE66)),IF(AE66="",_xlfn.CONCAT(K66,"_",M66,"_",W66,"_",AD66),_xlfn.CONCAT(K66,"_",M66,"_",W66,"_",AD66,".odm",AE66))),"NA") -> 0 | H66: =IF(I66="attributes",IF(AE66="",_xlfn.CONCAT(K66,"_",AD66),_xlfn.CONCAT(K66,"_",AD66,".odm",AE66)),"NA") -> 0 | I66: attributes | J66: Contact table Shorthand | K66: =IFERROR(VLOOKUP(J66,'wideName-Dropdowns'!$A:$B,2,FALSE),"") -> 0 | M66: =IFERROR(VLOOKUP(L66,'wideName-Dropdowns'!$C:$D,2,FALSE),"") -> 0 | O66: =IFERROR(VLOOKUP(N66,'wideName-Dropdowns'!$E:$F,2,FALSE),"") -> 0 | Q66: =IFERROR(VLOOKUP(P66,'wideName-Dropdowns'!$G:$H,2,FALSE),"") -> 0 | S66: =IFERROR(VLOOKUP(R66,'wideName-Dropdowns'!$I:$J,2,FALSE),"") -> 0 | U66: =IFERROR(VLOOKUP(T66,'wideName-Dropdowns'!$K:$L,2,FALSE),"") -> 0 | W66: =IFERROR(VLOOKUP(V66,'wideName-Dropdowns'!$M:$N,2,FALSE),"") -> 0 | Y66: =IFERROR(VLOOKUP(X66,'wideName-Dropdowns'!$O:$P,2,FALSE),"") -> 0 | AA66: =IFERROR(VLOOKUP(Z66,'wideName-Dropdowns'!$Q:$R,2,FALSE),"") -> 0 | AC66: Contact email | AD66: =IFERROR(VLOOKUP(AC66,'wideName-Dropdowns'!$S:$T,2,FALSE),"") -> 0
A67: =IF(I67="attributes",H67,IF(I67="measurements",F67,G67)) -> 0 | B67: Notes | C67: =LEN(A67) -> 0 | D67: Notes on a measure in a wide or combined long-and-wide table. | E67: HPAIV H5N1 Template | F67: =IF(I67="measurements",IF(AE67="",_xlfn.CONCAT(O67,"_",Q67,"_",S67,"_",U67,"_",Y67,"_",AA67,"_",AB67,"_",AD67),_xlfn.CONCAT(O67,"_",Q67,"_",S67,"_",U67,"_",Y67,"_",AA67,"_",AB67,"_",AD67,".odm",AE67)),"NA") -> 0 | G67: =IF(I67="methods",IF(L67="measurement",IF(AE67="",_xlfn.CONCAT(K67,"_",M67,"_",O67,"_",Q67,"_",S67,"_",U67,"_",Y67,"_",AA67,"_",AB67,"_",AD67),_xlfn.CONCAT(K67,"_",M67,"_",O67,"_",Q67,"_",S67,"_",U67,"_",Y67,"_",AA67,"_",AB67,"_",AD67,".odm",AE67)),IF(AE67="",_xlfn.CONCAT(K67,"_",M67,"_",W67,"_",AD67),_xlfn.CONCAT(K67,"_",M67,"_",W67,"_",AD67,".odm",AE67))),"NA") -> 0 | H67: =IF(I67="attributes",IF(AE67="",_xlfn.CONCAT(K67,"_",AD67),_xlfn.CONCAT(K67,"_",AD67,".odm",AE67)),"NA") -> 0 | I67: attributes | J67: Measure report table Shorthand | K67: =IFERROR(VLOOKUP(J67,'wideName-Dropdowns'!$A:$B,2,FALSE),"") -> 0 | M67: =IFERROR(VLOOKUP(L67,'wideName-Dropdowns'!$C:$D,2,FALSE),"") -> 0 | O67: =IFERROR(VLOOKUP(N67,'wideName-Dropdowns'!$E:$F,2,FALSE),"") -> 0 | Q67: =IFERROR(VLOOKUP(P67,'wideName-Dropdowns'!$G:$H,2,FALSE),"") -> 0 | S67: =IFERROR(VLOOKUP(R67,'wideName-Dropdowns'!$I:$J,2,FALSE),"") -> 0 | U67: =IFERROR(VLOOKUP(T67,'wideName-Dropdowns'!$K:$L,2,FALSE),"") -> 0 | W67: =IFERROR(VLOOKUP(V67,'wideName-Dropdowns'!$M:$N,2,FALSE),"") -> 0 | Y67: =IFERROR(VLOOKUP(X67,'wideName-Dropdowns'!$O:$P,2,FALSE),"") -> 0 | AA67: =IFERROR(VLOOKUP(Z67,'wideName-Dropdowns'!$Q:$R,2,FALSE),"") -> 0 | AC67: Notes | AD67: =IFERROR(VLOOKUP(AC67,'wideName-Dropdowns'!$S:$T,2,FALSE),"") -> 0
A68: =IF(I68="attributes",H68,IF(I68="measurements",F68,G68)) -> 0 | B68: address_country | C68: =LEN(A68) -> 0 | D68: Country where a site was. | E68: EU4S Data ODM wide Template | F68: =IF(I68="measurements",IF(AE68="",_xlfn.CONCAT(O68,"_",Q68,"_",S68,"_",U68,"_",Y68,"_",AA68,"_",AB68,"_",AD68),_xlfn.CONCAT(O68,"_",Q68,"_",S68,"_",U68,"_",Y68,"_",AA68,"_",AB68,"_",AD68,".odm",AE68)),"NA") -> 0 | G68: =IF(I68="methods",IF(L68="measurement",IF(AE68="",_xlfn.CONCAT(K68,"_",M68,"_",O68,"_",Q68,"_",S68,"_",U68,"_",Y68,"_",AA68,"_",AB68,"_",AD68),_xlfn.CONCAT(K68,"_",M68,"_",O68,"_",Q68,"_",S68,"_",U68,"_",Y68,"_",AA68,"_",AB68,"_",AD68,".odm",AE68)),IF(AE68="",_xlfn.CONCAT(K68,"_",M68,"_",W68,"_",AD68),_xlfn.CONCAT(K68,"_",M68,"_",W68,"_",AD68,".odm",AE68))),"NA") -> 0 | H68: =IF(I68="attributes",IF(AE68="",_xlfn.CONCAT(K68,"_",AD68),_xlfn.CONCAT(K68,"_",AD68,".odm",AE68)),"NA") -> 0 | I68: attributes | J68: Address table Shorthand | K68: =IFERROR(VLOOKUP(J68,'wideName-Dropdowns'!$A:$B,2,FALSE),"") -> 0 | M68: =IFERROR(VLOOKUP(L68,'wideName-Dropdowns'!$C:$D,2,FALSE),"") -> 0 | O68: =IFERROR(VLOOKUP(N68,'wideName-Dropdowns'!$E:$F,2,FALSE),"") -> 0 | Q68: =IFERROR(VLOOKUP(P68,'wideName-Dropdowns'!$G:$H,2,FALSE),"") -> 0 | S68: =IFERROR(VLOOKUP(R68,'wideName-Dropdowns'!$I:$J,2,FALSE),"") -> 0 | U68: =IFERROR(VLOOKUP(T68,'wideName-Dropdowns'!$K:$L,2,FALSE),"") -> 0 | W68: =IFERROR(VLOOKUP(V68,'wideName-Dropdowns'!$M:$N,2,FALSE),"") -> 0 | Y68: =IFERROR(VLOOKUP(X68,'wideName-Dropdowns'!$O:$P,2,FALSE),"") -> 0 | AA68: =IFERROR(VLOOKUP(Z68,'wideName-Dropdowns'!$Q:$R,2,FALSE),"") -> 0 | AC68: Country | AD68: =IFERROR(VLOOKUP(AC68,'wideName-Dropdowns'!$S:$T,2,FALSE),"") -> 0
A69: =IF(I69="attributes",H69,IF(I69="measurements",F69,G69)) -> 0 | B69: address_zone | C69: =LEN(A69) -> 0 | D69: State, province, or region where a site was. | E69: EU4S Data ODM wide Template | F69: =IF(I69="measurements",IF(AE69="",_xlfn.CONCAT(O69,"_",Q69,"_",S69,"_",U69,"_",Y69,"_",AA69,"_",AB69,"_",AD69),_xlfn.CONCAT(O69,"_",Q69,"_",S69,"_",U69,"_",Y69,"_",AA69,"_",AB69,"_",AD69,".odm",AE69)),"NA") -> 0 | G69: =IF(I69="methods",IF(L69="measurement",IF(AE69="",_xlfn.CONCAT(K69,"_",M69,"_",O69,"_",Q69,"_",S69,"_",U69,"_",Y69,"_",AA69,"_",AB69,"_",AD69),_xlfn.CONCAT(K69,"_",M69,"_",O69,"_",Q69,"_",S69,"_",U69,"_",Y69,"_",AA69,"_",AB69,"_",AD69,".odm",AE69)),IF(AE69="",_xlfn.CONCAT(K69,"_",M69,"_",W69,"_",AD69),_xlfn.CONCAT(K69,"_",M69,"_",W69,"_",AD69,".odm",AE69))),"NA") -> 0 | H69: =IF(I69="attributes",IF(AE69="",_xlfn.CONCAT(K69,"_",AD69),_xlfn.CONCAT(K69,"_",AD69,".odm",AE69)),"NA") -> 0 | I69: attributes | J69: Address table Shorthand | K69: =IFERROR(VLOOKUP(J69,'wideName-Dropdowns'!$A:$B,2,FALSE),"") -> 0 | M69: =IFERROR(VLOOKUP(L69,'wideName-Dropdowns'!$C:$D,2,FALSE),"") -> 0 | O69: =IFERROR(VLOOKUP(N69,'wideName-Dropdowns'!$E:$F,2,FALSE),"") -> 0 | Q69: =IFERROR(VLOOKUP(P69,'wideName-Dropdowns'!$G:$H,2,FALSE),"") -> 0 | S69: =IFERROR(VLOOKUP(R69,'wideName-Dropdowns'!$I:$J,2,FALSE),"") -> 0 | U69: =IFERROR(VLOOKUP(T69,'wideName-Dropdowns'!$K:$L,2,FALSE),"") -> 0 | W69: =IFERROR(VLOOKUP(V69,'wideName-Dropdowns'!$M:$N,2,FALSE),"") -> 0 | Y69: =IFERROR(VLOOKUP(X69,'wideName-Dropdowns'!$O:$P,2,FALSE),"") -> 0 | AA69: =IFERROR(VLOOKUP(Z69,'wideName-Dropdowns'!$Q:$R,2,FALSE),"") -> 0 | AC69: State, Province, or Region | AD69: =IFERROR(VLOOKUP(AC69,'wideName-Dropdowns'!$S:$T,2,FALSE),"") -> 0
A70: =IF(I70="attributes",H70,IF(I70="measurements",F70,G70)) -> 0 | B70: address_city | C70: =LEN(A70) -> 0 | D70: City where a site was. | E70: EU4S Data ODM wide Template | F70: =IF(I70="measurements",IF(AE70="",_xlfn.CONCAT(O70,"_",Q70,"_",S70,"_",U70,"_",Y70,"_",AA70,"_",AB70,"_",AD70),_xlfn.CONCAT(O70,"_",Q70,"_",S70,"_",U70,"_",Y70,"_",AA70,"_",AB70,"_",AD70,".odm",AE70)),"NA") -> 0 | G70: =IF(I70="methods",IF(L70="measurement",IF(AE70="",_xlfn.CONCAT(K70,"_",M70,"_",O70,"_",Q70,"_",S70,"_",U70,"_",Y70,"_",AA70,"_",AB70,"_",AD70),_xlfn.CONCAT(K70,"_",M70,"_",O70,"_",Q70,"_",S70,"_",U70,"_",Y70,"_",AA70,"_",AB70,"_",AD70,".odm",AE70)),IF(AE70="",_xlfn.CONCAT(K70,"_",M70,"_",W70,"_",AD70),_xlfn.CONCAT(K70,"_",M70,"_",W70,"_",AD70,".odm",AE70))),"NA") -> 0 | H70: =IF(I70="attributes",IF(AE70="",_xlfn.CONCAT(K70,"_",AD70),_xlfn.CONCAT(K70,"_",AD70,".odm",AE70)),"NA") -> 0 | I70: attributes | J70: Address table Shorthand | K70: =IFERROR(VLOOKUP(J70,'wideName-Dropdowns'!$A:$B,2,FALSE),"") -> 0 | M70: =IFERROR(VLOOKUP(L70,'wideName-Dropdowns'!$C:$D,2,FALSE),"") -> 0 | O70: =IFERROR(VLOOKUP(N70,'wideName-Dropdowns'!$E:$F,2,FALSE),"") -> 0 | Q70: =IFERROR(VLOOKUP(P70,'wideName-Dropdowns'!$G:$H,2,FALSE),"") -> 0 | S70: =IFERROR(VLOOKUP(R70,'wideName-Dropdowns'!$I:$J,2,FALSE),"") -> 0 | U70: =IFERROR(VLOOKUP(T70,'wideName-Dropdowns'!$K:$L,2,FALSE),"") -> 0 | W70: =IFERROR(VLOOKUP(V70,'wideName-Dropdowns'!$M:$N,2,FALSE),"") -> 0 | Y70: =IFERROR(VLOOKUP(X70,'wideName-Dropdowns'!$O:$P,2,FALSE),"") -> 0 | AA70: =IFERROR(VLOOKUP(Z70,'wideName-Dropdowns'!$Q:$R,2,FALSE),"") -> 0 | AC70: City | AD70: =IFERROR(VLOOKUP(AC70,'wideName-Dropdowns'!$S:$T,2,FALSE),"") -> 0
A71: =IF(I71="attributes",H71,IF(I71="measurements",F71,G71)) -> 0 | B71: sample_id | C71: =LEN(A71) -> 0 | D71: The unique identifier for a sample. | E71: EU4S Data ODM wide Template | F71: =IF(I71="measurements",IF(AE71="",_xlfn.CONCAT(O71,"_",Q71,"_",S71,"_",U71,"_",Y71,"_",AA71,"_",AB71,"_",AD71),_xlfn.CONCAT(O71,"_",Q71,"_",S71,"_",U71,"_",Y71,"_",AA71,"_",AB71,"_",AD71,".odm",AE71)),"NA") -> 0 | G71: =IF(I71="methods",IF(L71="measurement",IF(AE71="",_xlfn.CONCAT(K71,"_",M71,"_",O71,"_",Q71,"_",S71,"_",U71,"_",Y71,"_",AA71,"_",AB71,"_",AD71),_xlfn.CONCAT(K71,"_",M71,"_",O71,"_",Q71,"_",S71,"_",U71,"_",Y71,"_",AA71,"_",AB71,"_",AD71,".odm",AE71)),IF(AE71="",_xlfn.CONCAT(K71,"_",M71,"_",W71,"_",AD71),_xlfn.CONCAT(K71,"_",M71,"_",W71,"_",AD71,".odm",AE71))),"NA") -> 0 | H71: =IF(I71="attributes",IF(AE71="",_xlfn.CONCAT(K71,"_",AD71),_xlfn.CONCAT(K71,"_",AD71,".odm",AE71)),"NA") -> 0 | I71: attributes | J71: Sample report table Shorthand | K71: =IFERROR(VLOOKUP(J71,'wideName-Dropdowns'!$A:$B,2,FALSE),"") -> 0 | M71: =IFERROR(VLOOKUP(L71,'wideName-Dropdowns'!$C:$D,2,FALSE),"") -> 0 | O71: =IFERROR(VLOOKUP(N71,'wideName-Dropdowns'!$E:$F,2,FALSE),"") -> 0 | Q71: =IFERROR(VLOOKUP(P71,'wideName-Dropdowns'!$G:$H,2,FALSE),"") -> 0 | S71: =IFERROR(VLOOKUP(R71,'wideName-Dropdowns'!$I:$J,2,FALSE),"") -> 0 | U71: =IFERROR(VLOOKUP(T71,'wideName-Dropdowns'!$K:$L,2,FALSE),"") -> 0 | W71: =IFERROR(VLOOKUP(V71,'wideName-Dropdowns'!$M:$N,2,FALSE),"") -> 0 | Y71: =IFERROR(VLOOKUP(X71,'wideName-Dropdowns'!$O:$P,2,FALSE),"") -> 0 | AA71: =IFERROR(VLOOKUP(Z71,'wideName-Dropdowns'!$Q:$R,2,FALSE),"") -> 0 | AC71: Sample ID | AD71: =IFERROR(VLOOKUP(AC71,'wideName-Dropdowns'!$S:$T,2,FALSE),"") -> 0
A72: =IF(I72="attributes",H72,IF(I72="measurements",F72,G72)) -> 0 | B72: sample_collDT | C72: =LEN(A72) -> 0 | D72: Collection day and time of a sample. | E72: EU4S Data ODM wide Template | F72: =IF(I72="measurements",IF(AE72="",_xlfn.CONCAT(O72,"_",Q72,"_",S72,"_",U72,"_",Y72,"_",AA72,"_",AB72,"_",AD72),_xlfn.CONCAT(O72,"_",Q72,"_",S72,"_",U72,"_",Y72,"_",AA72,"_",AB72,"_",AD72,".odm",AE72)),"NA") -> 0 | G72: =IF(I72="methods",IF(L72="measurement",IF(AE72="",_xlfn.CONCAT(K72,"_",M72,"_",O72,"_",Q72,"_",S72,"_",U72,"_",Y72,"_",AA72,"_",AB72,"_",AD72),_xlfn.CONCAT(K72,"_",M72,"_",O72,"_",Q72,"_",S72,"_",U72,"_",Y72,"_",AA72,"_",AB72,"_",AD72,".odm",AE72)),IF(AE72="",_xlfn.CONCAT(K72,"_",M72,"_",W72,"_",AD72),_xlfn.CONCAT(K72,"_",M72,"_",W72,"_",AD72,".odm",AE72))),"NA") -> 0 | H72: =IF(I72="attributes",IF(AE72="",_xlfn.CONCAT(K72,"_",AD72),_xlfn.CONCAT(K72,"_",AD72,".odm",AE72)),"NA") -> 0 | I72: attributes | J72: Sample report table Shorthand | K72: =IFERROR(VLOOKUP(J72,'wideName-Dropdowns'!$A:$B,2,FALSE),"") -> 0 | M72: =IFERROR(VLOOKUP(L72,'wideName-Dropdowns'!$C:$D,2,FALSE),"") -> 0 | O72: =IFERROR(VLOOKUP(N72,'wideName-Dropdowns'!$E:$F,2,FALSE),"") -> 0 | Q72: =IFERROR(VLOOKUP(P72,'wideName-Dropdowns'!$G:$H,2,FALSE),"") -> 0 | S72: =IFERROR(VLOOKUP(R72,'wideName-Dropdowns'!$I:$J,2,FALSE),"") -> 0 | U72: =IFERROR(VLOOKUP(T72,'wideName-Dropdowns'!$K:$L,2,FALSE),"") -> 0 | W72: =IFERROR(VLOOKUP(V72,'wideName-Dropdowns'!$M:$N,2,FALSE),"") -> 0 | Y72: =IFERROR(VLOOKUP(X72,'wideName-Dropdowns'!$O:$P,2,FALSE),"") -> 0 | AA72: =IFERROR(VLOOKUP(Z72,'wideName-Dropdowns'!$Q:$R,2,FALSE),"") -> 0 | AC72: Collection date time | AD72: =IFERROR(VLOOKUP(AC72,'wideName-Dropdowns'!$S:$T,2,FALSE),"") -> 0
A73: =IF(I73="attributes",H73,IF(I73="measurements",F73,G73)) -> 0 | B73: sample_collDTend | C73: =LEN(A73) -> 0 | D73: The day and time when sample collection ended. | E73: EU4S Data ODM wide Template | F73: =IF(I73="measurements",IF(AE73="",_xlfn.CONCAT(O73,"_",Q73,"_",S73,"_",U73,"_",Y73,"_",AA73,"_",AB73,"_",AD73),_xlfn.CONCAT(O73,"_",Q73,"_",S73,"_",U73,"_",Y73,"_",AA73,"_",AB73,"_",AD73,".odm",AE73)),"NA") -> 0 | G73: =IF(I73="methods",IF(L73="measurement",IF(AE73="",_xlfn.CONCAT(K73,"_",M73,"_",O73,"_",Q73,"_",S73,"_",U73,"_",Y73,"_",AA73,"_",AB73,"_",AD73),_xlfn.CONCAT(K73,"_",M73,"_",O73,"_",Q73,"_",S73,"_",U73,"_",Y73,"_",AA73,"_",AB73,"_",AD73,".odm",AE73)),IF(AE73="",_xlfn.CONCAT(K73,"_",M73,"_",W73,"_",AD73),_xlfn.CONCAT(K73,"_",M73,"_",W73,"_",AD73,".odm",AE73))),"NA") -> 0 | H73: =IF(I73="attributes",IF(AE73="",_xlfn.CONCAT(K73,"_",AD73),_xlfn.CONCAT(K73,"_",AD73,".odm",AE73)),"NA") -> 0 | I73: attributes | J73: Sample report table Shorthand | K73: =IFERROR(VLOOKUP(J73,'wideName-Dropdowns'!$A:$B,2,FALSE),"") -> 0 | M73: =IFERROR(VLOOKUP(L73,'wideName-Dropdowns'!$C:$D,2,FALSE),"") -> 0 | O73: =IFERROR(VLOOKUP(N73,'wideName-Dropdowns'!$E:$F,2,FALSE),"") -> 0 | Q73: =IFERROR(VLOOKUP(P73,'wideName-Dropdowns'!$G:$H,2,FALSE),"") -> 0 | S73: =IFERROR(VLOOKUP(R73,'wideName-Dropdowns'!$I:$J,2,FALSE),"") -> 0 | U73: =IFERROR(VLOOKUP(T73,'wideName-Dropdowns'!$K:$L,2,FALSE),"") -> 0 | W73: =IFERROR(VLOOKUP(V73,'wideName-Dropdowns'!$M:$N,2,FALSE),"") -> 0 | Y73: =IFERROR(VLOOKUP(X73,'wideName-Dropdowns'!$O:$P,2,FALSE),"") -> 0 | AA73: =IFERROR(VLOOKUP(Z73,'wideName-Dropdowns'!$Q:$R,2,FALSE),"") -> 0 | AC73: Collection date time end | AD73: =IFERROR(VLOOKUP(AC73,'wideName-Dropdowns'!$S:$T,2,FALSE),"") -> 0
A74: =IF(I74="attributes",H74,IF(I74="measurements",F74,G74)) -> 0 | B74: sample_collDTstart | C74: =LEN(A74) -> 0 | D74: The day and time when sample collection started. | E74: EU4S Data ODM wide Template | F74: =IF(I74="measurements",IF(AE74="",_xlfn.CONCAT(O74,"_",Q74,"_",S74,"_",U74,"_",Y74,"_",AA74,"_",AB74,"_",AD74),_xlfn.CONCAT(O74,"_",Q74,"_",S74,"_",U74,"_",Y74,"_",AA74,"_",AB74,"_",AD74,".odm",AE74)),"NA") -> 0 | G74: =IF(I74="methods",IF(L74="measurement",IF(AE74="",_xlfn.CONCAT(K74,"_",M74,"_",O74,"_",Q74,"_",S74,"_",U74,"_",Y74,"_",AA74,"_",AB74,"_",AD74),_xlfn.CONCAT(K74,"_",M74,"_",O74,"_",Q74,"_",S74,"_",U74,"_",Y74,"_",AA74,"_",AB74,"_",AD74,".odm",AE74)),IF(AE74="",_xlfn.CONCAT(K74,"_",M74,"_",W74,"_",AD74),_xlfn.CONCAT(K74,"_",M74,"_",W74,"_",AD74,".odm",AE74))),"NA") -> 0 | H74: =IF(I74="attributes",IF(AE74="",_xlfn.CONCAT(K74,"_",AD74),_xlfn.CONCAT(K74,"_",AD74,".odm",AE74)),"NA") -> 0 | I74: attributes | J74: Sample report table Shorthand | K74: =IFERROR(VLOOKUP(J74,'wideName-Dropdowns'!$A:$B,2,FALSE),"") -> 0 | M74: =IFERROR(VLOOKUP(L74,'wideName-Dropdowns'!$C:$D,2,FALSE),"") -> 0 | O74: =IFERROR(VLOOKUP(N74,'wideName-Dropdowns'!$E:$F,2,FALSE),"") -> 0 | Q74: =IFERROR(VLOOKUP(P74,'wideName-Dropdowns'!$G:$H,2,FALSE),"") -> 0 | S74: =IFERROR(VLOOKUP(R74,'wideName-Dropdowns'!$I:$J,2,FALSE),"") -> 0 | U74: =IFERROR(VLOOKUP(T74,'wideName-Dropdowns'!$K:$L,2,FALSE),"") -> 0 | W74: =IFERROR(VLOOKUP(V74,'wideName-Dropdowns'!$M:$N,2,FALSE),"") -> 0 | Y74: =IFERROR(VLOOKUP(X74,'wideName-Dropdowns'!$O:$P,2,FALSE),"") -> 0 | AA74: =IFERROR(VLOOKUP(Z74,'wideName-Dropdowns'!$Q:$R,2,FALSE),"") -> 0 | AC74: Collection date time start | AD74: =IFERROR(VLOOKUP(AC74,'wideName-Dropdowns'!$S:$T,2,FALSE),"") -> 0
A75: =IF(I75="attributes",H75,IF(I75="measurements",F75,G75)) -> 0 | B75: sample_collPer | C75: =LEN(A75) -> 0 | D75: The period of time in hours in which a composite sample was collected. | E75: EU4S Data ODM wide Template | F75: =IF(I75="measurements",IF(AE75="",_xlfn.CONCAT(O75,"_",Q75,"_",S75,"_",U75,"_",Y75,"_",AA75,"_",AB75,"_",AD75),_xlfn.CONCAT(O75,"_",Q75,"_",S75,"_",U75,"_",Y75,"_",AA75,"_",AB75,"_",AD75,".odm",AE75)),"NA") -> 0 | G75: =IF(I75="methods",IF(L75="measurement",IF(AE75="",_xlfn.CONCAT(K75,"_",M75,"_",O75,"_",Q75,"_",S75,"_",U75,"_",Y75,"_",AA75,"_",AB75,"_",AD75),_xlfn.CONCAT(K75,"_",M75,"_",O75,"_",Q75,"_",S75,"_",U75,"_",Y75,"_",AA75,"_",AB75,"_",AD75,".odm",AE75)),IF(AE75="",_xlfn.CONCAT(K75,"_",M75,"_",W75,"_",AD75),_xlfn.CONCAT(K75,"_",M75,"_",W75,"_",AD75,".odm",AE75))),"NA") -> 0 | H75: =IF(I75="attributes",IF(AE75="",_xlfn.CONCAT(K75,"_",AD75),_xlfn.CONCAT(K75,"_",AD75,".odm",AE75)),"NA") -> 0 | I75: attributes | J75: Sample report table Shorthand | K75: =IFERROR(VLOOKUP(J75,'wideName-Dropdowns'!$A:$B,2,FALSE),"") -> 0 | M75: =IFERROR(VLOOKUP(L75,'wideName-Dropdowns'!$C:$D,2,FALSE),"") -> 0 | O75: =IFERROR(VLOOKUP(N75,'wideName-Dropdowns'!$E:$F,2,FALSE),"") -> 0 | Q75: =IFERROR(VLOOKUP(P75,'wideName-Dropdowns'!$G:$H,2,FALSE),"") -> 0 | S75: =IFERROR(VLOOKUP(R75,'wideName-Dropdowns'!$I:$J,2,FALSE),"") -> 0 | U75: =IFERROR(VLOOKUP(T75,'wideName-Dropdowns'!$K:$L,2,FALSE),"") -> 0 | W75: =IFERROR(VLOOKUP(V75,'wideName-Dropdowns'!$M:$N,2,FALSE),"") -> 0 | Y75: =IFERROR(VLOOKUP(X75,'wideName-Dropdowns'!$O:$P,2,FALSE),"") -> 0 | AA75: =IFERROR(VLOOKUP(Z75,'wideName-Dropdowns'!$Q:$R,2,FALSE),"") -> 0 | AC75: Collection period | AD75: =IFERROR(VLOOKUP(AC75,'wideName-Dropdowns'!$S:$T,2,FALSE),"") -> 0
A76: =IF(I76="attributes",H76,IF(I76="measurements",F76,G76)) -> 0 | B76: sample_collType | C76: =LEN(A76) -> 0 | D76: The type of collection done for a sample. | E76: EU4S Data ODM wide Template | F76: =IF(I76="measurements",IF(AE76="",_xlfn.CONCAT(O76,"_",Q76,"_",S76,"_",U76,"_",Y76,"_",AA76,"_",AB76,"_",AD76),_xlfn.CONCAT(O76,"_",Q76,"_",S76,"_",U76,"_",Y76,"_",AA76,"_",AB76,"_",AD76,".odm",AE76)),"NA") -> 0 | G76: =IF(I76="methods",IF(L76="measurement",IF(AE76="",_xlfn.CONCAT(K76,"_",M76,"_",O76,"_",Q76,"_",S76,"_",U76,"_",Y76,"_",AA76,"_",AB76,"_",AD76),_xlfn.CONCAT(K76,"_",M76,"_",O76,"_",Q76,"_",S76,"_",U76,"_",Y76,"_",AA76,"_",AB76,"_",AD76,".odm",AE76)),IF(AE76="",_xlfn.CONCAT(K76,"_",M76,"_",W76,"_",AD76),_xlfn.CONCAT(K76,"_",M76,"_",W76,"_",AD76,".odm",AE76))),"NA") -> 0 | H76: =IF(I76="attributes",IF(AE76="",_xlfn.CONCAT(K76,"_",AD76),_xlfn.CONCAT(K76,"_",AD76,".odm",AE76)),"NA") -> 0 | I76: attributes | J76: Sample report table Shorthand | K76: =IFERROR(VLOOKUP(J76,'wideName-Dropdowns'!$A:$B,2,FALSE),"") -> 0 | M76: =IFERROR(VLOOKUP(L76,'wideName-Dropdowns'!$C:$D,2,FALSE),"") -> 0 | O76: =IFERROR(VLOOKUP(N76,'wideName-Dropdowns'!$E:$F,2,FALSE),"") -> 0 | Q76: =IFERROR(VLOOKUP(P76,'wideName-Dropdowns'!$G:$H,2,FALSE),"") -> 0 | S76: =IFERROR(VLOOKUP(R76,'wideName-Dropdowns'!$I:$J,2,FALSE),"") -> 0 | U76: =IFERROR(VLOOKUP(T76,'wideName-Dropdowns'!$K:$L,2,FALSE),"") -> 0 | W76: =IFERROR(VLOOKUP(V76,'wideName-Dropdowns'!$M:$N,2,FALSE),"") -> 0 | Y76: =IFERROR(VLOOKUP(X76,'wideName-Dropdowns'!$O:$P,2,FALSE),"") -> 0 | AA76: =IFERROR(VLOOKUP(Z76,'wideName-Dropdowns'!$Q:$R,2,FALSE),"") -> 0 | AC76: Sample collection type | AD76: =IFERROR(VLOOKUP(AC76,'wideName-Dropdowns'!$S:$T,2,FALSE),"") -> 0
A77: mr_valTreat__estimate_ | B77: measure_estimated | C77: =LEN(A77) -> 0 | D77: A true or false indicator of whether a measure is an estimate or not. | E77: EU4S Data ODM wide Template | F77: =IF(I77="measurements",IF(AE77="",_xlfn.CONCAT(O77,"_",Q77,"_",S77,"_",U77,"_",Y77,"_",AA77,"_",AB77,"_",AD77),_xlfn.CONCAT(O77,"_",Q77,"_",S77,"_",U77,"_",Y77,"_",AA77,"_",AB77,"_",AD77,".odm",AE77)),"NA") -> 0 | G77: =IF(I77="methods",IF(L77="measurement",IF(AE77="",_xlfn.CONCAT(K77,"_",M77,"_",O77,"_",Q77,"_",S77,"_",U77,"_",Y77,"_",AA77,"_",AB77,"_",AD77),_xlfn.CONCAT(K77,"_",M77,"_",O77,"_",Q77,"_",S77,"_",U77,"_",Y77,"_",AA77,"_",AB77,"_",AD77,".odm",AE77)),IF(AE77="",_xlfn.CONCAT(K77,"_",M77,"_",W77,"_",AD77),_xlfn.CONCAT(K77,"_",M77,"_",W77,"_",AD77,".odm",AE77))),"NA") -> 0 | H77: =IF(I77="attributes",IF(AE77="",_xlfn.CONCAT(K77,"_",AD77),_xlfn.CONCAT(K77,"_",AD77,".odm",AE77)),"NA") -> 0 | I77: exceptions | J77: Measure report table Shorthand | K77: =IFERROR(VLOOKUP(J77,'wideName-Dropdowns'!$A:$B,2,FALSE),"") -> 0 | M77: =IFERROR(VLOOKUP(L77,'wideName-Dropdowns'!$C:$D,2,FALSE),"") -> 0 | O77: =IFERROR(VLOOKUP(N77,'wideName-Dropdowns'!$E:$F,2,FALSE),"") -> 0 | Q77: =IFERROR(VLOOKUP(P77,'wideName-Dropdowns'!$G:$H,2,FALSE),"") -> 0 | S77: =IFERROR(VLOOKUP(R77,'wideName-Dropdowns'!$I:$J,2,FALSE),"") -> 0 | U77: =IFERROR(VLOOKUP(T77,'wideName-Dropdowns'!$K:$L,2,FALSE),"") -> 0 | W77: =IFERROR(VLOOKUP(V77,'wideName-Dropdowns'!$M:$N,2,FALSE),"") -> 0 | Y77: =IFERROR(VLOOKUP(X77,'wideName-Dropdowns'!$O:$P,2,FALSE),"") -> 0 | AA77: =IFERROR(VLOOKUP(Z77,'wideName-Dropdowns'!$Q:$R,2,FALSE),"") -> 0 | AD77: =IFERROR(VLOOKUP(AC77,'wideName-Dropdowns'!$S:$T,2,FALSE),"") -> 0
A78: =IF(I78="attributes",H78,IF(I78="measurements",F78,G78)) -> 0 | B78: measure_hazard | C78: =LEN(A78) -> 0 | D78: The group (or main pathogen group) of a measure. | E78: EU4S Data ODM wide Template | F78: =IF(I78="measurements",IF(AE78="",_xlfn.CONCAT(O78,"_",Q78,"_",S78,"_",U78,"_",Y78,"_",AA78,"_",AB78,"_",AD78),_xlfn.CONCAT(O78,"_",Q78,"_",S78,"_",U78,"_",Y78,"_",AA78,"_",AB78,"_",AD78,".odm",AE78)),"NA") -> 0 | G78: =IF(I78="methods",IF(L78="measurement",IF(AE78="",_xlfn.CONCAT(K78,"_",M78,"_",O78,"_",Q78,"_",S78,"_",U78,"_",Y78,"_",AA78,"_",AB78,"_",AD78),_xlfn.CONCAT(K78,"_",M78,"_",O78,"_",Q78,"_",S78,"_",U78,"_",Y78,"_",AA78,"_",AB78,"_",AD78,".odm",AE78)),IF(AE78="",_xlfn.CONCAT(K78,"_",M78,"_",W78,"_",AD78),_xlfn.CONCAT(K78,"_",M78,"_",W78,"_",AD78,".odm",AE78))),"NA") -> 0 | H78: =IF(I78="attributes",IF(AE78="",_xlfn.CONCAT(K78,"_",AD78),_xlfn.CONCAT(K78,"_",AD78,".odm",AE78)),"NA") -> 0 | I78: attributes | J78: Measure report table Shorthand | K78: =IFERROR(VLOOKUP(J78,'wideName-Dropdowns'!$A:$B,2,FALSE),"") -> 0 | M78: =IFERROR(VLOOKUP(L78,'wideName-Dropdowns'!$C:$D,2,FALSE),"") -> 0 | O78: =IFERROR(VLOOKUP(N78,'wideName-Dropdowns'!$E:$F,2,FALSE),"") -> 0 | Q78: =IFERROR(VLOOKUP(P78,'wideName-Dropdowns'!$G:$H,2,FALSE),"") -> 0 | S78: =IFERROR(VLOOKUP(R78,'wideName-Dropdowns'!$I:$J,2,FALSE),"") -> 0 | U78: =IFERROR(VLOOKUP(T78,'wideName-Dropdowns'!$K:$L,2,FALSE),"") -> 0 | W78: =IFERROR(VLOOKUP(V78,'wideName-Dropdowns'!$M:$N,2,FALSE),"") -> 0 | Y78: =IFERROR(VLOOKUP(X78,'wideName-Dropdowns'!$O:$P,2,FALSE),"") -> 0 | AA78: =IFERROR(VLOOKUP(Z78,'wideName-Dropdowns'!$Q:$R,2,FALSE),"") -> 0 | AC78: Group | AD78: =IFERROR(VLOOKUP(AC78,'wideName-Dropdowns'!$S:$T,2,FALSE),"") -> 0
A79: =IF(I79="attributes",H79,IF(I79="measurements",F79,G79)) -> 0 | B79: measure_assay | C79: =LEN(A79) -> 0 | D79: The detailed type of measure that's been taken | E79: EU4S Data ODM wide Template | F79: =IF(I79="measurements",IF(AE79="",_xlfn.CONCAT(O79,"_",Q79,"_",S79,"_",U79,"_",Y79,"_",AA79,"_",AB79,"_",AD79),_xlfn.CONCAT(O79,"_",Q79,"_",S79,"_",U79,"_",Y79,"_",AA79,"_",AB79,"_",AD79,".odm",AE79)),"NA") -> 0 | G79: =IF(I79="methods",IF(L79="measurement",IF(AE79="",_xlfn.CONCAT(K79,"_",M79,"_",O79,"_",Q79,"_",S79,"_",U79,"_",Y79,"_",AA79,"_",AB79,"_",AD79),_xlfn.CONCAT(K79,"_",M79,"_",O79,"_",Q79,"_",S79,"_",U79,"_",Y79,"_",AA79,"_",AB79,"_",AD79,".odm",AE79)),IF(AE79="",_xlfn.CONCAT(K79,"_",M79,"_",W79,"_",AD79),_xlfn.CONCAT(K79,"_",M79,"_",W79,"_",AD79,".odm",AE79))),"NA") -> 0 | H79: =IF(I79="attributes",IF(AE79="",_xlfn.CONCAT(K79,"_",AD79),_xlfn.CONCAT(K79,"_",AD79,".odm",AE79)),"NA") -> 0 | I79: attributes | J79: Measure report table Shorthand | K79: =IFERROR(VLOOKUP(J79,'wideName-Dropdowns'!$A:$B,2,FALSE),"") -> 0 | M79: =IFERROR(VLOOKUP(L79,'wideName-Dropdowns'!$C:$D,2,FALSE),"") -> 0 | O79: =IFERROR(VLOOKUP(N79,'wideName-Dropdowns'!$E:$F,2,FALSE),"") -> 0 | Q79: =IFERROR(VLOOKUP(P79,'wideName-Dropdowns'!$G:$H,2,FALSE),"") -> 0 | S79: =IFERROR(VLOOKUP(R79,'wideName-Dropdowns'!$I:$J,2,FALSE),"") -> 0 | U79: =IFERROR(VLOOKUP(T79,'wideName-Dropdowns'!$K:$L,2,FALSE),"") -> 0 | W79: =IFERROR(VLOOKUP(V79,'wideName-Dropdowns'!$M:$N,2,FALSE),"") -> 0 | Y79: =IFERROR(VLOOKUP(X79,'wideName-Dropdowns'!$O:$P,2,FALSE),"") -> 0 | AA79: =IFERROR(VLOOKUP(Z79,'wideName-Dropdowns'!$Q:$R,2,FALSE),"") -> 0 | AC79: Measure | AD79: =IFERROR(VLOOKUP(AC79,'wideName-Dropdowns'!$S:$T,2,FALSE),"") -> 0
A80: =IF(I80="attributes",H80,IF(I80="measurements",F80,G80)) -> 0 | B80: measure_value | C80: =LEN(A80) -> 0 | D80: The value of the measure indicated in "mr_measure", if numeric. | E80: EU4S Data ODM wide Template | F80: =IF(I80="measurements",IF(AE80="",_xlfn.CONCAT(O80,"_",Q80,"_",S80,"_",U80,"_",Y80,"_",AA80,"_",AB80,"_",AD80),_xlfn.CONCAT(O80,"_",Q80,"_",S80,"_",U80,"_",Y80,"_",AA80,"_",AB80,"_",AD80,".odm",AE80)),"NA") -> 0 | G80: =IF(I80="methods",IF(L80="measurement",IF(AE80="",_xlfn.CONCAT(K80,"_",M80,"_",O80,"_",Q80,"_",S80,"_",U80,"_",Y80,"_",AA80,"_",AB80,"_",AD80),_xlfn.CONCAT(K80,"_",M80,"_",O80,"_",Q80,"_",S80,"_",U80,"_",Y80,"_",AA80,"_",AB80,"_",AD80,".odm",AE80)),IF(AE80="",_xlfn.CONCAT(K80,"_",M80,"_",W80,"_",AD80),_xlfn.CONCAT(K80,"_",M80,"_",W80,"_",AD80,".odm",AE80))),"NA") -> 0 | H80: =IF(I80="attributes",IF(AE80="",_xlfn.CONCAT(K80,"_",AD80),_xlfn.CONCAT(K80,"_",AD80,".odm",AE80)),"NA") -> 0 | I80: measurements | K80: =IFERROR(VLOOKUP(J80,'wideName-Dropdowns'!$A:$B,2,FALSE),"") -> 0 | M80: =IFERROR(VLOOKUP(L80,'wideName-Dropdowns'!$C:$D,2,FALSE),"") -> 0 | N80: Water compartment | O80: =IFERROR(VLOOKUP(N80,'wideName-Dropdowns'!$E:$F,2,FALSE),"") -> 0 | P80: Sample | Q80: =IFERROR(VLOOKUP(P80,'wideName-Dropdowns'!$G:$H,2,FALSE),"") -> 0 | R80: Not reported | S80: =IFERROR(VLOOKUP(R80,'wideName-Dropdowns'!$I:$J,2,FALSE),"") -> 0 | T80: See Header for Measure | U80: =IFERROR(VLOOKUP(T80,'wideName-Dropdowns'!$K:$L,2,FALSE),"") -> 0 | W80: =IFERROR(VLOOKUP(V80,'wideName-Dropdowns'!$M:$N,2,FALSE),"") -> 0 | X80: See Header for Unit | Y80: =IFERROR(VLOOKUP(X80,'wideName-Dropdowns'!$O:$P,2,FALSE),"") -> 0 | Z80: See Header for Aggregation | AA80: =IFERROR(VLOOKUP(Z80,'wideName-Dropdowns'!$Q:$R,2,FALSE),"") -> 0 | AB80: NR | AC80: Value | AD80: =IFERROR(VLOOKUP(AC80,'wideName-Dropdowns'!$S:$T,2,FALSE),"") -> 0 | AE80: 1
A81: =IF(I81="attributes",H81,IF(I81="measurements",F81,G81)) -> 0 | B81: measure_value_alpha | C81: =LEN(A81) -> 0 | D81: The value of the measure indicated in "mr_measure", if a string. | E81: EU4S Data ODM wide Template | F81: =IF(I81="measurements",IF(AE81="",_xlfn.CONCAT(O81,"_",Q81,"_",S81,"_",U81,"_",Y81,"_",AA81,"_",AB81,"_",AD81),_xlfn.CONCAT(O81,"_",Q81,"_",S81,"_",U81,"_",Y81,"_",AA81,"_",AB81,"_",AD81,".odm",AE81)),"NA") -> 0 | G81: =IF(I81="methods",IF(L81="measurement",IF(AE81="",_xlfn.CONCAT(K81,"_",M81,"_",O81,"_",Q81,"_",S81,"_",U81,"_",Y81,"_",AA81,"_",AB81,"_",AD81),_xlfn.CONCAT(K81,"_",M81,"_",O81,"_",Q81,"_",S81,"_",U81,"_",Y81,"_",AA81,"_",AB81,"_",AD81,".odm",AE81)),IF(AE81="",_xlfn.CONCAT(K81,"_",M81,"_",W81,"_",AD81),_xlfn.CONCAT(K81,"_",M81,"_",W81,"_",AD81,".odm",AE81))),"NA") -> 0 | H81: =IF(I81="attributes",IF(AE81="",_xlfn.CONCAT(K81,"_",AD81),_xlfn.CONCAT(K81,"_",AD81,".odm",AE81)),"NA") -> 0 | I81: measurements | K81: =IFERROR(VLOOKUP(J81,'wideName-Dropdowns'!$A:$B,2,FALSE),"") -> 0 | M81: =IFERROR(VLOOKUP(L81,'wideName-Dropdowns'!$C:$D,2,FALSE),"") -> 0 | N81: Water compartment | O81: =IFERROR(VLOOKUP(N81,'wideName-Dropdowns'!$E:$F,2,FALSE),"") -> 0 | P81: Sample | Q81: =IFERROR(VLOOKUP(P81,'wideName-Dropdowns'!$G:$H,2,FALSE),"") -> 0 | R81: Not reported | S81: =IFERROR(VLOOKUP(R81,'wideName-Dropdowns'!$I:$J,2,FALSE),"") -> 0 | T81: See Header for Measure | U81: =IFERROR(VLOOKUP(T81,'wideName-Dropdowns'!$K:$L,2,FALSE),"") -> 0 | W81: =IFERROR(VLOOKUP(V81,'wideName-Dropdowns'!$M:$N,2,FALSE),"") -> 0 | X81: See Header for Unit | Y81: =IFERROR(VLOOKUP(X81,'wideName-Dropdowns'!$O:$P,2,FALSE),"") -> 0 | Z81: See Header for Aggregation | AA81: =IFERROR(VLOOKUP(Z81,'wideName-Dropdowns'!$Q:$R,2,FALSE),"") -> 0 | AB81: NR | AC81: Value | AD81: =IFERROR(VLOOKUP(AC81,'wideName-Dropdowns'!$S:$T,2,FALSE),"") -> 0 | AE81: 1
A82: =IF(I82="attributes",H82,IF(I82="measurements",F82,G82)) -> 0 | B82: measure_name | C82: =LEN(A82) -> 0 | D82: The name of the measure. | E82: EU4S Data ODM wide Template | F82: =IF(I82="measurements",IF(AE82="",_xlfn.CONCAT(O82,"_",Q82,"_",S82,"_",U82,"_",Y82,"_",AA82,"_",AB82,"_",AD82),_xlfn.CONCAT(O82,"_",Q82,"_",S82,"_",U82,"_",Y82,"_",AA82,"_",AB82,"_",AD82,".odm",AE82)),"NA") -> 0 | G82: =IF(I82="methods",IF(L82="measurement",IF(AE82="",_xlfn.CONCAT(K82,"_",M82,"_",O82,"_",Q82,"_",S82,"_",U82,"_",Y82,"_",AA82,"_",AB82,"_",AD82),_xlfn.CONCAT(K82,"_",M82,"_",O82,"_",Q82,"_",S82,"_",U82,"_",Y82,"_",AA82,"_",AB82,"_",AD82,".odm",AE82)),IF(AE82="",_xlfn.CONCAT(K82,"_",M82,"_",W82,"_",AD82),_xlfn.CONCAT(K82,"_",M82,"_",W82,"_",AD82,".odm",AE82))),"NA") -> 0 | H82: =IF(I82="attributes",IF(AE82="",_xlfn.CONCAT(K82,"_",AD82),_xlfn.CONCAT(K82,"_",AD82,".odm",AE82)),"NA") -> 0 | I82: attributes | J82: Measure report table Shorthand | K82: =IFERROR(VLOOKUP(J82,'wideName-Dropdowns'!$A:$B,2,FALSE),"") -> 0 | M82: =IFERROR(VLOOKUP(L82,'wideName-Dropdowns'!$C:$D,2,FALSE),"") -> 0 | O82: =IFERROR(VLOOKUP(N82,'wideName-Dropdowns'!$E:$F,2,FALSE),"") -> 0 | Q82: =IFERROR(VLOOKUP(P82,'wideName-Dropdowns'!$G:$H,2,FALSE),"") -> 0 | S82: =IFERROR(VLOOKUP(R82,'wideName-Dropdowns'!$I:$J,2,FALSE),"") -> 0 | U82: =IFERROR(VLOOKUP(T82,'wideName-Dropdowns'!$K:$L,2,FALSE),"") -> 0 | W82: =IFERROR(VLOOKUP(V82,'wideName-Dropdowns'!$M:$N,2,FALSE),"") -> 0 | Y82: =IFERROR(VLOOKUP(X82,'wideName-Dropdowns'!$O:$P,2,FALSE),"") -> 0 | AA82: =IFERROR(VLOOKUP(Z82,'wideName-Dropdowns'!$Q:$R,2,FALSE),"") -> 0 | AC82: Name | AD82: =IFERROR(VLOOKUP(AC82,'wideName-Dropdowns'!$S:$T,2,FALSE),"") -> 0 | AE82: 1
A83: =IF(I83="attributes",H83,IF(I83="measurements",F83,G83)) -> 0 | B83: measure_value_measunit | C83: =LEN(A83) -> 0 | D83: The unit for the measure. | E83: EU4S Data ODM wide Template | F83: =IF(I83="measurements",IF(AE83="",_xlfn.CONCAT(O83,"_",Q83,"_",S83,"_",U83,"_",Y83,"_",AA83,"_",AB83,"_",AD83),_xlfn.CONCAT(O83,"_",Q83,"_",S83,"_",U83,"_",Y83,"_",AA83,"_",AB83,"_",AD83,".odm",AE83)),"NA") -> 0 | G83: =IF(I83="methods",IF(L83="measurement",IF(AE83="",_xlfn.CONCAT(K83,"_",M83,"_",O83,"_",Q83,"_",S83,"_",U83,"_",Y83,"_",AA83,"_",AB83,"_",AD83),_xlfn.CONCAT(K83,"_",M83,"_",O83,"_",Q83,"_",S83,"_",U83,"_",Y83,"_",AA83,"_",AB83,"_",AD83,".odm",AE83)),IF(AE83="",_xlfn.CONCAT(K83,"_",M83,"_",W83,"_",AD83),_xlfn.CONCAT(K83,"_",M83,"_",W83,"_",AD83,".odm",AE83))),"NA") -> 0 | H83: =IF(I83="attributes",IF(AE83="",_xlfn.CONCAT(K83,"_",AD83),_xlfn.CONCAT(K83,"_",AD83,".odm",AE83)),"NA") -> 0 | I83: attributes | J83: Measure report table Shorthand | K83: =IFERROR(VLOOKUP(J83,'wideName-Dropdowns'!$A:$B,2,FALSE),"") -> 0 | M83: =IFERROR(VLOOKUP(L83,'wideName-Dropdowns'!$C:$D,2,FALSE),"") -> 0 | O83: =IFERROR(VLOOKUP(N83,'wideName-Dropdowns'!$E:$F,2,FALSE),"") -> 0 | Q83: =IFERROR(VLOOKUP(P83,'wideName-Dropdowns'!$G:$H,2,FALSE),"") -> 0 | S83: =IFERROR(VLOOKUP(R83,'wideName-Dropdowns'!$I:$J,2,FALSE),"") -> 0 | U83: =IFERROR(VLOOKUP(T83,'wideName-Dropdowns'!$K:$L,2,FALSE),"") -> 0 | W83: =IFERROR(VLOOKUP(V83,'wideName-Dropdowns'!$M:$N,2,FALSE),"") -> 0 | Y83: =IFERROR(VLOOKUP(X83,'wideName-Dropdowns'!$O:$P,2,FALSE),"") -> 0 | AA83: =IFERROR(VLOOKUP(Z83,'wideName-Dropdowns'!$Q:$R,2,FALSE),"") -> 0 | AC83: Unit | AD83: =IFERROR(VLOOKUP(AC83,'wideName-Dropdowns'!$S:$T,2,FALSE),"") -> 0 | AE83: 1
A84: cl_2_AND_standard_calcType__standardization_ | B84: measure_value_normalization_method | C84: =LEN(A84) -> 0 | D84: The standard for use of standardization of the main measure. | E84: EU4S Data ODM wide Template | F84: =IF(I84="measurements",IF(AE84="",_xlfn.CONCAT(O84,"_",Q84,"_",S84,"_",U84,"_",Y84,"_",AA84,"_",AB84,"_",AD84),_xlfn.CONCAT(O84,"_",Q84,"_",S84,"_",U84,"_",Y84,"_",AA84,"_",AB84,"_",AD84,".odm",AE84)),"NA") -> 0 | G84: =IF(I84="methods",IF(L84="measurement",IF(AE84="",_xlfn.CONCAT(K84,"_",M84,"_",O84,"_",Q84,"_",S84,"_",U84,"_",Y84,"_",AA84,"_",AB84,"_",AD84),_xlfn.CONCAT(K84,"_",M84,"_",O84,"_",Q84,"_",S84,"_",U84,"_",Y84,"_",AA84,"_",AB84,"_",AD84,".odm",AE84)),IF(AE84="",_xlfn.CONCAT(K84,"_",M84,"_",W84,"_",AD84),_xlfn.CONCAT(K84,"_",M84,"_",W84,"_",AD84,".odm",AE84))),"NA") -> 0 | H84: =IF(I84="attributes",IF(AE84="",_xlfn.CONCAT(K84,"_",AD84),_xlfn.CONCAT(K84,"_",AD84,".odm",AE84)),"NA") -> 0 | I84: exceptions | K84: =IFERROR(VLOOKUP(J84,'wideName-Dropdowns'!$A:$B,2,FALSE),"") -> 0 | M84: =IFERROR(VLOOKUP(L84,'wideName-Dropdowns'!$C:$D,2,FALSE),"") -> 0 | O84: =IFERROR(VLOOKUP(N84,'wideName-Dropdowns'!$E:$F,2,FALSE),"") -> 0 | Q84: =IFERROR(VLOOKUP(P84,'wideName-Dropdowns'!$G:$H,2,FALSE),"") -> 0 | S84: =IFERROR(VLOOKUP(R84,'wideName-Dropdowns'!$I:$J,2,FALSE),"") -> 0 | U84: =IFERROR(VLOOKUP(T84,'wideName-Dropdowns'!$K:$L,2,FALSE),"") -> 0 | W84: =IFERROR(VLOOKUP(V84,'wideName-Dropdowns'!$M:$N,2,FALSE),"") -> 0 | Y84: =IFERROR(VLOOKUP(X84,'wideName-Dropdowns'!$O:$P,2,FALSE),"") -> 0 | AA84: =IFERROR(VLOOKUP(Z84,'wideName-Dropdowns'!$Q:$R,2,FALSE),"") -> 0 | AD84: =IFERROR(VLOOKUP(AC84,'wideName-Dropdowns'!$S:$T,2,FALSE),"") -> 0
A85: =IF(I85="attributes",H85,IF(I85="measurements",F85,G85)) -> 0 | B85: measure_aggregation | C85: =LEN(A85) -> 0 | D85: The aggregation for the measure. | E85: EU4S Data ODM wide Template | F85: =IF(I85="measurements",IF(AE85="",_xlfn.CONCAT(O85,"_",Q85,"_",S85,"_",U85,"_",Y85,"_",AA85,"_",AB85,"_",AD85),_xlfn.CONCAT(O85,"_",Q85,"_",S85,"_",U85,"_",Y85,"_",AA85,"_",AB85,"_",AD85,".odm",AE85)),"NA") -> 0 | G85: =IF(I85="methods",IF(L85="measurement",IF(AE85="",_xlfn.CONCAT(K85,"_",M85,"_",O85,"_",Q85,"_",S85,"_",U85,"_",Y85,"_",AA85,"_",AB85,"_",AD85),_xlfn.CONCAT(K85,"_",M85,"_",O85,"_",Q85,"_",S85,"_",U85,"_",Y85,"_",AA85,"_",AB85,"_",AD85,".odm",AE85)),IF(AE85="",_xlfn.CONCAT(K85,"_",M85,"_",W85,"_",AD85),_xlfn.CONCAT(K85,"_",M85,"_",W85,"_",AD85,".odm",AE85))),"NA") -> 0 | H85: =IF(I85="attributes",IF(AE85="",_xlfn.CONCAT(K85,"_",AD85),_xlfn.CONCAT(K85,"_",AD85,".odm",AE85)),"NA") -> 0 | I85: attributes | J85: Measure report table Shorthand | K85: =IFERROR(VLOOKUP(J85,'wideName-Dropdowns'!$A:$B,2,FALSE),"") -> 0 | M85: =IFERROR(VLOOKUP(L85,'wideName-Dropdowns'!$C:$D,2,FALSE),"") -> 0 | O85: =IFERROR(VLOOKUP(N85,'wideName-Dropdowns'!$E:$F,2,FALSE),"") -> 0 | Q85: =IFERROR(VLOOKUP(P85,'wideName-Dropdowns'!$G:$H,2,FALSE),"") -> 0 | S85: =IFERROR(VLOOKUP(R85,'wideName-Dropdowns'!$I:$J,2,FALSE),"") -> 0 | U85: =IFERROR(VLOOKUP(T85,'wideName-Dropdowns'!$K:$L,2,FALSE),"") -> 0 | W85: =IFERROR(VLOOKUP(V85,'wideName-Dropdowns'!$M:$N,2,FALSE),"") -> 0 | Y85: =IFERROR(VLOOKUP(X85,'wideName-Dropdowns'!$O:$P,2,FALSE),"") -> 0 | AA85: =IFERROR(VLOOKUP(Z85,'wideName-Dropdowns'!$Q:$R,2,FALSE),"") -> 0 | AC85: Aggregation | AD85: =IFERROR(VLOOKUP(AC85,'wideName-Dropdowns'!$S:$T,2,FALSE),"") -> 0
A86: =IF(I86="attributes",H86,IF(I86="measurements",F86,G86)) -> 0 | B86: measure_notes | C86: =LEN(A86) -> 0 | D86: Any additional notes for a measure. | E86: EU4S Data ODM wide Template | F86: =IF(I86="measurements",IF(AE86="",_xlfn.CONCAT(O86,"_",Q86,"_",S86,"_",U86,"_",Y86,"_",AA86,"_",AB86,"_",AD86),_xlfn.CONCAT(O86,"_",Q86,"_",S86,"_",U86,"_",Y86,"_",AA86,"_",AB86,"_",AD86,".odm",AE86)),"NA") -> 0 | G86: =IF(I86="methods",IF(L86="measurement",IF(AE86="",_xlfn.CONCAT(K86,"_",M86,"_",O86,"_",Q86,"_",S86,"_",U86,"_",Y86,"_",AA86,"_",AB86,"_",AD86),_xlfn.CONCAT(K86,"_",M86,"_",O86,"_",Q86,"_",S86,"_",U86,"_",Y86,"_",AA86,"_",AB86,"_",AD86,".odm",AE86)),IF(AE86="",_xlfn.CONCAT(K86,"_",M86,"_",W86,"_",AD86),_xlfn.CONCAT(K86,"_",M86,"_",W86,"_",AD86,".odm",AE86))),"NA") -> 0 | H86: =IF(I86="attributes",IF(AE86="",_xlfn.CONCAT(K86,"_",AD86),_xlfn.CONCAT(K86,"_",AD86,".odm",AE86)),"NA") -> 0 | I86: attributes | J86: Measure report table Shorthand | K86: =IFERROR(VLOOKUP(J86,'wideName-Dropdowns'!$A:$B,2,FALSE),"") -> 0 | M86: =IFERROR(VLOOKUP(L86,'wideName-Dropdowns'!$C:$D,2,FALSE),"") -> 0 | O86: =IFERROR(VLOOKUP(N86,'wideName-Dropdowns'!$E:$F,2,FALSE),"") -> 0 | Q86: =IFERROR(VLOOKUP(P86,'wideName-Dropdowns'!$G:$H,2,FALSE),"") -> 0 | S86: =IFERROR(VLOOKUP(R86,'wideName-Dropdowns'!$I:$J,2,FALSE),"") -> 0 | U86: =IFERROR(VLOOKUP(T86,'wideName-Dropdowns'!$K:$L,2,FALSE),"") -> 0 | W86: =IFERROR(VLOOKUP(V86,'wideName-Dropdowns'!$M:$N,2,FALSE),"") -> 0 | Y86: =IFERROR(VLOOKUP(X86,'wideName-Dropdowns'!$O:$P,2,FALSE),"") -> 0 | AA86: =IFERROR(VLOOKUP(Z86,'wideName-Dropdowns'!$Q:$R,2,FALSE),"") -> 0 | AC86: Notes | AD86: =IFERROR(VLOOKUP(AC86,'wideName-Dropdowns'!$S:$T,2,FALSE),"") -> 0
A87: =IF(I87="attributes",H87,IF(I87="measurements",F87,G87)) -> 0 | B87: measure_reportDate | C87: =LEN(A87) -> 0 | D87: The date a measure was reported. | E87: EU4S Data ODM wide Template | F87: =IF(I87="measurements",IF(AE87="",_xlfn.CONCAT(O87,"_",Q87,"_",S87,"_",U87,"_",Y87,"_",AA87,"_",AB87,"_",AD87),_xlfn.CONCAT(O87,"_",Q87,"_",S87,"_",U87,"_",Y87,"_",AA87,"_",AB87,"_",AD87,".odm",AE87)),"NA") -> 0 | G87: =IF(I87="methods",IF(L87="measurement",IF(AE87="",_xlfn.CONCAT(K87,"_",M87,"_",O87,"_",Q87,"_",S87,"_",U87,"_",Y87,"_",AA87,"_",AB87,"_",AD87),_xlfn.CONCAT(K87,"_",M87,"_",O87,"_",Q87,"_",S87,"_",U87,"_",Y87,"_",AA87,"_",AB87,"_",AD87,".odm",AE87)),IF(AE87="",_xlfn.CONCAT(K87,"_",M87,"_",W87,"_",AD87),_xlfn.CONCAT(K87,"_",M87,"_",W87,"_",AD87,".odm",AE87))),"NA") -> 0 | H87: =IF(I87="attributes",IF(AE87="",_xlfn.CONCAT(K87,"_",AD87),_xlfn.CONCAT(K87,"_",AD87,".odm",AE87)),"NA") -> 0 | I87: attributes | J87: Measure report table Shorthand | K87: =IFERROR(VLOOKUP(J87,'wideName-Dropdowns'!$A:$B,2,FALSE),"") -> 0 | M87: =IFERROR(VLOOKUP(L87,'wideName-Dropdowns'!$C:$D,2,FALSE),"") -> 0 | O87: =IFERROR(VLOOKUP(N87,'wideName-Dropdowns'!$E:$F,2,FALSE),"") -> 0 | Q87: =IFERROR(VLOOKUP(P87,'wideName-Dropdowns'!$G:$H,2,FALSE),"") -> 0 | S87: =IFERROR(VLOOKUP(R87,'wideName-Dropdowns'!$I:$J,2,FALSE),"") -> 0 | U87: =IFERROR(VLOOKUP(T87,'wideName-Dropdowns'!$K:$L,2,FALSE),"") -> 0 | W87: =IFERROR(VLOOKUP(V87,'wideName-Dropdowns'!$M:$N,2,FALSE),"") -> 0 | Y87: =IFERROR(VLOOKUP(X87,'wideName-Dropdowns'!$O:$P,2,FALSE),"") -> 0 | AA87: =IFERROR(VLOOKUP(Z87,'wideName-Dropdowns'!$Q:$R,2,FALSE),"") -> 0 | AC87: Report date | AD87: =IFERROR(VLOOKUP(AC87,'wideName-Dropdowns'!$S:$T,2,FALSE),"") -> 0
A88: =IF(I88="attributes",H88,IF(I88="measurements",F88,G88)) -> 0 | B88: measure_measureRepID | C88: =LEN(A88) -> 0 | D88: The unique identifier for a measure. | E88: EU4S Data ODM wide Template | F88: =IF(I88="measurements",IF(AE88="",_xlfn.CONCAT(O88,"_",Q88,"_",S88,"_",U88,"_",Y88,"_",AA88,"_",AB88,"_",AD88),_xlfn.CONCAT(O88,"_",Q88,"_",S88,"_",U88,"_",Y88,"_",AA88,"_",AB88,"_",AD88,".odm",AE88)),"NA") -> 0 | G88: =IF(I88="methods",IF(L88="measurement",IF(AE88="",_xlfn.CONCAT(K88,"_",M88,"_",O88,"_",Q88,"_",S88,"_",U88,"_",Y88,"_",AA88,"_",AB88,"_",AD88),_xlfn.CONCAT(K88,"_",M88,"_",O88,"_",Q88,"_",S88,"_",U88,"_",Y88,"_",AA88,"_",AB88,"_",AD88,".odm",AE88)),IF(AE88="",_xlfn.CONCAT(K88,"_",M88,"_",W88,"_",AD88),_xlfn.CONCAT(K88,"_",M88,"_",W88,"_",AD88,".odm",AE88))),"NA") -> 0 | H88: =IF(I88="attributes",IF(AE88="",_xlfn.CONCAT(K88,"_",AD88),_xlfn.CONCAT(K88,"_",AD88,".odm",AE88)),"NA") -> 0 | I88: attributes | J88: Measure report table Shorthand | K88: =IFERROR(VLOOKUP(J88,'wideName-Dropdowns'!$A:$B,2,FALSE),"") -> 0 | M88: =IFERROR(VLOOKUP(L88,'wideName-Dropdowns'!$C:$D,2,FALSE),"") -> 0 | O88: =IFERROR(VLOOKUP(N88,'wideName-Dropdowns'!$E:$F,2,FALSE),"") -> 0 | Q88: =IFERROR(VLOOKUP(P88,'wideName-Dropdowns'!$G:$H,2,FALSE),"") -> 0 | S88: =IFERROR(VLOOKUP(R88,'wideName-Dropdowns'!$I:$J,2,FALSE),"") -> 0 | U88: =IFERROR(VLOOKUP(T88,'wideName-Dropdowns'!$K:$L,2,FALSE),"") -> 0 | W88: =IFERROR(VLOOKUP(V88,'wideName-Dropdowns'!$M:$N,2,FALSE),"") -> 0 | Y88: =IFERROR(VLOOKUP(X88,'wideName-Dropdowns'!$O:$P,2,FALSE),"") -> 0 | AA88: =IFERROR(VLOOKUP(Z88,'wideName-Dropdowns'!$Q:$R,2,FALSE),"") -> 0 | AC88: Measure Report ID | AD88: =IFERROR(VLOOKUP(AC88,'wideName-Dropdowns'!$S:$T,2,FALSE),"") -> 0
A89: =IF(I89="attributes",H89,IF(I89="measurements",F89,G89)) -> 0 | B89: protocol_name | C89: =LEN(A89) -> 0 | D89: The name of the protocol. | E89: EU4S Data ODM wide Template | F89: =IF(I89="measurements",IF(AE89="",_xlfn.CONCAT(O89,"_",Q89,"_",S89,"_",U89,"_",Y89,"_",AA89,"_",AB89,"_",AD89),_xlfn.CONCAT(O89,"_",Q89,"_",S89,"_",U89,"_",Y89,"_",AA89,"_",AB89,"_",AD89,".odm",AE89)),"NA") -> 0 | G89: =IF(I89="methods",IF(L89="measurement",IF(AE89="",_xlfn.CONCAT(K89,"_",M89,"_",O89,"_",Q89,"_",S89,"_",U89,"_",Y89,"_",AA89,"_",AB89,"_",AD89),_xlfn.CONCAT(K89,"_",M89,"_",O89,"_",Q89,"_",S89,"_",U89,"_",Y89,"_",AA89,"_",AB89,"_",AD89,".odm",AE89)),IF(AE89="",_xlfn.CONCAT(K89,"_",M89,"_",W89,"_",AD89),_xlfn.CONCAT(K89,"_",M89,"_",W89,"_",AD89,".odm",AE89))),"NA") -> 0 | H89: =IF(I89="attributes",IF(AE89="",_xlfn.CONCAT(K89,"_",AD89),_xlfn.CONCAT(K89,"_",AD89,".odm",AE89)),"NA") -> 0 | I89: attributes | J89: Protocols table Shorthand | K89: =IFERROR(VLOOKUP(J89,'wideName-Dropdowns'!$A:$B,2,FALSE),"") -> 0 | M89: =IFERROR(VLOOKUP(L89,'wideName-Dropdowns'!$C:$D,2,FALSE),"") -> 0 | O89: =IFERROR(VLOOKUP(N89,'wideName-Dropdowns'!$E:$F,2,FALSE),"") -> 0 | Q89: =IFERROR(VLOOKUP(P89,'wideName-Dropdowns'!$G:$H,2,FALSE),"") -> 0 | S89: =IFERROR(VLOOKUP(R89,'wideName-Dropdowns'!$I:$J,2,FALSE),"") -> 0 | U89: =IFERROR(VLOOKUP(T89,'wideName-Dropdowns'!$K:$L,2,FALSE),"") -> 0 | W89: =IFERROR(VLOOKUP(V89,'wideName-Dropdowns'!$M:$N,2,FALSE),"") -> 0 | Y89: =IFERROR(VLOOKUP(X89,'wideName-Dropdowns'!$O:$P,2,FALSE),"") -> 0 | AA89: =IFERROR(VLOOKUP(Z89,'wideName-Dropdowns'!$Q:$R,2,FALSE),"") -> 0 | AC89: Name | AD89: =IFERROR(VLOOKUP(AC89,'wideName-Dropdowns'!$S:$T,2,FALSE),"") -> 0
A90: =IF(I90="attributes",H90,IF(I90="measurements",F90,G90)) -> 0 | B90: protocol_protocol_ID | C90: =LEN(A90) -> 0 | D90: The unique identifier for a protocol. | E90: EU4S Data ODM wide Template | F90: =IF(I90="measurements",IF(AE90="",_xlfn.CONCAT(O90,"_",Q90,"_",S90,"_",U90,"_",Y90,"_",AA90,"_",AB90,"_",AD90),_xlfn.CONCAT(O90,"_",Q90,"_",S90,"_",U90,"_",Y90,"_",AA90,"_",AB90,"_",AD90,".odm",AE90)),"NA") -> 0 | G90: =IF(I90="methods",IF(L90="measurement",IF(AE90="",_xlfn.CONCAT(K90,"_",M90,"_",O90,"_",Q90,"_",S90,"_",U90,"_",Y90,"_",AA90,"_",AB90,"_",AD90),_xlfn.CONCAT(K90,"_",M90,"_",O90,"_",Q90,"_",S90,"_",U90,"_",Y90,"_",AA90,"_",AB90,"_",AD90,".odm",AE90)),IF(AE90="",_xlfn.CONCAT(K90,"_",M90,"_",W90,"_",AD90),_xlfn.CONCAT(K90,"_",M90,"_",W90,"_",AD90,".odm",AE90))),"NA") -> 0 | H90: =IF(I90="attributes",IF(AE90="",_xlfn.CONCAT(K90,"_",AD90),_xlfn.CONCAT(K90,"_",AD90,".odm",AE90)),"NA") -> 0 | I90: attributes | J90: Protocols table Shorthand | K90: =IFERROR(VLOOKUP(J90,'wideName-Dropdowns'!$A:$B,2,FALSE),"") -> 0 | M90: =IFERROR(VLOOKUP(L90,'wideName-Dropdowns'!$C:$D,2,FALSE),"") -> 0 | O90: =IFERROR(VLOOKUP(N90,'wideName-Dropdowns'!$E:$F,2,FALSE),"") -> 0 | Q90: =IFERROR(VLOOKUP(P90,'wideName-Dropdowns'!$G:$H,2,FALSE),"") -> 0 | S90: =IFERROR(VLOOKUP(R90,'wideName-Dropdowns'!$I:$J,2,FALSE),"") -> 0 | U90: =IFERROR(VLOOKUP(T90,'wideName-Dropdowns'!$K:$L,2,FALSE),"") -> 0 | W90: =IFERROR(VLOOKUP(V90,'wideName-Dropdowns'!$M:$N,2,FALSE),"") -> 0 | Y90: =IFERROR(VLOOKUP(X90,'wideName-Dropdowns'!$O:$P,2,FALSE),"") -> 0 | AA90: =IFERROR(VLOOKUP(Z90,'wideName-Dropdowns'!$Q:$R,2,FALSE),"") -> 0 | AC90: Protocol ID | AD90: =IFERROR(VLOOKUP(AC90,'wideName-Dropdowns'!$S:$T,2,FALSE),"") -> 0
A91: =IF(I91="attributes",H91,IF(I91="measurements",F91,G91)) -> 0 | B91: protocol_protocolVersion | C91: =LEN(A91) -> 0 | D91: The version of a protocol. | E91: EU4S Data ODM wide Template | F91: =IF(I91="measurements",IF(AE91="",_xlfn.CONCAT(O91,"_",Q91,"_",S91,"_",U91,"_",Y91,"_",AA91,"_",AB91,"_",AD91),_xlfn.CONCAT(O91,"_",Q91,"_",S91,"_",U91,"_",Y91,"_",AA91,"_",AB91,"_",AD91,".odm",AE91)),"NA") -> 0 | G91: =IF(I91="methods",IF(L91="measurement",IF(AE91="",_xlfn.CONCAT(K91,"_",M91,"_",O91,"_",Q91,"_",S91,"_",U91,"_",Y91,"_",AA91,"_",AB91,"_",AD91),_xlfn.CONCAT(K91,"_",M91,"_",O91,"_",Q91,"_",S91,"_",U91,"_",Y91,"_",AA91,"_",AB91,"_",AD91,".odm",AE91)),IF(AE91="",_xlfn.CONCAT(K91,"_",M91,"_",W91,"_",AD91),_xlfn.CONCAT(K91,"_",M91,"_",W91,"_",AD91,".odm",AE91))),"NA") -> 0 | H91: =IF(I91="attributes",IF(AE91="",_xlfn.CONCAT(K91,"_",AD91),_xlfn.CONCAT(K91,"_",AD91,".odm",AE91)),"NA") -> 0 | I91: attributes | J91: Protocols table Shorthand | K91: =IFERROR(VLOOKUP(J91,'wideName-Dropdowns'!$A:$B,2,FALSE),"") -> 0 | M91: =IFERROR(VLOOKUP(L91,'wideName-Dropdowns'!$C:$D,2,FALSE),"") -> 0 | O91: =IFERROR(VLOOKUP(N91,'wideName-Dropdowns'!$E:$F,2,FALSE),"") -> 0 | Q91: =IFERROR(VLOOKUP(P91,'wideName-Dropdowns'!$G:$H,2,FALSE),"") -> 0 | S91: =IFERROR(VLOOKUP(R91,'wideName-Dropdowns'!$I:$J,2,FALSE),"") -> 0 | U91: =IFERROR(VLOOKUP(T91,'wideName-Dropdowns'!$K:$L,2,FALSE),"") -> 0 | W91: =IFERROR(VLOOKUP(V91,'wideName-Dropdowns'!$M:$N,2,FALSE),"") -> 0 | Y91: =IFERROR(VLOOKUP(X91,'wideName-Dropdowns'!$O:$P,2,FALSE),"") -> 0 | AA91: =IFERROR(VLOOKUP(Z91,'wideName-Dropdowns'!$Q:$R,2,FALSE),"") -> 0 | AC91: Protocol version | AD91: =IFERROR(VLOOKUP(AC91,'wideName-Dropdowns'!$S:$T,2,FALSE),"") -> 0
A92: =IF(I92="attributes",H92,IF(I92="measurements",F92,G92)) -> 0 | B92: qualityReports_notes | C92: =LEN(A92) -> 0 | D92: Any additional notes on a quality issue for a measure. | E92: EU4S Data ODM wide Template | F92: =IF(I92="measurements",IF(AE92="",_xlfn.CONCAT(O92,"_",Q92,"_",S92,"_",U92,"_",Y92,"_",AA92,"_",AB92,"_",AD92),_xlfn.CONCAT(O92,"_",Q92,"_",S92,"_",U92,"_",Y92,"_",AA92,"_",AB92,"_",AD92,".odm",AE92)),"NA") -> 0 | G92: =IF(I92="methods",IF(L92="measurement",IF(AE92="",_xlfn.CONCAT(K92,"_",M92,"_",O92,"_",Q92,"_",S92,"_",U92,"_",Y92,"_",AA92,"_",AB92,"_",AD92),_xlfn.CONCAT(K92,"_",M92,"_",O92,"_",Q92,"_",S92,"_",U92,"_",Y92,"_",AA92,"_",AB92,"_",AD92,".odm",AE92)),IF(AE92="",_xlfn.CONCAT(K92,"_",M92,"_",W92,"_",AD92),_xlfn.CONCAT(K92,"_",M92,"_",W92,"_",AD92,".odm",AE92))),"NA") -> 0 | H92: =IF(I92="attributes",IF(AE92="",_xlfn.CONCAT(K92,"_",AD92),_xlfn.CONCAT(K92,"_",AD92,".odm",AE92)),"NA") -> 0 | I92: attributes | J92: Quality reports table Shorthand | K92: =IFERROR(VLOOKUP(J92,'wideName-Dropdowns'!$A:$B,2,FALSE),"") -> 0 | M92: =IFERROR(VLOOKUP(L92,'wideName-Dropdowns'!$C:$D,2,FALSE),"") -> 0 | O92: =IFERROR(VLOOKUP(N92,'wideName-Dropdowns'!$E:$F,2,FALSE),"") -> 0 | Q92: =IFERROR(VLOOKUP(P92,'wideName-Dropdowns'!$G:$H,2,FALSE),"") -> 0 | S92: =IFERROR(VLOOKUP(R92,'wideName-Dropdowns'!$I:$J,2,FALSE),"") -> 0 | U92: =IFERROR(VLOOKUP(T92,'wideName-Dropdowns'!$K:$L,2,FALSE),"") -> 0 | W92: =IFERROR(VLOOKUP(V92,'wideName-Dropdowns'!$M:$N,2,FALSE),"") -> 0 | Y92: =IFERROR(VLOOKUP(X92,'wideName-Dropdowns'!$O:$P,2,FALSE),"") -> 0 | AA92: =IFERROR(VLOOKUP(Z92,'wideName-Dropdowns'!$Q:$R,2,FALSE),"") -> 0 | AC92: Notes | AD92: =IFERROR(VLOOKUP(AC92,'wideName-Dropdowns'!$S:$T,2,FALSE),"") -> 0
A93: =IF(I93="attributes",H93,IF(I93="measurements",F93,G93)) -> 0 | B93: qualityReports_qualityFlag | C93: =LEN(A93) -> 0 | D93: A quality indicator for a measure. | E93: EU4S Data ODM wide Template | F93: =IF(I93="measurements",IF(AE93="",_xlfn.CONCAT(O93,"_",Q93,"_",S93,"_",U93,"_",Y93,"_",AA93,"_",AB93,"_",AD93),_xlfn.CONCAT(O93,"_",Q93,"_",S93,"_",U93,"_",Y93,"_",AA93,"_",AB93,"_",AD93,".odm",AE93)),"NA") -> 0 | G93: =IF(I93="methods",IF(L93="measurement",IF(AE93="",_xlfn.CONCAT(K93,"_",M93,"_",O93,"_",Q93,"_",S93,"_",U93,"_",Y93,"_",AA93,"_",AB93,"_",AD93),_xlfn.CONCAT(K93,"_",M93,"_",O93,"_",Q93,"_",S93,"_",U93,"_",Y93,"_",AA93,"_",AB93,"_",AD93,".odm",AE93)),IF(AE93="",_xlfn.CONCAT(K93,"_",M93,"_",W93,"_",AD93),_xlfn.CONCAT(K93,"_",M93,"_",W93,"_",AD93,".odm",AE93))),"NA") -> 0 | H93: =IF(I93="attributes",IF(AE93="",_xlfn.CONCAT(K93,"_",AD93),_xlfn.CONCAT(K93,"_",AD93,".odm",AE93)),"NA") -> 0 | I93: attributes | J93: Quality reports table Shorthand | K93: =IFERROR(VLOOKUP(J93,'wideName-Dropdowns'!$A:$B,2,FALSE),"") -> 0 | M93: =IFERROR(VLOOKUP(L93,'wideName-Dropdowns'!$C:$D,2,FALSE),"") -> 0 | O93: =IFERROR(VLOOKUP(N93,'wideName-Dropdowns'!$E:$F,2,FALSE),"") -> 0 | Q93: =IFERROR(VLOOKUP(P93,'wideName-Dropdowns'!$G:$H,2,FALSE),"") -> 0 | S93: =IFERROR(VLOOKUP(R93,'wideName-Dropdowns'!$I:$J,2,FALSE),"") -> 0 | U93: =IFERROR(VLOOKUP(T93,'wideName-Dropdowns'!$K:$L,2,FALSE),"") -> 0 | W93: =IFERROR(VLOOKUP(V93,'wideName-Dropdowns'!$M:$N,2,FALSE),"") -> 0 | Y93: =IFERROR(VLOOKUP(X93,'wideName-Dropdowns'!$O:$P,2,FALSE),"") -> 0 | AA93: =IFERROR(VLOOKUP(Z93,'wideName-Dropdowns'!$Q:$R,2,FALSE),"") -> 0 | AC93: Quality flag | AD93: =IFERROR(VLOOKUP(AC93,'wideName-Dropdowns'!$S:$T,2,FALSE),"") -> 0
A94: in_2_AND_name_insType__flowmeter_ | B94: instrument_name_flowmeter | C94: =LEN(A94) -> 0 | D94: The name of the flow meter. | E94: EU4S Data ODM wide Template | F94: =IF(I94="measurements",IF(AE94="",_xlfn.CONCAT(O94,"_",Q94,"_",S94,"_",U94,"_",Y94,"_",AA94,"_",AB94,"_",AD94),_xlfn.CONCAT(O94,"_",Q94,"_",S94,"_",U94,"_",Y94,"_",AA94,"_",AB94,"_",AD94,".odm",AE94)),"NA") -> 0 | G94: =IF(I94="methods",IF(L94="measurement",IF(AE94="",_xlfn.CONCAT(K94,"_",M94,"_",O94,"_",Q94,"_",S94,"_",U94,"_",Y94,"_",AA94,"_",AB94,"_",AD94),_xlfn.CONCAT(K94,"_",M94,"_",O94,"_",Q94,"_",S94,"_",U94,"_",Y94,"_",AA94,"_",AB94,"_",AD94,".odm",AE94)),IF(AE94="",_xlfn.CONCAT(K94,"_",M94,"_",W94,"_",AD94),_xlfn.CONCAT(K94,"_",M94,"_",W94,"_",AD94,".odm",AE94))),"NA") -> 0 | H94: =IF(I94="attributes",IF(AE94="",_xlfn.CONCAT(K94,"_",AD94),_xlfn.CONCAT(K94,"_",AD94,".odm",AE94)),"NA") -> 0 | I94: exceptions | K94: =IFERROR(VLOOKUP(J94,'wideName-Dropdowns'!$A:$B,2,FALSE),"") -> 0 | M94: =IFERROR(VLOOKUP(L94,'wideName-Dropdowns'!$C:$D,2,FALSE),"") -> 0 | O94: =IFERROR(VLOOKUP(N94,'wideName-Dropdowns'!$E:$F,2,FALSE),"") -> 0 | Q94: =IFERROR(VLOOKUP(P94,'wideName-Dropdowns'!$G:$H,2,FALSE),"") -> 0 | S94: =IFERROR(VLOOKUP(R94,'wideName-Dropdowns'!$I:$J,2,FALSE),"") -> 0 | U94: =IFERROR(VLOOKUP(T94,'wideName-Dropdowns'!$K:$L,2,FALSE),"") -> 0 | W94: =IFERROR(VLOOKUP(V94,'wideName-Dropdowns'!$M:$N,2,FALSE),"") -> 0 | Y94: =IFERROR(VLOOKUP(X94,'wideName-Dropdowns'!$O:$P,2,FALSE),"") -> 0 | AA94: =IFERROR(VLOOKUP(Z94,'wideName-Dropdowns'!$Q:$R,2,FALSE),"") -> 0 | AD94: =IFERROR(VLOOKUP(AC94,'wideName-Dropdowns'!$S:$T,2,FALSE),"") -> 0
A95: in_2_AND_name_insType__sampler_ | B95: instrument_name_sampler | C95: =LEN(A95) -> 0 | D95: The name of the sampler. | E95: EU4S Data ODM wide Template | F95: =IF(I95="measurements",IF(AE95="",_xlfn.CONCAT(O95,"_",Q95,"_",S95,"_",U95,"_",Y95,"_",AA95,"_",AB95,"_",AD95),_xlfn.CONCAT(O95,"_",Q95,"_",S95,"_",U95,"_",Y95,"_",AA95,"_",AB95,"_",AD95,".odm",AE95)),"NA") -> 0 | G95: =IF(I95="methods",IF(L95="measurement",IF(AE95="",_xlfn.CONCAT(K95,"_",M95,"_",O95,"_",Q95,"_",S95,"_",U95,"_",Y95,"_",AA95,"_",AB95,"_",AD95),_xlfn.CONCAT(K95,"_",M95,"_",O95,"_",Q95,"_",S95,"_",U95,"_",Y95,"_",AA95,"_",AB95,"_",AD95,".odm",AE95)),IF(AE95="",_xlfn.CONCAT(K95,"_",M95,"_",W95,"_",AD95),_xlfn.CONCAT(K95,"_",M95,"_",W95,"_",AD95,".odm",AE95))),"NA") -> 0 | H95: =IF(I95="attributes",IF(AE95="",_xlfn.CONCAT(K95,"_",AD95),_xlfn.CONCAT(K95,"_",AD95,".odm",AE95)),"NA") -> 0 | I95: exceptions | K95: =IFERROR(VLOOKUP(J95,'wideName-Dropdowns'!$A:$B,2,FALSE),"") -> 0 | M95: =IFERROR(VLOOKUP(L95,'wideName-Dropdowns'!$C:$D,2,FALSE),"") -> 0 | O95: =IFERROR(VLOOKUP(N95,'wideName-Dropdowns'!$E:$F,2,FALSE),"") -> 0 | Q95: =IFERROR(VLOOKUP(P95,'wideName-Dropdowns'!$G:$H,2,FALSE),"") -> 0 | S95: =IFERROR(VLOOKUP(R95,'wideName-Dropdowns'!$I:$J,2,FALSE),"") -> 0 | U95: =IFERROR(VLOOKUP(T95,'wideName-Dropdowns'!$K:$L,2,FALSE),"") -> 0 | W95: =IFERROR(VLOOKUP(V95,'wideName-Dropdowns'!$M:$N,2,FALSE),"") -> 0 | Y95: =IFERROR(VLOOKUP(X95,'wideName-Dropdowns'!$O:$P,2,FALSE),"") -> 0 | AA95: =IFERROR(VLOOKUP(Z95,'wideName-Dropdowns'!$Q:$R,2,FALSE),"") -> 0 | AD95: =IFERROR(VLOOKUP(AC95,'wideName-Dropdowns'!$S:$T,2,FALSE),"") -> 0
